Workbook

Sheet INDEX
C2: Group No. | D2: Parag Milk Foods Limited
C4: Details of group members
C5: Name | D5: ID
C6: Adya Srivastava | D6: 2022A3PS0467P
C7: Priyan Hemil Mody | D7: 2020B3AA1964P
C8: Shreeram Petkar | D8: 2020B3A21966P
B13: Index
B14: Question
B15: I (a) | C15: Historical Data Daily
B16: I (a) | C16: Historical Data Monthly
B17: I (a) | C17: NIFTY 50
B18: I (a) | C18: Descriptive Stats
B19: I (a) | C19: Technical Analysis
B20: I (b) | C20: Balance Sheet
B21: I (b) | C21: Income Statement
B22: I (b) | C22: Ratio Analysis
B23: I (b) | C23: Company Stock Analysis
B24: II. | C24: Portfolio Analysis

Sheet Historical Data Daily
A1: Date | B1: Open | C1: High | D1: Low | E1: Close | F1: Adj Close | G1: Volume | H1: Normalised Volume | I1: HPR | J1: HPY | K1: Daily Range | L1: Normalised Daily Range | M1: CHG% | N1: Normalised CHG% | O1: CHG % of NIFTY 50 | P1: News Event | U1: 3 Year Bond Yield
A2: 44287 | B2: 106.5 | C2: 112 | D2: 105.95 | E2: 111.45 | F2: 111.03085 | G2: 1193557 | H2: =(G2-'Descriptive Stats'!$B$55)/('Descriptive Stats'!$B$56-'Descriptive Stats'!$B$55) -> 0.063914066 | K2: =C2-D2 -> 6.050003 | L2: =(K2-'Descriptive Stats'!$B$60)/('Descriptive Stats'!$B$61-'Descriptive Stats'!$B$60) -> 0.14804083 | Q2: 0 | U2: Date | V2: Price | W2: Open | X2: High | Y2: Low
A3: 44291 | B3: 114.05 | C3: 116.8 | D3: 107.5 | E3: 115.75 | F3: 115.31468 | G3: 3656668 | H3: =(G3-'Descriptive Stats'!$B$55)/('Descriptive Stats'!$B$56-'Descriptive Stats'!$B$55) -> 0.20247065 | I3: =E3/E2 -> 1.0385824 | J3: =I3-1 -> 0.038582352 | K3: =C3-D3 -> 9.300003 | L3: =(K3-'Descriptive Stats'!$B$60)/('Descriptive Stats'!$B$61-'Descriptive Stats'!$B$60) -> 0.24238046 | M3: =((E3-E2)/E2)*100 -> 3.8582352 | N3: =(M3-'Descriptive Stats'!$B$65)/('Descriptive Stats'!$B$66-'Descriptive Stats'!$B$65) -> 0.53400733 | O3: =((G3-G2)/G2)*100 -> 206.36727 | Q3: 0 | U3: 28/03/24 | V3: 7.052 | W3: 7.031 | X3: 7.055 | Y3: 7.031
A4: 44292 | B4: 115.8 | C4: 118.25 | D4: 112.4 | E4: 115.7 | F4: 115.26487 | G4: 1243382 | H4: =(G4-'Descriptive Stats'!$B$55)/('Descriptive Stats'!$B$56-'Descriptive Stats'!$B$55) -> 0.066716855 | I4: =E4/E3 -> 0.99956801 | J4: =I4-1 -> -0.00043199136 | K4: =C4-D4 -> 5.849998 | L4: =(K4-'Descriptive Stats'!$B$60)/('Descriptive Stats'!$B$61-'Descriptive Stats'!$B$60) -> 0.14223516 | M4: =((E4-E3)/E3)*100 -> -0.043199136 | N4: =(M4-'Descriptive Stats'!$B$65)/('Descriptive Stats'!$B$66-'Descriptive Stats'!$B$65) -> 0.38735158 | O4: =((G4-G3)/G3)*100 -> -65.996858 | Q4: 0 | U4: 27/03/24 | V4: 7.072 | W4: 7.097 | X4: 7.097 | Y4: 7.067
A5: 44293 | B5: 116.45 | C5: 118.05 | D5: 114.5 | E5: 114.9 | F5: 114.46788 | G5: 636056 | H5: =(G5-'Descriptive Stats'!$B$55)/('Descriptive Stats'!$B$56-'Descriptive Stats'!$B$55) -> 0.032553142 | I5: =E5/E4 -> 0.99308561 | J5: =I5-1 -> -0.0069143908 | K5: =C5-D5 -> 3.550003 | L5: =(K5-'Descriptive Stats'!$B$60)/('Descriptive Stats'!$B$61-'Descriptive Stats'!$B$60) -> 0.075471879 | M5: =((E5-E4)/E4)*100 -> -0.69143908 | N5: =(M5-'Descriptive Stats'!$B$65)/('Descriptive Stats'!$B$66-'Descriptive Stats'!$B$65) -> 0.3629841 | O5: =((G5-G4)/G4)*100 -> -48.844683 | Q5: 0 | U5: 26/03/24 | V5: 7.089 | W5: 7.091 | X5: 7.1 | Y5: 7.079
A6: 44294 | B6: 115.85 | C6: 118.2 | D6: 115 | E6: 116.15 | F6: 115.71318 | G6: 1332806 | H6: =(G6-'Descriptive Stats'!$B$55)/('Descriptive Stats'!$B$56-'Descriptive Stats'!$B$55) -> 0.071747195 | I6: =E6/E5 -> 1.010879 | J6: =I6-1 -> 0.010879025 | K6: =C6-D6 -> 3.199997 | L6: =(K6-'Descriptive Stats'!$B$60)/('Descriptive Stats'!$B$61-'Descriptive Stats'!$B$60) -> 0.065312052 | M6: =((E6-E5)/E5)*100 -> 1.0879025 | N6: =(M6-'Descriptive Stats'!$B$65)/('Descriptive Stats'!$B$66-'Descriptive Stats'!$B$65) -> 0.42986993 | O6: =((G6-G5)/G5)*100 -> 109.54224 | Q6: 0 | U6: 22/03/24 | V6: 7.087 | W6: 7.062 | X6: 7.096 | Y6: 7.055
A7: 44295 | B7: 116 | C7: 121.25 | D7: 115.05 | E7: 116.45 | F7: 116.01205 | G7: 1552030 | H7: =(G7-'Descriptive Stats'!$B$55)/('Descriptive Stats'!$B$56-'Descriptive Stats'!$B$55) -> 0.084079131 | I7: =E7/E6 -> 1.0025828 | J7: =I7-1 -> 0.0025828239 | K7: =C7-D7 -> 6.199997 | L7: =(K7-'Descriptive Stats'!$B$60)/('Descriptive Stats'!$B$61-'Descriptive Stats'!$B$60) -> 0.15239479 | M7: =((E7-E6)/E6)*100 -> 0.25828239 | N7: =(M7-'Descriptive Stats'!$B$65)/('Descriptive Stats'!$B$66-'Descriptive Stats'!$B$65) -> 0.39868433 | O7: =((G7-G6)/G6)*100 -> 16.448305 | Q7: 0 | U7: 21/03/24 | V7: 7.05 | W7: 7.08 | X7: 7.08 | Y7: 7.048
A8: 44298 | B8: 113.5 | C8: 114 | D8: 102 | E8: 104.4 | F8: 104.00737 | G8: 1241621 | H8: =(G8-'Descriptive Stats'!$B$55)/('Descriptive Stats'!$B$56-'Descriptive Stats'!$B$55) -> 0.066617794 | I8: =E8/E7 -> 0.89652215 | J8: =I8-1 -> -0.10347785 | K8: =C8-D8 -> 12 | L8: =(K8-'Descriptive Stats'!$B$60)/('Descriptive Stats'!$B$61-'Descriptive Stats'!$B$60) -> 0.32075483 | M8: =((E8-E7)/E7)*100 -> -10.347785 | N8: =(M8-'Descriptive Stats'!$B$65)/('Descriptive Stats'!$B$66-'Descriptive Stats'!$B$65) -> 0 | O8: =((G8-G7)/G7)*100 -> -20.000193 | Q8: 0 | U8: 20/03/24 | V8: 7.097 | W8: 7.101 | X8: 7.103 | Y8: 7.089
A9: 44299 | B9: 105.05 | C9: 111 | D9: 105.05 | E9: 109.2 | F9: 108.78931 | G9: 1016289 | H9: =(G9-'Descriptive Stats'!$B$55)/('Descriptive Stats'!$B$56-'Descriptive Stats'!$B$55) -> 0.053942266 | I9: =E9/E8 -> 1.045977 | J9: =I9-1 -> 0.045976963 | K9: =C9-D9 -> 5.949997 | L9: =(K9-'Descriptive Stats'!$B$60)/('Descriptive Stats'!$B$61-'Descriptive Stats'!$B$60) -> 0.14513789 | M9: =((E9-E8)/E8)*100 -> 4.5976963 | N9: =(M9-'Descriptive Stats'!$B$65)/('Descriptive Stats'!$B$66-'Descriptive Stats'!$B$65) -> 0.56180383 | O9: =((G9-G8)/G8)*100 -> -18.148211 | Q9: 0 | U9: 19/03/24 | V9: 7.095 | W9: 7.096 | X9: 7.1 | Y9: 7.081
A10: 44301 | B10: 108.15 | C10: 109.95 | D10: 104.7 | E10: 107.1 | F10: 106.69721 | G10: 388528 | H10: =(G10-'Descriptive Stats'!$B$55)/('Descriptive Stats'!$B$56-'Descriptive Stats'!$B$55) -> 0.01862903 | I10: =E10/E9 -> 0.98076924 | J10: =I10-1 -> -0.019230761 | K10: =C10-D10 -> 5.25 | L10: =(K10-'Descriptive Stats'!$B$60)/('Descriptive Stats'!$B$61-'Descriptive Stats'!$B$60) -> 0.12481868 | M10: =((E10-E9)/E9)*100 -> -1.9230761 | N10: =(M10-'Descriptive Stats'!$B$65)/('Descriptive Stats'!$B$66-'Descriptive Stats'!$B$65) -> 0.3166866 | O10: =((G10-G9)/G9)*100 -> -61.76993 | Q10: 0 | U10: 18/03/24 | V10: 7.087 | W10: 7.08 | X10: 7.088 | Y10: 7.075
A11: 44302 | B11: 107.9 | C11: 114.7 | D11: 106.8 | E11: 112.3 | F11: 111.87766 | G11: 1006186 | H11: =(G11-'Descriptive Stats'!$B$55)/('Descriptive Stats'!$B$56-'Descriptive Stats'!$B$55) -> 0.053373946 | I11: =E11/E10 -> 1.0485528 | J11: =I11-1 -> 0.048552802 | K11: =C11-D11 -> 7.899994 | L11: =(K11-'Descriptive Stats'!$B$60)/('Descriptive Stats'!$B$61-'Descriptive Stats'!$B$60) -> 0.20174159 | M11: =((E11-E10)/E10)*100 -> 4.8552802 | N11: =(M11-'Descriptive Stats'!$B$65)/('Descriptive Stats'!$B$66-'Descriptive Stats'!$B$65) -> 0.57148646 | O11: =((G11-G10)/G10)*100 -> 158.97387 | Q11: 0 | U11: 15/03/24 | V11: 7.062 | W11: 7.06 | X11: 7.064 | Y11: 7.051
A12: 44305 | B12: 108.9 | C12: 110.1 | D12: 106.2 | E12: 108.55 | F12: 108.14177 | G12: 448582 | H12: =(G12-'Descriptive Stats'!$B$55)/('Descriptive Stats'!$B$56-'Descriptive Stats'!$B$55) -> 0.022007228 | I12: =E12/E11 -> 0.9666073 | J12: =I12-1 -> -0.033392697 | K12: =C12-D12 -> 3.900001 | L12: =(K12-'Descriptive Stats'!$B$60)/('Descriptive Stats'!$B$61-'Descriptive Stats'!$B$60) -> 0.085631473 | M12: =((E12-E11)/E11)*100 -> -3.3392697 | N12: =(M12-'Descriptive Stats'!$B$65)/('Descriptive Stats'!$B$66-'Descriptive Stats'!$B$65) -> 0.26345158 | O12: =((G12-G11)/G11)*100 -> -55.417587 | Q12: 0 | R12: Smoothing factor for 12 | S12: =2/13 -> 0.15384615 | U12: 14/03/24 | V12: 7.041 | W12: 7.046 | X12: 7.048 | Y12: 7.038
A13: 44306 | B13: 109.15 | C13: 111.7 | D13: 105.9 | E13: 106.9 | F13: 106.49797 | G13: 279311 | H13: =(G13-'Descriptive Stats'!$B$55)/('Descriptive Stats'!$B$56-'Descriptive Stats'!$B$55) -> 0.012485281 | I13: =E13/E12 -> 0.98479962 | J13: =I13-1 -> -0.015200377 | K13: =C13-D13 -> 5.799995 | L13: =(K13-'Descriptive Stats'!$B$60)/('Descriptive Stats'!$B$61-'Descriptive Stats'!$B$60) -> 0.1407837 | M13: =((E13-E12)/E12)*100 -> -1.5200377 | N13: =(M13-'Descriptive Stats'!$B$65)/('Descriptive Stats'!$B$66-'Descriptive Stats'!$B$65) -> 0.3318369 | O13: =((G13-G12)/G12)*100 -> -37.734684 | Q13: 0 | R13: Smoothing factor for 26 | S13: =2/27 -> 0.074074074 | U13: 13/03/24 | V13: 7.039 | W13: 7.043 | X13: 7.043 | Y13: 7.03
A14: 44308 | B14: 106.9 | C14: 109.75 | D14: 105.1 | E14: 106.8 | F14: 106.39835 | G14: 319736 | H14: =(G14-'Descriptive Stats'!$B$55)/('Descriptive Stats'!$B$56-'Descriptive Stats'!$B$55) -> 0.014759296 | I14: =E14/E13 -> 0.99906456 | J14: =I14-1 -> -0.00093544432 | K14: =C14-D14 -> 4.650002 | L14: =(K14-'Descriptive Stats'!$B$60)/('Descriptive Stats'!$B$61-'Descriptive Stats'!$B$60) -> 0.10740219 | M14: =((E14-E13)/E13)*100 -> -0.093544432 | N14: =(M14-'Descriptive Stats'!$B$65)/('Descriptive Stats'!$B$66-'Descriptive Stats'!$B$65) -> 0.38545909 | O14: =((G14-G13)/G13)*100 -> 14.473114 | Q14: 0 | R14: Smoothing factor 9 | S14: =2/10 -> 0.2 | U14: 45629 | V14: 7.026 | W14: 7.025 | X14: 7.029 | Y14: 7.015
A15: 44309 | B15: 107.45 | C15: 115.5 | D15: 106.9 | E15: 111.75 | F15: 111.32973 | G15: 1058052 | H15: =(G15-'Descriptive Stats'!$B$55)/('Descriptive Stats'!$B$56-'Descriptive Stats'!$B$55) -> 0.056291547 | I15: =E15/E14 -> 1.0463483 | J15: =I15-1 -> 0.046348285 | K15: =C15-D15 -> 8.599998 | L15: =(K15-'Descriptive Stats'!$B$60)/('Descriptive Stats'!$B$61-'Descriptive Stats'!$B$60) -> 0.22206101 | M15: =((E15-E14)/E14)*100 -> 4.6348285 | N15: =(M15-'Descriptive Stats'!$B$65)/('Descriptive Stats'!$B$66-'Descriptive Stats'!$B$65) -> 0.56319964 | O15: =((G15-G14)/G14)*100 -> 230.91425 | Q15: 0 | U15: 45599 | V15: 7.014 | W15: 7.025 | X15: 7.025 | Y15: 7.006
A16: 44312 | B16: 112.45 | C16: 114.9 | D16: 111.05 | E16: 114.3 | F16: 113.87014 | G16: 525753 | H16: =(G16-'Descriptive Stats'!$B$55)/('Descriptive Stats'!$B$56-'Descriptive Stats'!$B$55) -> 0.026348304 | I16: =E16/E15 -> 1.0228188 | J16: =I16-1 -> 0.022818819 | K16: =C16-D16 -> 3.849999 | L16: =(K16-'Descriptive Stats'!$B$60)/('Descriptive Stats'!$B$61-'Descriptive Stats'!$B$60) -> 0.084180036 | M16: =((E16-E15)/E15)*100 -> 2.2818819 | N16: =(M16-'Descriptive Stats'!$B$65)/('Descriptive Stats'!$B$66-'Descriptive Stats'!$B$65) -> 0.47475187 | O16: =((G16-G15)/G15)*100 -> -50.309342 | Q16: 0 | U16: 45476 | V16: 7.031 | W16: 7.054 | X16: 7.054 | Y16: 7.026
A17: 44313 | B17: 115 | C17: 115.65 | D17: 111 | E17: 111.9 | F17: 111.47916 | G17: 425358 | H17: =(G17-'Descriptive Stats'!$B$55)/('Descriptive Stats'!$B$56-'Descriptive Stats'!$B$55) -> 0.020700816 | I17: =E17/E16 -> 0.97900262 | J17: =I17-1 -> -0.020997384 | K17: =C17-D17 -> 4.650002 | L17: =(K17-'Descriptive Stats'!$B$60)/('Descriptive Stats'!$B$61-'Descriptive Stats'!$B$60) -> 0.10740219 | M17: =((E17-E16)/E16)*100 -> -2.0997384 | N17: =(M17-'Descriptive Stats'!$B$65)/('Descriptive Stats'!$B$66-'Descriptive Stats'!$B$65) -> 0.31004583 | O17: =((G17-G16)/G16)*100 -> -19.095469 | Q17: 0 | U17: 45446 | V17: 7.054 | W17: 7.053 | X17: 7.057 | Y17: 7.048
A18: 44314 | B18: 113.3 | C18: 115.6 | D18: 112.3 | E18: 114.15 | F18: 113.7207 | G18: 576458 | H18: =(G18-'Descriptive Stats'!$B$55)/('Descriptive Stats'!$B$56-'Descriptive Stats'!$B$55) -> 0.029200595 | I18: =E18/E17 -> 1.0201072 | J18: =I18-1 -> 0.020107238 | K18: =C18-D18 -> 3.299995 | L18: =(K18-'Descriptive Stats'!$B$60)/('Descriptive Stats'!$B$61-'Descriptive Stats'!$B$60) -> 0.068214752 | M18: =((E18-E17)/E17)*100 -> 2.0107238 | N18: =(M18-'Descriptive Stats'!$B$65)/('Descriptive Stats'!$B$66-'Descriptive Stats'!$B$65) -> 0.46455898 | O18: =((G18-G17)/G17)*100 -> 35.523018 | Q18: 0 | U18: 45415 | V18: 7.057 | W18: 7.066 | X18: 7.066 | Y18: 7.053
A19: 44315 | B19: 115 | C19: 115.45 | D19: 110.9 | E19: 112.05 | F19: 111.6286 | G19: 409072 | H19: =(G19-'Descriptive Stats'!$B$55)/('Descriptive Stats'!$B$56-'Descriptive Stats'!$B$55) -> 0.019784685 | I19: =E19/E18 -> 0.98160316 | J19: =I19-1 -> -0.018396837 | K19: =C19-D19 -> 4.549995 | L19: =(K19-'Descriptive Stats'!$B$60)/('Descriptive Stats'!$B$61-'Descriptive Stats'!$B$60) -> 0.10449923 | M19: =((E19-E18)/E18)*100 -> -1.8396837 | N19: =(M19-'Descriptive Stats'!$B$65)/('Descriptive Stats'!$B$66-'Descriptive Stats'!$B$65) -> 0.31982134 | O19: =((G19-G18)/G18)*100 -> -29.036981 | Q19: 0 | U19: 45385 | V19: 7.06 | W19: 7.051 | X19: 7.062 | Y19: 7.047
A20: 44316 | B20: 111 | C20: 116.6 | D20: 111 | E20: 111.7 | F20: 111.27992 | G20: 707041 | H20: =(G20-'Descriptive Stats'!$B$55)/('Descriptive Stats'!$B$56-'Descriptive Stats'!$B$55) -> 0.036546239 | I20: =E20/E19 -> 0.99687634 | J20: =I20-1 -> -0.003123659 | K20: =C20-D20 -> 5.599998 | L20: =(K20-'Descriptive Stats'!$B$60)/('Descriptive Stats'!$B$61-'Descriptive Stats'!$B$60) -> 0.13497827 | M20: =((E20-E19)/E19)*100 -> -0.3123659 | N20: =(M20-'Descriptive Stats'!$B$65)/('Descriptive Stats'!$B$66-'Descriptive Stats'!$B$65) -> 0.37723354 | O20: =((G20-G19)/G19)*100 -> 72.840233 | Q20: 0 | U20: 45294 | V20: 7.06 | W20: 7.062 | X20: 7.082 | Y20: 7.057
A21: 44319 | B21: 111.05 | C21: 115.5 | D21: 111.05 | E21: 113.95 | F21: 113.52145 | G21: 404637 | H21: =(G21-'Descriptive Stats'!$B$55)/('Descriptive Stats'!$B$56-'Descriptive Stats'!$B$55) -> 0.019535204 | I21: =E21/E20 -> 1.0201432 | J21: =I21-1 -> 0.020143241 | K21: =C21-D21 -> 4.449997 | L21: =(K21-'Descriptive Stats'!$B$60)/('Descriptive Stats'!$B$61-'Descriptive Stats'!$B$60) -> 0.10159653 | M21: =((E21-E20)/E20)*100 -> 2.0143241 | N21: =(M21-'Descriptive Stats'!$B$65)/('Descriptive Stats'!$B$66-'Descriptive Stats'!$B$65) -> 0.46469432 | O21: =((G21-G20)/G20)*100 -> -42.770363 | Q21: 0 | U21: 29/02/24 | V21: 7.078 | W21: 7.059 | X21: 7.082 | Y21: 7.057
A22: 44320 | B22: 114.5 | C22: 118.6 | D22: 114.05 | E22: 115.35 | F22: 114.91619 | G22: 1164324 | H22: =(G22-'Descriptive Stats'!$B$55)/('Descriptive Stats'!$B$56-'Descriptive Stats'!$B$55) -> 0.062269631 | I22: =E22/E21 -> 1.0122861 | J22: =I22-1 -> 0.012286099 | K22: =C22-D22 -> 4.549995 | L22: =(K22-'Descriptive Stats'!$B$60)/('Descriptive Stats'!$B$61-'Descriptive Stats'!$B$60) -> 0.10449923 | M22: =((E22-E21)/E21)*100 -> 1.2286099 | N22: =(M22-'Descriptive Stats'!$B$65)/('Descriptive Stats'!$B$66-'Descriptive Stats'!$B$65) -> 0.43515915 | O22: =((G22-G21)/G21)*100 -> 187.74531 | Q22: 0 | U22: 28/02/24 | V22: 7.065 | W22: 7.076 | X22: 7.076 | Y22: 7.06
A23: 44321 | B23: 115.7 | C23: 137 | D23: 115.55 | E23: 134.10001 | F23: 133.59569 | G23: 9274147 | H23: =(G23-'Descriptive Stats'!$B$55)/('Descriptive Stats'!$B$56-'Descriptive Stats'!$B$55) -> 0.51846888 | I23: =E23/E22 -> 1.1625488 | J23: =I23-1 -> 0.16254884 | K23: =C23-D23 -> 21.449997 | L23: =(K23-'Descriptive Stats'!$B$60)/('Descriptive Stats'!$B$61-'Descriptive Stats'!$B$60) -> 0.59506536 | M23: =((E23-E22)/E22)*100 -> 16.254884 | N23: =(M23-'Descriptive Stats'!$B$65)/('Descriptive Stats'!$B$66-'Descriptive Stats'!$B$65) -> 1 | O23: =((G23-G22)/G22)*100 -> 696.52631 | Q23: 0 | U23: 27/02/24 | V23: 7.068 | W23: 7.074 | X23: 7.074 | Y23: 7.061
A24: 44322 | B24: 137.5 | C24: 143.8 | D24: 132.2 | E24: 138.89999 | F24: 138.37761 | G24: 6033249 | H24: =(G24-'Descriptive Stats'!$B$55)/('Descriptive Stats'!$B$56-'Descriptive Stats'!$B$55) -> 0.33615969 | I24: =E24/E23 -> 1.0357941 | J24: =I24-1 -> 0.035794092 | K24: =C24-D24 -> 11.600006 | L24: =(K24-'Descriptive Stats'!$B$60)/('Descriptive Stats'!$B$61-'Descriptive Stats'!$B$60) -> 0.30914397 | M24: =((E24-E23)/E23)*100 -> 3.5794092 | N24: =(M24-'Descriptive Stats'!$B$65)/('Descriptive Stats'!$B$66-'Descriptive Stats'!$B$65) -> 0.5235262 | O24: =((G24-G23)/G23)*100 -> -34.94551 | Q24: 0 | U24: 26/02/24 | V24: 7.063 | W24: 7.055 | X24: 7.066 | Y24: 7.046
A25: 44323 | B25: 139.85001 | C25: 141.75 | D25: 134.60001 | E25: 135.5 | F25: 134.9904 | G25: 1282935 | H25: =(G25-'Descriptive Stats'!$B$55)/('Descriptive Stats'!$B$56-'Descriptive Stats'!$B$55) -> 0.068941817 | I25: =E25/E24 -> 0.975522 | J25: =I25-1 -> -0.024478 | K25: =C25-D25 -> 7.149994 | L25: =(K25-'Descriptive Stats'!$B$60)/('Descriptive Stats'!$B$61-'Descriptive Stats'!$B$60) -> 0.1799709 | M25: =((E25-E24)/E24)*100 -> -2.4478 | N25: =(M25-'Descriptive Stats'!$B$65)/('Descriptive Stats'!$B$66-'Descriptive Stats'!$B$65) -> 0.29696212 | O25: =((G25-G24)/G24)*100 -> -78.735587 | Q25: 0 | U25: 23/02/24 | V25: 7.077 | W25: 7.074 | X25: 7.081 | Y25: 7.062
A26: 44326 | B26: 139 | C26: 140.5 | D26: 135.60001 | E26: 137.75 | F26: 137.23195 | G26: 1021520 | H26: =(G26-'Descriptive Stats'!$B$55)/('Descriptive Stats'!$B$56-'Descriptive Stats'!$B$55) -> 0.054236524 | I26: =E26/E25 -> 1.0166052 | J26: =I26-1 -> 0.016605166 | K26: =C26-D26 -> 4.899994 | L26: =(K26-'Descriptive Stats'!$B$60)/('Descriptive Stats'!$B$61-'Descriptive Stats'!$B$60) -> 0.11465885 | M26: =((E26-E25)/E25)*100 -> 1.6605166 | N26: =(M26-'Descriptive Stats'!$B$65)/('Descriptive Stats'!$B$66-'Descriptive Stats'!$B$65) -> 0.45139462 | O26: =((G26-G25)/G25)*100 -> -20.376325 | Q26: 0 | U26: 22/02/24 | V26: 7.062 | W26: 7.062 | X26: 7.076 | Y26: 7.045
A27: 44327 | B27: 135 | C27: 150.60001 | D27: 132.60001 | E27: 146.60001 | F27: 146.04868 | G27: 3087135 | H27: =(G27-'Descriptive Stats'!$B$55)/('Descriptive Stats'!$B$56-'Descriptive Stats'!$B$55) -> 0.1704329 | I27: =E27/E26 -> 1.0642469 | J27: =I27-1 -> 0.064246868 | K27: =C27-D27 -> 18 | L27: =(K27-'Descriptive Stats'!$B$60)/('Descriptive Stats'!$B$61-'Descriptive Stats'!$B$60) -> 0.4949203 | M27: =((E27-E26)/E26)*100 -> 6.4246868 | N27: =(M27-'Descriptive Stats'!$B$65)/('Descriptive Stats'!$B$66-'Descriptive Stats'!$B$65) -> 0.63048079 | O27: =((G27-G26)/G26)*100 -> 202.20994 | Q27: 0 | U27: 21/02/24 | V27: 7.045 | W27: 7.065 | X27: 7.065 | Y27: 7.038
A28: 44328 | B28: 146.5 | C28: 157.8 | D28: 144 | E28: 149.64999 | F28: 149.08719 | G28: 2302867 | H28: =(G28-'Descriptive Stats'!$B$55)/('Descriptive Stats'!$B$56-'Descriptive Stats'!$B$55) -> 0.12631572 | I28: =E28/E27 -> 1.0208048 | J28: =I28-1 -> 0.020804829 | K28: =C28-D28 -> 13.800003 | L28: =(K28-'Descriptive Stats'!$B$60)/('Descriptive Stats'!$B$61-'Descriptive Stats'!$B$60) -> 0.37300456 | M28: =((E28-E27)/E27)*100 -> 2.0804829 | N28: =(M28-'Descriptive Stats'!$B$65)/('Descriptive Stats'!$B$66-'Descriptive Stats'!$B$65) -> 0.46718124 | O28: =((G28-G27)/G27)*100 -> -25.404396 | Q28: 0 | U28: 20/02/24 | V28: 7.062 | W28: 7.118 | X28: 7.118 | Y28: 7.06
A29: 44330 | B29: 151.60001 | C29: 153 | D29: 141.05 | E29: 145.75 | F29: 145.20186 | G29: 1079044 | H29: =(G29-'Descriptive Stats'!$B$55)/('Descriptive Stats'!$B$56-'Descriptive Stats'!$B$55) -> 0.057472403 | I29: =E29/E28 -> 0.97393923 | J29: =I29-1 -> -0.02606077 | K29: =C29-D29 -> 11.949997 | L29: =(K29-'Descriptive Stats'!$B$60)/('Descriptive Stats'!$B$61-'Descriptive Stats'!$B$60) -> 0.31930337 | M29: =((E29-E28)/E28)*100 -> -2.6060769 | N29: =(M29-'Descriptive Stats'!$B$65)/('Descriptive Stats'!$B$66-'Descriptive Stats'!$B$65) -> 0.29101245 | O29: =((G29-G28)/G28)*100 -> -53.143451 | Q29: 0 | U29: 16/02/24 | V29: 7.099 | W29: 7.097 | X29: 7.103 | Y29: 7.075
A30: 44333 | B30: 148.7 | C30: 151 | D30: 146.05 | E30: 146.75 | F30: 146.1981 | G30: 721676 | H30: =(G30-'Descriptive Stats'!$B$55)/('Descriptive Stats'!$B$56-'Descriptive Stats'!$B$55) -> 0.037369497 | I30: =E30/E29 -> 1.0068611 | J30: =I30-1 -> 0.0068610635 | K30: =C30-D30 -> 4.949997 | L30: =(K30-'Descriptive Stats'!$B$60)/('Descriptive Stats'!$B$61-'Descriptive Stats'!$B$60) -> 0.11611031 | M30: =((E30-E29)/E29)*100 -> 0.68610635 | N30: =(M30-'Descriptive Stats'!$B$65)/('Descriptive Stats'!$B$66-'Descriptive Stats'!$B$65) -> 0.41476633 | O30: =((G30-G29)/G29)*100 -> -33.118946 | Q30: 0 | U30: 15/02/24 | V30: 7.085 | W30: 7.104 | X30: 7.104 | Y30: 7.079
A31: 44334 | B31: 147.95 | C31: 149.05 | D31: 143 | E31: 143.60001 | F31: 143.05995 | G31: 426155 | H31: =(G31-'Descriptive Stats'!$B$55)/('Descriptive Stats'!$B$56-'Descriptive Stats'!$B$55) -> 0.020745649 | I31: =E31/E30 -> 0.97853496 | J31: =I31-1 -> -0.021465036 | K31: =C31-D31 -> 6.050003 | L31: =(K31-'Descriptive Stats'!$B$60)/('Descriptive Stats'!$B$61-'Descriptive Stats'!$B$60) -> 0.14804083 | M31: =((E31-E30)/E30)*100 -> -2.1465036 | N31: =(M31-'Descriptive Stats'!$B$65)/('Descriptive Stats'!$B$66-'Descriptive Stats'!$B$65) -> 0.30828791 | O31: =((G31-G30)/G30)*100 -> -40.949263 | Q31: 0 | U31: 14/02/24 | V31: 7.114 | W31: 7.136 | X31: 7.14 | Y31: 7.11
A32: 44335 | B32: 144.25 | C32: 147.85001 | D32: 143.10001 | E32: 144.14999 | F32: 143.60788 | G32: 405679 | H32: =(G32-'Descriptive Stats'!$B$55)/('Descriptive Stats'!$B$56-'Descriptive Stats'!$B$55) -> 0.01959382 | I32: =E32/E31 -> 1.00383 | J32: =I32-1 -> 0.0038299998 | K32: =C32-D32 -> 4.75 | L32: =(K32-'Descriptive Stats'!$B$60)/('Descriptive Stats'!$B$61-'Descriptive Stats'!$B$60) -> 0.11030489 | M32: =((E32-E31)/E31)*100 -> 0.38299998 | N32: =(M32-'Descriptive Stats'!$B$65)/('Descriptive Stats'!$B$66-'Descriptive Stats'!$B$65) -> 0.40337249 | O32: =((G32-G31)/G31)*100 -> -4.8048245 | Q32: 0 | U32: 13/02/24 | V32: 7.097 | W32: 7.105 | X32: 7.109 | Y32: 7.096
A33: 44336 | B33: 146.60001 | C33: 146.60001 | D33: 140.5 | E33: 140.89999 | F33: 140.3701 | G33: 378596 | H33: =(G33-'Descriptive Stats'!$B$55)/('Descriptive Stats'!$B$56-'Descriptive Stats'!$B$55) -> 0.018070328 | I33: =E33/E32 -> 0.97745404 | J33: =I33-1 -> -0.02254596 | K33: =C33-D33 -> 6.100006 | L33: =(K33-'Descriptive Stats'!$B$60)/('Descriptive Stats'!$B$61-'Descriptive Stats'!$B$60) -> 0.14949229 | M33: =((E33-E32)/E32)*100 -> -2.254596 | N33: =(M33-'Descriptive Stats'!$B$65)/('Descriptive Stats'!$B$66-'Descriptive Stats'!$B$65) -> 0.3042247 | O33: =((G33-G32)/G32)*100 -> -6.6759679 | Q33: 0 | U33: 45628 | V33: 7.097 | W33: 7.12 | X33: 7.12 | Y33: 7.09
A34: 44337 | B34: 141 | C34: 144.7 | D34: 140.10001 | E34: 140.55 | F34: 140.02142 | G34: 390552 | H34: =(G34-'Descriptive Stats'!$B$55)/('Descriptive Stats'!$B$56-'Descriptive Stats'!$B$55) -> 0.018742885 | I34: =E34/E33 -> 0.99751603 | J34: =I34-1 -> -0.0024839675 | K34: =C34-D34 -> 4.599991 | L34: =(K34-'Descriptive Stats'!$B$60)/('Descriptive Stats'!$B$61-'Descriptive Stats'!$B$60) -> 0.10595049 | M34: =((E34-E33)/E33)*100 -> -0.24839675 | N34: =(M34-'Descriptive Stats'!$B$65)/('Descriptive Stats'!$B$66-'Descriptive Stats'!$B$65) -> 0.37963816 | O34: =((G34-G33)/G33)*100 -> 3.1579837 | Q34: 0 | U34: 45537 | V34: 7.114 | W34: 7.091 | X34: 7.118 | Y34: 7.075
A35: 44340 | B35: 141 | C35: 143.10001 | D35: 139.45 | E35: 141.45 | F35: 140.91803 | G35: 329083 | H35: =(G35-'Descriptive Stats'!$B$55)/('Descriptive Stats'!$B$56-'Descriptive Stats'!$B$55) -> 0.01528509 | I35: =E35/E34 -> 1.0064034 | J35: =I35-1 -> 0.0064033723 | K35: =C35-D35 -> 3.650009 | L35: =(K35-'Descriptive Stats'!$B$60)/('Descriptive Stats'!$B$61-'Descriptive Stats'!$B$60) -> 0.078374811 | M35: =((E35-E34)/E34)*100 -> 0.64033723 | N35: =(M35-'Descriptive Stats'!$B$65)/('Descriptive Stats'!$B$66-'Descriptive Stats'!$B$65) -> 0.41304586 | O35: =((G35-G34)/G34)*100 -> -15.739005 | Q35: 0 | U35: 45506 | V35: 7.082 | W35: 7.073 | X35: 7.092 | Y35: 7.048
A36: 44341 | B36: 141.45 | C36: 147.75 | D36: 141.3 | E36: 145.39999 | F36: 144.85316 | G36: 719677 | H36: =(G36-'Descriptive Stats'!$B$55)/('Descriptive Stats'!$B$56-'Descriptive Stats'!$B$55) -> 0.037257048 | I36: =E36/E35 -> 1.027925 | J36: =I36-1 -> 0.027925041 | K36: =C36-D36 -> 6.449997 | L36: =(K36-'Descriptive Stats'!$B$60)/('Descriptive Stats'!$B$61-'Descriptive Stats'!$B$60) -> 0.15965168 | M36: =((E36-E35)/E35)*100 -> 2.7925041 | N36: =(M36-'Descriptive Stats'!$B$65)/('Descriptive Stats'!$B$66-'Descriptive Stats'!$B$65) -> 0.49394627 | O36: =((G36-G35)/G35)*100 -> 118.69164 | Q36: 0 | U36: 45475 | V36: 7.074 | W36: 7.075 | X36: 7.078 | Y36: 7.064
A37: 44342 | B37: 146 | C37: 146.7 | D37: 139.75 | E37: 140.60001 | F37: 140.07123 | G37: 474210 | H37: =(G37-'Descriptive Stats'!$B$55)/('Descriptive Stats'!$B$56-'Descriptive Stats'!$B$55) -> 0.023448872 | I37: =E37/E36 -> 0.9669877 | J37: =I37-1 -> -0.033012298 | K37: =C37-D37 -> 6.949997 | L37: =(K37-'Descriptive Stats'!$B$60)/('Descriptive Stats'!$B$61-'Descriptive Stats'!$B$60) -> 0.17416547 | M37: =((E37-E36)/E36)*100 -> -3.3012298 | N37: =(M37-'Descriptive Stats'!$B$65)/('Descriptive Stats'!$B$66-'Descriptive Stats'!$B$65) -> 0.26488151 | O37: =((G37-G36)/G36)*100 -> -34.10794 | Q37: 0 | U37: 45445 | V37: 7.092 | W37: 7.096 | X37: 7.096 | Y37: 7.07
A38: 44343 | B38: 141.7 | C38: 143.5 | D38: 140.7 | E38: 141.14999 | F38: 140.61916 | G38: 270275 | H38: =(G38-'Descriptive Stats'!$B$55)/('Descriptive Stats'!$B$56-'Descriptive Stats'!$B$55) -> 0.011976982 | I38: =E38/E37 -> 1.0039117 | J38: =I38-1 -> 0.003911721 | K38: =C38-D38 -> 2.800003 | L38: =(K38-'Descriptive Stats'!$B$60)/('Descriptive Stats'!$B$61-'Descriptive Stats'!$B$60) -> 0.053701195 | M38: =((E38-E37)/E37)*100 -> 0.3911721 | N38: =(M38-'Descriptive Stats'!$B$65)/('Descriptive Stats'!$B$66-'Descriptive Stats'!$B$65) -> 0.40367969 | O38: =((G38-G37)/G37)*100 -> -43.005209 | Q38: 0 | U38: 45414 | V38: 7.091 | W38: 7.092 | X38: 7.096 | Y38: 7.071
A39: 44344 | B39: 142.2 | C39: 143.39999 | D39: 137.10001 | E39: 137.89999 | F39: 137.38138 | G39: 404747 | H39: =(G39-'Descriptive Stats'!$B$55)/('Descriptive Stats'!$B$56-'Descriptive Stats'!$B$55) -> 0.019541392 | I39: =E39/E38 -> 0.97697485 | J39: =I39-1 -> -0.023025152 | K39: =C39-D39 -> 6.299988 | L39: =(K39-'Descriptive Stats'!$B$60)/('Descriptive Stats'!$B$61-'Descriptive Stats'!$B$60) -> 0.15529728 | M39: =((E39-E38)/E38)*100 -> -2.3025152 | N39: =(M39-'Descriptive Stats'!$B$65)/('Descriptive Stats'!$B$66-'Descriptive Stats'!$B$65) -> 0.30242341 | O39: =((G39-G38)/G38)*100 -> 49.753769 | Q39: 0 | U39: 45324 | V39: 7.05 | W39: 7.054 | X39: 7.058 | Y39: 7.021
A40: 44347 | B40: 138.05 | C40: 139.45 | D40: 134 | E40: 135.10001 | F40: 134.59192 | G40: 448153 | H40: =(G40-'Descriptive Stats'!$B$55)/('Descriptive Stats'!$B$56-'Descriptive Stats'!$B$55) -> 0.021983096 | I40: =E40/E39 -> 0.97969552 | J40: =I40-1 -> -0.020304482 | K40: =C40-D40 -> 5.449997 | L40: =(K40-'Descriptive Stats'!$B$60)/('Descriptive Stats'!$B$61-'Descriptive Stats'!$B$60) -> 0.1306241 | M40: =((E40-E39)/E39)*100 -> -2.0304482 | N40: =(M40-'Descriptive Stats'!$B$65)/('Descriptive Stats'!$B$66-'Descriptive Stats'!$B$65) -> 0.31265046 | O40: =((G40-G39)/G39)*100 -> 10.72423 | Q40: 0 | U40: 45293 | V40: 7.064 | W40: 7.129 | X40: 7.135 | Y40: 7.039
A41: 44348 | B41: 137.5 | C41: 142 | D41: 136.85001 | E41: 139.60001 | F41: 139.075 | G41: 792163 | H41: =(G41-'Descriptive Stats'!$B$55)/('Descriptive Stats'!$B$56-'Descriptive Stats'!$B$55) -> 0.041334579 | I41: =E41/E40 -> 1.0333087 | J41: =I41-1 -> 0.033308659 | K41: =C41-D41 -> 5.149994 | L41: =(K41-'Descriptive Stats'!$B$60)/('Descriptive Stats'!$B$61-'Descriptive Stats'!$B$60) -> 0.12191574 | M41: =((E41-E40)/E40)*100 -> 3.3308659 | N41: =(M41-'Descriptive Stats'!$B$65)/('Descriptive Stats'!$B$66-'Descriptive Stats'!$B$65) -> 0.5141834 | O41: =((G41-G40)/G40)*100 -> 76.761731 | Q41: 0 | U41: 31/01/24 | V41: 7.144 | W41: 7.152 | X41: 7.152 | Y41: 7.139
A42: 44349 | B42: 140.39999 | C42: 143.60001 | D42: 137.8 | E42: 140.39999 | F42: 139.87198 | G42: 559269 | H42: =(G42-'Descriptive Stats'!$B$55)/('Descriptive Stats'!$B$56-'Descriptive Stats'!$B$55) -> 0.028233668 | I42: =E42/E41 -> 1.0057306 | J42: =I42-1 -> 0.0057305728 | K42: =C42-D42 -> 5.800003 | L42: =(K42-'Descriptive Stats'!$B$60)/('Descriptive Stats'!$B$61-'Descriptive Stats'!$B$60) -> 0.14078393 | M42: =((E42-E41)/E41)*100 -> 0.57305728 | N42: =(M42-'Descriptive Stats'!$B$65)/('Descriptive Stats'!$B$66-'Descriptive Stats'!$B$65) -> 0.41051679 | O42: =((G42-G41)/G41)*100 -> -29.399757 | Q42: 0 | U42: 30/01/24 | V42: 7.155 | W42: 7.164 | X42: 7.164 | Y42: 7.147
A43: 44350 | B43: 141.5 | C43: 142.8 | D43: 139.14999 | E43: 139.7 | F43: 139.17461 | G43: 246986 | H43: =(G43-'Descriptive Stats'!$B$55)/('Descriptive Stats'!$B$56-'Descriptive Stats'!$B$55) -> 0.010666914 | I43: =E43/E42 -> 0.99501427 | J43: =I43-1 -> -0.0049857338 | K43: =C43-D43 -> 3.650009 | L43: =(K43-'Descriptive Stats'!$B$60)/('Descriptive Stats'!$B$61-'Descriptive Stats'!$B$60) -> 0.078374811 | M43: =((E43-E42)/E42)*100 -> -0.49857338 | N43: =(M43-'Descriptive Stats'!$B$65)/('Descriptive Stats'!$B$66-'Descriptive Stats'!$B$65) -> 0.37023396 | O43: =((G43-G42)/G42)*100 -> -55.83771 | Q43: 0 | U43: 29/01/24 | V43: 7.171 | W43: 7.182 | X43: 7.182 | Y43: 7.165
A44: 44351 | B44: 139.60001 | C44: 144 | D44: 138.35001 | E44: 139.25 | F44: 138.7263 | G44: 527503 | H44: =(G44-'Descriptive Stats'!$B$55)/('Descriptive Stats'!$B$56-'Descriptive Stats'!$B$55) -> 0.026446746 | I44: =E44/E43 -> 0.99677883 | J44: =I44-1 -> -0.0032211669 | K44: =C44-D44 -> 5.649994 | L44: =(K44-'Descriptive Stats'!$B$60)/('Descriptive Stats'!$B$61-'Descriptive Stats'!$B$60) -> 0.13642953 | M44: =((E44-E43)/E43)*100 -> -0.32211669 | N44: =(M44-'Descriptive Stats'!$B$65)/('Descriptive Stats'!$B$66-'Descriptive Stats'!$B$65) -> 0.37686701 | O44: =((G44-G43)/G43)*100 -> 113.57607 | Q44: 0 | U44: 25/01/24 | V44: 7.171 | W44: 7.195 | X44: 7.195 | Y44: 7.169
A45: 44354 | B45: 140.35001 | C45: 142.10001 | D45: 138.35001 | E45: 138.75 | F45: 138.22818 | G45: 385275 | H45: =(G45-'Descriptive Stats'!$B$55)/('Descriptive Stats'!$B$56-'Descriptive Stats'!$B$55) -> 0.01844604 | I45: =E45/E44 -> 0.99640934 | J45: =I45-1 -> -0.0035906643 | K45: =C45-D45 -> 3.75 | L45: =(K45-'Descriptive Stats'!$B$60)/('Descriptive Stats'!$B$61-'Descriptive Stats'!$B$60) -> 0.081277308 | M45: =((E45-E44)/E44)*100 -> -0.35906643 | N45: =(M45-'Descriptive Stats'!$B$65)/('Descriptive Stats'!$B$66-'Descriptive Stats'!$B$65) -> 0.37547806 | O45: =((G45-G44)/G44)*100 -> -26.962501 | Q45: 0 | U45: 24/01/24 | V45: 7.181 | W45: 7.186 | X45: 7.186 | Y45: 7.17
A46: 44355 | B46: 139.60001 | C46: 143.95 | D46: 135.64999 | E46: 140.85001 | F46: 140.3203 | G46: 975001 | H46: =(G46-'Descriptive Stats'!$B$55)/('Descriptive Stats'!$B$56-'Descriptive Stats'!$B$55) -> 0.051619706 | I46: =E46/E45 -> 1.0151352 | J46: =I46-1 -> 0.015135178 | K46: =C46-D46 -> 8.300003 | L46: =(K46-'Descriptive Stats'!$B$60)/('Descriptive Stats'!$B$61-'Descriptive Stats'!$B$60) -> 0.21335288 | M46: =((E46-E45)/E45)*100 -> 1.5135178 | N46: =(M46-'Descriptive Stats'!$B$65)/('Descriptive Stats'!$B$66-'Descriptive Stats'!$B$65) -> 0.4458689 | O46: =((G46-G45)/G45)*100 -> 153.06625 | Q46: 0 | U46: 23/01/24 | V46: 7.174 | W46: 7.172 | X46: 7.177 | Y46: 7.166
A47: 44356 | B47: 141.95 | C47: 146.39999 | D47: 136.7 | E47: 138.89999 | F47: 138.37761 | G47: 1426232 | H47: =(G47-'Descriptive Stats'!$B$55)/('Descriptive Stats'!$B$56-'Descriptive Stats'!$B$55) -> 0.077002657 | I47: =E47/E46 -> 0.9861554 | J47: =I47-1 -> -0.0138446 | K47: =C47-D47 -> 9.699997 | L47: =(K47-'Descriptive Stats'!$B$60)/('Descriptive Stats'!$B$61-'Descriptive Stats'!$B$60) -> 0.25399131 | M47: =((E47-E46)/E46)*100 -> -1.38446 | N47: =(M47-'Descriptive Stats'!$B$65)/('Descriptive Stats'!$B$66-'Descriptive Stats'!$B$65) -> 0.33693329 | O47: =((G47-G46)/G46)*100 -> 46.280055 | Q47: 0 | U47: 19/01/24 | V47: 7.184 | W47: 7.194 | X47: 7.196 | Y47: 7.177
A48: 44357 | B48: 142.10001 | C48: 143.8 | D48: 140.5 | E48: 141.85001 | F48: 141.31653 | G48: 489950 | H48: =(G48-'Descriptive Stats'!$B$55)/('Descriptive Stats'!$B$56-'Descriptive Stats'!$B$55) -> 0.024334289 | I48: =E48/E47 -> 1.0212384 | J48: =I48-1 -> 0.021238388 | K48: =C48-D48 -> 3.300003 | L48: =(K48-'Descriptive Stats'!$B$60)/('Descriptive Stats'!$B$61-'Descriptive Stats'!$B$60) -> 0.068214984 | M48: =((E48-E47)/E47)*100 -> 2.1238388 | N48: =(M48-'Descriptive Stats'!$B$65)/('Descriptive Stats'!$B$66-'Descriptive Stats'!$B$65) -> 0.468811 | O48: =((G48-G47)/G47)*100 -> -65.647244 | Q48: 0 | U48: 18/01/24 | V48: 7.178 | W48: 7.177 | X48: 7.18 | Y48: 7.169
A49: 44358 | B49: 146 | C49: 148 | D49: 143.05 | E49: 146.75 | F49: 146.1981 | G49: 1428949 | H49: =(G49-'Descriptive Stats'!$B$55)/('Descriptive Stats'!$B$56-'Descriptive Stats'!$B$55) -> 0.077155496 | I49: =E49/E48 -> 1.0345435 | J49: =I49-1 -> 0.034543488 | K49: =C49-D49 -> 4.949997 | L49: =(K49-'Descriptive Stats'!$B$60)/('Descriptive Stats'!$B$61-'Descriptive Stats'!$B$60) -> 0.11611031 | M49: =((E49-E48)/E48)*100 -> 3.4543488 | N49: =(M49-'Descriptive Stats'!$B$65)/('Descriptive Stats'!$B$66-'Descriptive Stats'!$B$65) -> 0.51882515 | O49: =((G49-G48)/G48)*100 -> 191.65201 | P49: Earnings | Q49: 0.5 | U49: 17/01/24 | V49: 7.163 | W49: 7.161 | X49: 7.165 | Y49: 7.151
A50: 44361 | B50: 138.89999 | C50: 141.5 | D50: 133.05 | E50: 138.5 | F50: 137.97913 | G50: 1925438 | H50: =(G50-'Descriptive Stats'!$B$55)/('Descriptive Stats'!$B$56-'Descriptive Stats'!$B$55) -> 0.10508433 | I50: =E50/E49 -> 0.94378194 | J50: =I50-1 -> -0.056218058 | K50: =C50-D50 -> 8.449997 | L50: =(K50-'Descriptive Stats'!$B$60)/('Descriptive Stats'!$B$61-'Descriptive Stats'!$B$60) -> 0.21770684 | M50: =((E50-E49)/E49)*100 -> -5.6218058 | N50: =(M50-'Descriptive Stats'!$B$65)/('Descriptive Stats'!$B$66-'Descriptive Stats'!$B$65) -> 0.17765056 | O50: =((G50-G49)/G49)*100 -> 34.745047 | Q50: 0 | U50: 16/01/24 | V50: 7.146 | W50: 7.161 | X50: 7.161 | Y50: 7.14
A51: 44362 | B51: 139.89999 | C51: 147.5 | D51: 139 | E51: 146.10001 | F51: 145.55055 | G51: 2286847 | H51: =(G51-'Descriptive Stats'!$B$55)/('Descriptive Stats'!$B$56-'Descriptive Stats'!$B$55) -> 0.12541455 | I51: =E51/E50 -> 1.0548737 | J51: =I51-1 -> 0.05487369 | K51: =C51-D51 -> 8.5 | L51: =(K51-'Descriptive Stats'!$B$60)/('Descriptive Stats'!$B$61-'Descriptive Stats'!$B$60) -> 0.21915831 | M51: =((E51-E50)/E50)*100 -> 5.487369 | N51: =(M51-'Descriptive Stats'!$B$65)/('Descriptive Stats'!$B$66-'Descriptive Stats'!$B$65) -> 0.59524682 | O51: =((G51-G50)/G50)*100 -> 18.770223 | Q51: 0 | U51: 15/01/24 | V51: 7.148 | W51: 7.153 | X51: 7.153 | Y51: 7.134
A52: 44363 | B52: 147.10001 | C52: 150.5 | D52: 141 | E52: 142.05 | F52: 141.51578 | G52: 1763830 | H52: =(G52-'Descriptive Stats'!$B$55)/('Descriptive Stats'!$B$56-'Descriptive Stats'!$B$55) -> 0.095993448 | I52: =E52/E51 -> 0.97227924 | J52: =I52-1 -> -0.027720759 | K52: =C52-D52 -> 9.5 | L52: =(K52-'Descriptive Stats'!$B$60)/('Descriptive Stats'!$B$61-'Descriptive Stats'!$B$60) -> 0.24818589 | M52: =((E52-E51)/E51)*100 -> -2.7720759 | N52: =(M52-'Descriptive Stats'!$B$65)/('Descriptive Stats'!$B$66-'Descriptive Stats'!$B$65) -> 0.28477252 | O52: =((G52-G51)/G51)*100 -> -22.87066 | Q52: 0 | U52: 45627 | V52: 7.178 | W52: 7.168 | X52: 7.181 | Y52: 7.158
A53: 44364 | B53: 143 | C53: 148.7 | D53: 139.5 | E53: 141.14999 | F53: 140.61916 | G53: 875606 | H53: =(G53-'Descriptive Stats'!$B$55)/('Descriptive Stats'!$B$56-'Descriptive Stats'!$B$55) -> 0.046028471 | I53: =E53/E52 -> 0.99366414 | J53: =I53-1 -> -0.0063358605 | K53: =C53-D53 -> 9.199997 | L53: =(K53-'Descriptive Stats'!$B$60)/('Descriptive Stats'!$B$61-'Descriptive Stats'!$B$60) -> 0.23947752 | M53: =((E53-E52)/E52)*100 -> -0.63358605 | N53: =(M53-'Descriptive Stats'!$B$65)/('Descriptive Stats'!$B$66-'Descriptive Stats'!$B$65) -> 0.36515881 | O53: =((G53-G52)/G52)*100 -> -50.357688 | Q53: 0 | U53: 45597 | V53: 7.165 | W53: 7.192 | X53: 7.192 | Y53: 7.162
A54: 44365 | B54: 142 | C54: 143 | D54: 134.10001 | E54: 140.75 | F54: 140.22067 | G54: 957063 | H54: =(G54-'Descriptive Stats'!$B$55)/('Descriptive Stats'!$B$56-'Descriptive Stats'!$B$55) -> 0.050610645 | I54: =E54/E53 -> 0.99716618 | J54: =I54-1 -> -0.0028338223 | K54: =C54-D54 -> 8.899994 | L54: =(K54-'Descriptive Stats'!$B$60)/('Descriptive Stats'!$B$61-'Descriptive Stats'!$B$60) -> 0.23076916 | M54: =((E54-E53)/E53)*100 -> -0.28338223 | N54: =(M54-'Descriptive Stats'!$B$65)/('Descriptive Stats'!$B$66-'Descriptive Stats'!$B$65) -> 0.37832304 | O54: =((G54-G53)/G53)*100 -> 9.3029285 | Q54: 0 | U54: 45566 | V54: 7.178 | W54: 7.192 | X54: 7.192 | Y54: 7.176
A55: 44368 | B55: 139.3 | C55: 140.55 | D55: 136.5 | E55: 139.2 | F55: 138.6765 | G55: 350475 | H55: =(G55-'Descriptive Stats'!$B$55)/('Descriptive Stats'!$B$56-'Descriptive Stats'!$B$55) -> 0.016488447 | I55: =E55/E54 -> 0.98898755 | J55: =I55-1 -> -0.011012455 | K55: =C55-D55 -> 4.050003 | L55: =(K55-'Descriptive Stats'!$B$60)/('Descriptive Stats'!$B$61-'Descriptive Stats'!$B$60) -> 0.089985668 | M55: =((E55-E54)/E54)*100 -> -1.1012455 | N55: =(M55-'Descriptive Stats'!$B$65)/('Descriptive Stats'!$B$66-'Descriptive Stats'!$B$65) -> 0.34757939 | O55: =((G55-G54)/G54)*100 -> -63.380154 | Q55: 0 | U55: 45536 | V55: 7.189 | W55: 7.183 | X55: 7.197 | Y55: 7.182
A56: 44369 | B56: 140.3 | C56: 141.14999 | D56: 137.64999 | E56: 138.45 | F56: 137.92931 | G56: 313491 | H56: =(G56-'Descriptive Stats'!$B$55)/('Descriptive Stats'!$B$56-'Descriptive Stats'!$B$55) -> 0.014407998 | I56: =E56/E55 -> 0.99461207 | J56: =I56-1 -> -0.0053879312 | K56: =C56-D56 -> 3.5 | L56: =(K56-'Descriptive Stats'!$B$60)/('Descriptive Stats'!$B$61-'Descriptive Stats'!$B$60) -> 0.074020413 | M56: =((E56-E55)/E55)*100 -> -0.53879312 | N56: =(M56-'Descriptive Stats'!$B$65)/('Descriptive Stats'!$B$66-'Descriptive Stats'!$B$65) -> 0.36872209 | O56: =((G56-G55)/G55)*100 -> -10.552536 | Q56: 0 | U56: 45505 | V56: 7.203 | W56: 7.233 | X56: 7.233 | Y56: 7.201
A57: 44370 | B57: 139 | C57: 140.10001 | D57: 137.55 | E57: 137.75 | F57: 137.23195 | G57: 183666 | H57: =(G57-'Descriptive Stats'!$B$55)/('Descriptive Stats'!$B$56-'Descriptive Stats'!$B$55) -> 0.0071049943 | I57: =E57/E56 -> 0.99494404 | J57: =I57-1 -> -0.0050559553 | K57: =C57-D57 -> 2.550003 | L57: =(K57-'Descriptive Stats'!$B$60)/('Descriptive Stats'!$B$61-'Descriptive Stats'!$B$60) -> 0.0464443 | M57: =((E57-E56)/E56)*100 -> -0.50559553 | N57: =(M57-'Descriptive Stats'!$B$65)/('Descriptive Stats'!$B$66-'Descriptive Stats'!$B$65) -> 0.36997 | O57: =((G57-G56)/G56)*100 -> -41.412672 | Q57: 0 | U57: 45413 | V57: 7.235 | W57: 7.237 | X57: 7.239 | Y57: 7.225
A58: 44371 | B58: 138.55 | C58: 140.85001 | D58: 135.60001 | E58: 137.64999 | F58: 137.13232 | G58: 399199 | H58: =(G58-'Descriptive Stats'!$B$55)/('Descriptive Stats'!$B$56-'Descriptive Stats'!$B$55) -> 0.019229302 | I58: =E58/E57 -> 0.999274 | J58: =I58-1 -> -0.00072599637 | K58: =C58-D58 -> 5.25 | L58: =(K58-'Descriptive Stats'!$B$60)/('Descriptive Stats'!$B$61-'Descriptive Stats'!$B$60) -> 0.12481868 | M58: =((E58-E57)/E57)*100 -> -0.072599637 | N58: =(M58-'Descriptive Stats'!$B$65)/('Descriptive Stats'!$B$66-'Descriptive Stats'!$B$65) -> 0.38624641 | O58: =((G58-G57)/G57)*100 -> 117.35052 | Q58: 0 | U58: 45383 | V58: 7.22 | W58: 7.214 | X58: 7.224 | Y58: 7.208
A59: 44372 | B59: 138.75 | C59: 139 | D59: 134.5 | E59: 135.85001 | F59: 135.3391 | G59: 483895 | H59: =(G59-'Descriptive Stats'!$B$55)/('Descriptive Stats'!$B$56-'Descriptive Stats'!$B$55) -> 0.023993679 | I59: =E59/E58 -> 0.98692344 | J59: =I59-1 -> -0.013076557 | K59: =C59-D59 -> 4.5 | L59: =(K59-'Descriptive Stats'!$B$60)/('Descriptive Stats'!$B$61-'Descriptive Stats'!$B$60) -> 0.10304799 | M59: =((E59-E58)/E58)*100 -> -1.3076557 | N59: =(M59-'Descriptive Stats'!$B$65)/('Descriptive Stats'!$B$66-'Descriptive Stats'!$B$65) -> 0.33982039 | O59: =((G59-G58)/G58)*100 -> 21.216486 | Q59: 0 | U59: 45352 | V59: 7.216 | W59: 7.215 | X59: 7.222 | Y59: 7.197
A60: 44375 | B60: 137.39999 | C60: 144 | D60: 135.25 | E60: 137.55 | F60: 137.0327 | G60: 1242796 | H60: =(G60-'Descriptive Stats'!$B$55)/('Descriptive Stats'!$B$56-'Descriptive Stats'!$B$55) -> 0.066683891 | I60: =E60/E59 -> 1.0125138 | J60: =I60-1 -> 0.012513779 | K60: =C60-D60 -> 8.75 | L60: =(K60-'Descriptive Stats'!$B$60)/('Descriptive Stats'!$B$61-'Descriptive Stats'!$B$60) -> 0.2264152 | M60: =((E60-E59)/E59)*100 -> 1.2513779 | N60: =(M60-'Descriptive Stats'!$B$65)/('Descriptive Stats'!$B$66-'Descriptive Stats'!$B$65) -> 0.43601501 | O60: =((G60-G59)/G59)*100 -> 156.83175 | Q60: 0 | U60: 45323 | V60: 7.206 | W60: 7.215 | X60: 7.215 | Y60: 7.204
A61: 44376 | B61: 138.60001 | C61: 140.39999 | D61: 137.5 | E61: 137.95 | F61: 137.4312 | G61: 547908 | H61: =(G61-'Descriptive Stats'!$B$55)/('Descriptive Stats'!$B$56-'Descriptive Stats'!$B$55) -> 0.027594582 | I61: =E61/E60 -> 1.002908 | J61: =I61-1 -> 0.0029079898 | K61: =C61-D61 -> 2.899994 | L61: =(K61-'Descriptive Stats'!$B$60)/('Descriptive Stats'!$B$61-'Descriptive Stats'!$B$60) -> 0.056603691 | M61: =((E61-E60)/E60)*100 -> 0.29079898 | N61: =(M61-'Descriptive Stats'!$B$65)/('Descriptive Stats'!$B$66-'Descriptive Stats'!$B$65) -> 0.39990664 | O61: =((G61-G60)/G60)*100 -> -55.913279 | Q61: 0 | U61: 45292 | V61: 7.196 | W61: 7.207 | X61: 7.207 | Y61: 7.192
A62: 44377 | B62: 138.95 | C62: 142.39999 | D62: 135.05 | E62: 136.60001 | F62: 136.08627 | G62: 1145083 | H62: =(G62-'Descriptive Stats'!$B$55)/('Descriptive Stats'!$B$56-'Descriptive Stats'!$B$55) -> 0.061187273 | I62: =E62/E61 -> 0.99021391 | J62: =I62-1 -> -0.0097860894 | K62: =C62-D62 -> 7.349991 | L62: =(K62-'Descriptive Stats'!$B$60)/('Descriptive Stats'!$B$61-'Descriptive Stats'!$B$60) -> 0.18577633 | M62: =((E62-E61)/E61)*100 -> -0.97860894 | N62: =(M62-'Descriptive Stats'!$B$65)/('Descriptive Stats'!$B$66-'Descriptive Stats'!$B$65) -> 0.35218932 | O62: =((G62-G61)/G61)*100 -> 108.99184 | Q62: 0 | U62: 29/12/23 | V62: 7.176 | W62: 7.225 | X62: 7.225 | Y62: 7.172
A63: 44378 | B63: 136.7 | C63: 138.95 | D63: 135.60001 | E63: 136.2 | F63: 135.68777 | G63: 315431 | H63: =(G63-'Descriptive Stats'!$B$55)/('Descriptive Stats'!$B$56-'Descriptive Stats'!$B$55) -> 0.014517128 | I63: =E63/E62 -> 0.99707168 | J63: =I63-1 -> -0.0029283234 | K63: =C63-D63 -> 3.349991 | L63: =(K63-'Descriptive Stats'!$B$60)/('Descriptive Stats'!$B$61-'Descriptive Stats'!$B$60) -> 0.069666015 | M63: =((E63-E62)/E62)*100 -> -0.29283234 | N63: =(M63-'Descriptive Stats'!$B$65)/('Descriptive Stats'!$B$66-'Descriptive Stats'!$B$65) -> 0.37796781 | O63: =((G63-G62)/G62)*100 -> -72.453438 | Q63: 0 | U63: 28/12/23 | V63: 7.207 | W63: 7.2 | X63: 7.213 | Y63: 7.191
A64: 44379 | B64: 136.89999 | C64: 140.25 | D64: 136.55 | E64: 137.95 | F64: 137.4312 | G64: 576712 | H64: =(G64-'Descriptive Stats'!$B$55)/('Descriptive Stats'!$B$56-'Descriptive Stats'!$B$55) -> 0.029214884 | I64: =E64/E63 -> 1.0128488 | J64: =I64-1 -> 0.012848752 | K64: =C64-D64 -> 3.699997 | L64: =(K64-'Descriptive Stats'!$B$60)/('Descriptive Stats'!$B$61-'Descriptive Stats'!$B$60) -> 0.079825841 | M64: =((E64-E63)/E63)*100 -> 1.2848752 | N64: =(M64-'Descriptive Stats'!$B$65)/('Descriptive Stats'!$B$66-'Descriptive Stats'!$B$65) -> 0.43727418 | O64: =((G64-G63)/G63)*100 -> 82.833013 | Q64: 0 | U64: 27/12/23 | V64: 7.205 | W64: 7.191 | X64: 7.208 | Y64: 7.182
A65: 44382 | B65: 138.85001 | C65: 139.39999 | D65: 136.7 | E65: 137.10001 | F65: 136.5844 | G65: 364577 | H65: =(G65-'Descriptive Stats'!$B$55)/('Descriptive Stats'!$B$56-'Descriptive Stats'!$B$55) -> 0.017281722 | I65: =E65/E64 -> 0.99383841 | J65: =I65-1 -> -0.0061615877 | K65: =C65-D65 -> 2.699997 | L65: =(K65-'Descriptive Stats'!$B$60)/('Descriptive Stats'!$B$61-'Descriptive Stats'!$B$60) -> 0.050798263 | M65: =((E65-E64)/E64)*100 -> -0.61615877 | N65: =(M65-'Descriptive Stats'!$B$65)/('Descriptive Stats'!$B$66-'Descriptive Stats'!$B$65) -> 0.3658139 | O65: =((G65-G64)/G64)*100 -> -36.783525 | Q65: 0 | U65: 26/12/23 | V65: 7.183 | W65: 7.213 | X65: 7.213 | Y65: 7.177
A66: 44383 | B66: 137.7 | C66: 138.45 | D66: 134.25 | E66: 135.10001 | F66: 134.59192 | G66: 418151 | H66: =(G66-'Descriptive Stats'!$B$55)/('Descriptive Stats'!$B$56-'Descriptive Stats'!$B$55) -> 0.020295403 | I66: =E66/E65 -> 0.98541211 | J66: =I66-1 -> -0.014587891 | K66: =C66-D66 -> 4.199997 | L66: =(K66-'Descriptive Stats'!$B$60)/('Descriptive Stats'!$B$61-'Descriptive Stats'!$B$60) -> 0.094339631 | M66: =((E66-E65)/E65)*100 -> -1.4587891 | N66: =(M66-'Descriptive Stats'!$B$65)/('Descriptive Stats'!$B$66-'Descriptive Stats'!$B$65) -> 0.33413925 | O66: =((G66-G65)/G65)*100 -> 14.694838 | Q66: 0 | U66: 22/12/23 | V66: 7.188 | W66: 7.187 | X66: 7.198 | Y66: 7.185
A67: 44384 | B67: 135.75 | C67: 136.85001 | D67: 133.10001 | E67: 134.5 | F67: 133.99417 | G67: 396557 | H67: =(G67-'Descriptive Stats'!$B$55)/('Descriptive Stats'!$B$56-'Descriptive Stats'!$B$55) -> 0.019080683 | I67: =E67/E66 -> 0.9955588 | J67: =I67-1 -> -0.0044411989 | K67: =C67-D67 -> 3.75 | L67: =(K67-'Descriptive Stats'!$B$60)/('Descriptive Stats'!$B$61-'Descriptive Stats'!$B$60) -> 0.081277308 | M67: =((E67-E66)/E66)*100 -> -0.44411989 | N67: =(M67-'Descriptive Stats'!$B$65)/('Descriptive Stats'!$B$66-'Descriptive Stats'!$B$65) -> 0.37228088 | O67: =((G67-G66)/G66)*100 -> -5.1641632 | Q67: 0 | U67: 21/12/23 | V67: 7.184 | W67: 7.173 | X67: 7.188 | Y67: 7.151
A68: 44385 | B68: 134.5 | C68: 139.39999 | D68: 134.5 | E68: 135.60001 | F68: 135.09004 | G68: 641012 | H68: =(G68-'Descriptive Stats'!$B$55)/('Descriptive Stats'!$B$56-'Descriptive Stats'!$B$55) -> 0.032831931 | I68: =E68/E67 -> 1.0081785 | J68: =I68-1 -> 0.0081784833 | K68: =C68-D68 -> 4.899994 | L68: =(K68-'Descriptive Stats'!$B$60)/('Descriptive Stats'!$B$61-'Descriptive Stats'!$B$60) -> 0.11465885 | M68: =((E68-E67)/E67)*100 -> 0.81784833 | N68: =(M68-'Descriptive Stats'!$B$65)/('Descriptive Stats'!$B$66-'Descriptive Stats'!$B$65) -> 0.41971854 | O68: =((G68-G67)/G67)*100 -> 61.644354 | Q68: 0 | U68: 20/12/23 | V68: 7.171 | W68: 7.184 | X68: 7.184 | Y68: 7.165
A69: 44386 | B69: 136 | C69: 136.89999 | D69: 134.7 | E69: 135 | F69: 134.49229 | G69: 233912 | H69: =(G69-'Descriptive Stats'!$B$55)/('Descriptive Stats'!$B$56-'Descriptive Stats'!$B$55) -> 0.0099314662 | I69: =E69/E68 -> 0.99557518 | J69: =I69-1 -> -0.0044248228 | K69: =C69-D69 -> 2.199997 | L69: =(K69-'Descriptive Stats'!$B$60)/('Descriptive Stats'!$B$61-'Descriptive Stats'!$B$60) -> 0.036284473 | M69: =((E69-E68)/E68)*100 -> -0.44248228 | N69: =(M69-'Descriptive Stats'!$B$65)/('Descriptive Stats'!$B$66-'Descriptive Stats'!$B$65) -> 0.37234244 | O69: =((G69-G68)/G68)*100 -> -63.508951 | Q69: 0 | U69: 19/12/23 | V69: 7.171 | W69: 7.185 | X69: 7.185 | Y69: 7.153
A70: 44389 | B70: 136.10001 | C70: 139.3 | D70: 135.35001 | E70: 136.14999 | F70: 135.63796 | G70: 453071 | H70: =(G70-'Descriptive Stats'!$B$55)/('Descriptive Stats'!$B$56-'Descriptive Stats'!$B$55) -> 0.022259747 | I70: =E70/E69 -> 1.0085185 | J70: =I70-1 -> 0.0085184741 | K70: =C70-D70 -> 3.949997 | L70: =(K70-'Descriptive Stats'!$B$60)/('Descriptive Stats'!$B$61-'Descriptive Stats'!$B$60) -> 0.087082736 | M70: =((E70-E69)/E69)*100 -> 0.85184741 | N70: =(M70-'Descriptive Stats'!$B$65)/('Descriptive Stats'!$B$66-'Descriptive Stats'!$B$65) -> 0.42099657 | O70: =((G70-G69)/G69)*100 -> 93.692927 | Q70: 0 | U70: 18/12/23 | V70: 7.153 | W70: 7.171 | X70: 7.179 | Y70: 7.147
A71: 44390 | B71: 137.3 | C71: 138.55 | D71: 136.10001 | E71: 136.5 | F71: 135.98665 | G71: 293375 | H71: =(G71-'Descriptive Stats'!$B$55)/('Descriptive Stats'!$B$56-'Descriptive Stats'!$B$55) -> 0.013276419 | I71: =E71/E70 -> 1.0025707 | J71: =I71-1 -> 0.0025707383 | K71: =C71-D71 -> 2.449997 | L71: =(K71-'Descriptive Stats'!$B$60)/('Descriptive Stats'!$B$61-'Descriptive Stats'!$B$60) -> 0.043541368 | M71: =((E71-E70)/E70)*100 -> 0.25707383 | N71: =(M71-'Descriptive Stats'!$B$65)/('Descriptive Stats'!$B$66-'Descriptive Stats'!$B$65) -> 0.3986389 | O71: =((G71-G70)/G70)*100 -> -35.247456 | Q71: 0 | U71: 15/12/23 | V71: 7.163 | W71: 7.204 | X71: 7.206 | Y71: 7.155
A72: 44391 | B72: 136.85001 | C72: 141.8 | D72: 135.8 | E72: 140.60001 | F72: 140.07123 | G72: 843653 | H72: =(G72-'Descriptive Stats'!$B$55)/('Descriptive Stats'!$B$56-'Descriptive Stats'!$B$55) -> 0.044231029 | I72: =E72/E71 -> 1.0300367 | J72: =I72-1 -> 0.030036674 | K72: =C72-D72 -> 6 | L72: =(K72-'Descriptive Stats'!$B$60)/('Descriptive Stats'!$B$61-'Descriptive Stats'!$B$60) -> 0.14658936 | M72: =((E72-E71)/E71)*100 -> 3.0036674 | N72: =(M72-'Descriptive Stats'!$B$65)/('Descriptive Stats'!$B$66-'Descriptive Stats'!$B$65) -> 0.50188394 | O72: =((G72-G71)/G71)*100 -> 187.56813 | Q72: 0 | U72: 14/12/23 | V72: 7.194 | W72: 7.222 | X72: 7.224 | Y72: 7.185
A73: 44392 | B73: 143 | C73: 147.45 | D73: 141.5 | E73: 142.10001 | F73: 141.5656 | G73: 2347433 | H73: =(G73-'Descriptive Stats'!$B$55)/('Descriptive Stats'!$B$56-'Descriptive Stats'!$B$55) -> 0.12882268 | I73: =E73/E72 -> 1.0106686 | J73: =I73-1 -> 0.010668563 | K73: =C73-D73 -> 5.949997 | L73: =(K73-'Descriptive Stats'!$B$60)/('Descriptive Stats'!$B$61-'Descriptive Stats'!$B$60) -> 0.14513789 | M73: =((E73-E72)/E72)*100 -> 1.0668563 | N73: =(M73-'Descriptive Stats'!$B$65)/('Descriptive Stats'!$B$66-'Descriptive Stats'!$B$65) -> 0.4290788 | O73: =((G73-G72)/G72)*100 -> 178.24627 | Q73: 0 | U73: 13/12/23 | V73: 7.259 | W73: 7.262 | X73: 7.269 | Y73: 7.257
A74: 44393 | B74: 142.55 | C74: 144.8 | D74: 142.39999 | E74: 143.3 | F74: 142.76108 | G74: 517441 | H74: =(G74-'Descriptive Stats'!$B$55)/('Descriptive Stats'!$B$56-'Descriptive Stats'!$B$55) -> 0.025880731 | I74: =E74/E73 -> 1.0084447 | J74: =I74-1 -> 0.0084447357 | K74: =C74-D74 -> 2.400009 | L74: =(K74-'Descriptive Stats'!$B$60)/('Descriptive Stats'!$B$61-'Descriptive Stats'!$B$60) -> 0.042090337 | M74: =((E74-E73)/E73)*100 -> 0.84447357 | N74: =(M74-'Descriptive Stats'!$B$65)/('Descriptive Stats'!$B$66-'Descriptive Stats'!$B$65) -> 0.42071939 | O74: =((G74-G73)/G73)*100 -> -77.957156 | Q74: 0 | U74: 45272 | V74: 7.275 | W74: 7.279 | X74: 7.28 | Y74: 7.267
A75: 44396 | B75: 141.8 | C75: 144.5 | D75: 140.25 | E75: 141.8 | F75: 141.26672 | G75: 836591 | H75: =(G75-'Descriptive Stats'!$B$55)/('Descriptive Stats'!$B$56-'Descriptive Stats'!$B$55) -> 0.043833773 | I75: =E75/E74 -> 0.98953245 | J75: =I75-1 -> -0.01046755 | K75: =C75-D75 -> 4.25 | L75: =(K75-'Descriptive Stats'!$B$60)/('Descriptive Stats'!$B$61-'Descriptive Stats'!$B$60) -> 0.095791097 | M75: =((E75-E74)/E74)*100 -> -1.046755 | N75: =(M75-'Descriptive Stats'!$B$65)/('Descriptive Stats'!$B$66-'Descriptive Stats'!$B$65) -> 0.3496277 | O75: =((G75-G74)/G74)*100 -> 61.67853 | Q75: 0 | U75: 45242 | V75: 7.281 | W75: 7.287 | X75: 7.287 | Y75: 7.273
A76: 44397 | B76: 141 | C76: 142.14999 | D76: 136.2 | E76: 138.3 | F76: 137.77988 | G76: 577647 | H76: =(G76-'Descriptive Stats'!$B$55)/('Descriptive Stats'!$B$56-'Descriptive Stats'!$B$55) -> 0.02926748 | I76: =E76/E75 -> 0.97531735 | J76: =I76-1 -> -0.024682651 | K76: =C76-D76 -> 5.949997 | L76: =(K76-'Descriptive Stats'!$B$60)/('Descriptive Stats'!$B$61-'Descriptive Stats'!$B$60) -> 0.14513789 | M76: =((E76-E75)/E75)*100 -> -2.4682651 | N76: =(M76-'Descriptive Stats'!$B$65)/('Descriptive Stats'!$B$66-'Descriptive Stats'!$B$65) -> 0.29619283 | O76: =((G76-G75)/G75)*100 -> -30.952281 | Q76: 0 | U76: 45150 | V76: 7.266 | W76: 7.249 | X76: 7.271 | Y76: 7.226
A77: 44399 | B77: 139.60001 | C77: 144 | D77: 138 | E77: 142.45 | F77: 141.91428 | G77: 873693 | H77: =(G77-'Descriptive Stats'!$B$55)/('Descriptive Stats'!$B$56-'Descriptive Stats'!$B$55) -> 0.04592086 | I77: =E77/E76 -> 1.0300072 | J77: =I77-1 -> 0.030007187 | K77: =C77-D77 -> 6 | L77: =(K77-'Descriptive Stats'!$B$60)/('Descriptive Stats'!$B$61-'Descriptive Stats'!$B$60) -> 0.14658936 | M77: =((E77-E76)/E76)*100 -> 3.0007187 | N77: =(M77-'Descriptive Stats'!$B$65)/('Descriptive Stats'!$B$66-'Descriptive Stats'!$B$65) -> 0.5017731 | O77: =((G77-G76)/G76)*100 -> 51.250331 | Q77: 0 | U77: 45119 | V77: 7.236 | W77: 7.248 | X77: 7.248 | Y77: 7.233
A78: 44400 | B78: 143.75 | C78: 144.5 | D78: 137.5 | E78: 138.7 | F78: 138.17837 | G78: 897587 | H78: =(G78-'Descriptive Stats'!$B$55)/('Descriptive Stats'!$B$56-'Descriptive Stats'!$B$55) -> 0.047264961 | I78: =E78/E77 -> 0.97367497 | J78: =I78-1 -> -0.026325027 | K78: =C78-D78 -> 7 | L78: =(K78-'Descriptive Stats'!$B$60)/('Descriptive Stats'!$B$61-'Descriptive Stats'!$B$60) -> 0.17561694 | M78: =((E78-E77)/E77)*100 -> -2.6325027 | N78: =(M78-'Descriptive Stats'!$B$65)/('Descriptive Stats'!$B$66-'Descriptive Stats'!$B$65) -> 0.2900191 | O78: =((G78-G77)/G77)*100 -> 2.7348279 | Q78: 0 | U78: 45089 | V78: 7.248 | W78: 7.251 | X78: 7.254 | Y78: 7.243
A79: 44403 | B79: 138 | C79: 140.2 | D79: 137 | E79: 137.64999 | F79: 137.13232 | G79: 335128 | H79: =(G79-'Descriptive Stats'!$B$55)/('Descriptive Stats'!$B$56-'Descriptive Stats'!$B$55) -> 0.015625137 | I79: =E79/E78 -> 0.99242968 | J79: =I79-1 -> -0.0075703174 | K79: =C79-D79 -> 3.199997 | L79: =(K79-'Descriptive Stats'!$B$60)/('Descriptive Stats'!$B$61-'Descriptive Stats'!$B$60) -> 0.065312052 | M79: =((E79-E78)/E78)*100 -> -0.75703174 | N79: =(M79-'Descriptive Stats'!$B$65)/('Descriptive Stats'!$B$66-'Descriptive Stats'!$B$65) -> 0.36051846 | O79: =((G79-G78)/G78)*100 -> -62.663452 | Q79: 0 | U79: 45058 | V79: 7.262 | W79: 7.275 | X79: 7.275 | Y79: 7.256
A80: 44404 | B80: 138.5 | C80: 143 | D80: 134.25 | E80: 135.8 | F80: 135.28929 | G80: 1356258 | H80: =(G80-'Descriptive Stats'!$B$55)/('Descriptive Stats'!$B$56-'Descriptive Stats'!$B$55) -> 0.073066432 | I80: =E80/E79 -> 0.98656018 | J80: =I80-1 -> -0.013439819 | K80: =C80-D80 -> 8.75 | L80: =(K80-'Descriptive Stats'!$B$60)/('Descriptive Stats'!$B$61-'Descriptive Stats'!$B$60) -> 0.2264152 | M80: =((E80-E79)/E79)*100 -> -1.3439819 | N80: =(M80-'Descriptive Stats'!$B$65)/('Descriptive Stats'!$B$66-'Descriptive Stats'!$B$65) -> 0.33845488 | O80: =((G80-G79)/G79)*100 -> 304.6985 | Q80: 0 | U80: 45028 | V80: 7.271 | W80: 7.264 | X80: 7.276 | Y80: 7.262
A81: 44405 | B81: 136.5 | C81: 138.8 | D81: 130.5 | E81: 136.39999 | F81: 135.88702 | G81: 844260 | H81: =(G81-'Descriptive Stats'!$B$55)/('Descriptive Stats'!$B$56-'Descriptive Stats'!$B$55) -> 0.044265175 | I81: =E81/E80 -> 1.0044182 | J81: =I81-1 -> 0.0044181958 | K81: =C81-D81 -> 8.300003 | L81: =(K81-'Descriptive Stats'!$B$60)/('Descriptive Stats'!$B$61-'Descriptive Stats'!$B$60) -> 0.21335288 | M81: =((E81-E80)/E80)*100 -> 0.44181958 | N81: =(M81-'Descriptive Stats'!$B$65)/('Descriptive Stats'!$B$66-'Descriptive Stats'!$B$65) -> 0.40558354 | O81: =((G81-G80)/G80)*100 -> -37.750782 | Q81: 0 | U81: 44938 | V81: 7.29 | W81: 7.293 | X81: 7.298 | Y81: 7.279
A82: 44406 | B82: 137.60001 | C82: 142.10001 | D82: 136.7 | E82: 141.25 | F82: 140.71878 | G82: 1283349 | H82: =(G82-'Descriptive Stats'!$B$55)/('Descriptive Stats'!$B$56-'Descriptive Stats'!$B$55) -> 0.068965106 | I82: =E82/E81 -> 1.0355572 | J82: =I82-1 -> 0.03555723 | K82: =C82-D82 -> 5.400009 | L82: =(K82-'Descriptive Stats'!$B$60)/('Descriptive Stats'!$B$61-'Descriptive Stats'!$B$60) -> 0.12917307 | M82: =((E82-E81)/E81)*100 -> 3.555723 | N82: =(M82-'Descriptive Stats'!$B$65)/('Descriptive Stats'!$B$66-'Descriptive Stats'!$B$65) -> 0.52263583 | O82: =((G82-G81)/G81)*100 -> 52.008741 | Q82: 0 | U82: 30/11/23 | V82: 7.279 | W82: 7.25 | X82: 7.287 | Y82: 7.248
A83: 44407 | B83: 146.10001 | C83: 148.60001 | D83: 137.10001 | E83: 138.55 | F83: 138.02895 | G83: 2409956 | H83: =(G83-'Descriptive Stats'!$B$55)/('Descriptive Stats'!$B$56-'Descriptive Stats'!$B$55) -> 0.13233976 | I83: =E83/E82 -> 0.98088498 | J83: =I83-1 -> -0.019115023 | K83: =C83-D83 -> 11.5 | L83: =(K83-'Descriptive Stats'!$B$60)/('Descriptive Stats'!$B$61-'Descriptive Stats'!$B$60) -> 0.30624104 | M83: =((E83-E82)/E82)*100 -> -1.9115023 | N83: =(M83-'Descriptive Stats'!$B$65)/('Descriptive Stats'!$B$66-'Descriptive Stats'!$B$65) -> 0.31712166 | O83: =((G83-G82)/G82)*100 -> 87.786487 | Q83: 0 | U83: 29/11/23 | V83: 7.252 | W83: 7.258 | X83: 7.258 | Y83: 7.237
A84: 44410 | B84: 141.95 | C84: 142 | D84: 136 | E84: 136.95 | F84: 136.43495 | G84: 645887 | H84: =(G84-'Descriptive Stats'!$B$55)/('Descriptive Stats'!$B$56-'Descriptive Stats'!$B$55) -> 0.033106163 | I84: =E84/E83 -> 0.98845178 | J84: =I84-1 -> -0.011548221 | K84: =C84-D84 -> 6 | L84: =(K84-'Descriptive Stats'!$B$60)/('Descriptive Stats'!$B$61-'Descriptive Stats'!$B$60) -> 0.14658936 | M84: =((E84-E83)/E83)*100 -> -1.1548221 | N84: =(M84-'Descriptive Stats'!$B$65)/('Descriptive Stats'!$B$66-'Descriptive Stats'!$B$65) -> 0.34556543 | O84: =((G84-G83)/G83)*100 -> -73.19922 | Q84: 0 | U84: 28/11/23 | V84: 7.273 | W84: 7.258 | X84: 7.277 | Y84: 7.253
A85: 44411 | B85: 138 | C85: 139 | D85: 135.5 | E85: 136.14999 | F85: 135.63796 | G85: 444932 | H85: =(G85-'Descriptive Stats'!$B$55)/('Descriptive Stats'!$B$56-'Descriptive Stats'!$B$55) -> 0.021801906 | I85: =E85/E84 -> 0.99415843 | J85: =I85-1 -> -0.00584157 | K85: =C85-D85 -> 3.5 | L85: =(K85-'Descriptive Stats'!$B$60)/('Descriptive Stats'!$B$61-'Descriptive Stats'!$B$60) -> 0.074020413 | M85: =((E85-E84)/E84)*100 -> -0.584157 | N85: =(M85-'Descriptive Stats'!$B$65)/('Descriptive Stats'!$B$66-'Descriptive Stats'!$B$65) -> 0.36701686 | O85: =((G85-G84)/G84)*100 -> -31.113028 | Q85: 0 | U85: 24/11/23 | V85: 7.272 | W85: 7.278 | X85: 7.291 | Y85: 7.266
A86: 44412 | B86: 137.2 | C86: 140.8 | D86: 133.60001 | E86: 134.64999 | F86: 134.1436 | G86: 1003908 | H86: =(G86-'Descriptive Stats'!$B$55)/('Descriptive Stats'!$B$56-'Descriptive Stats'!$B$55) -> 0.053245802 | I86: =E86/E85 -> 0.98898274 | J86: =I86-1 -> -0.011017261 | K86: =C86-D86 -> 7.199997 | L86: =(K86-'Descriptive Stats'!$B$60)/('Descriptive Stats'!$B$61-'Descriptive Stats'!$B$60) -> 0.18142237 | M86: =((E86-E85)/E85)*100 -> -1.1017261 | N86: =(M86-'Descriptive Stats'!$B$65)/('Descriptive Stats'!$B$66-'Descriptive Stats'!$B$65) -> 0.34756132 | O86: =((G86-G85)/G85)*100 -> 125.63178 | Q86: 0 | U86: 23/11/23 | V86: 7.253 | W86: 7.258 | X86: 7.263 | Y86: 7.246
A87: 44413 | B87: 135.5 | C87: 137.25 | D87: 133.55 | E87: 135 | F87: 134.49229 | G87: 485937 | H87: =(G87-'Descriptive Stats'!$B$55)/('Descriptive Stats'!$B$56-'Descriptive Stats'!$B$55) -> 0.024108547 | I87: =E87/E86 -> 1.0025994 | J87: =I87-1 -> 0.0025993763 | K87: =C87-D87 -> 3.699997 | L87: =(K87-'Descriptive Stats'!$B$60)/('Descriptive Stats'!$B$61-'Descriptive Stats'!$B$60) -> 0.079825841 | M87: =((E87-E86)/E86)*100 -> 0.25993763 | N87: =(M87-'Descriptive Stats'!$B$65)/('Descriptive Stats'!$B$66-'Descriptive Stats'!$B$65) -> 0.39874655 | O87: =((G87-G86)/G86)*100 -> -51.595465 | Q87: 0 | U87: 22/11/23 | V87: 7.247 | W87: 7.277 | X87: 7.277 | Y87: 7.245
A88: 44414 | B88: 135.39999 | C88: 136.75 | D88: 134 | E88: 134.89999 | F88: 134.39265 | G88: 270554 | H88: =(G88-'Descriptive Stats'!$B$55)/('Descriptive Stats'!$B$56-'Descriptive Stats'!$B$55) -> 0.011992677 | I88: =E88/E87 -> 0.99925921 | J88: =I88-1 -> -0.00074078519 | K88: =C88-D88 -> 2.75 | L88: =(K88-'Descriptive Stats'!$B$60)/('Descriptive Stats'!$B$61-'Descriptive Stats'!$B$60) -> 0.052249729 | M88: =((E88-E87)/E87)*100 -> -0.074078519 | N88: =(M88-'Descriptive Stats'!$B$65)/('Descriptive Stats'!$B$66-'Descriptive Stats'!$B$65) -> 0.38619082 | O88: =((G88-G87)/G87)*100 -> -44.323235 | Q88: 0 | U88: 21/11/23 | V88: 7.269 | W88: 7.247 | X88: 7.272 | Y88: 7.237
A89: 44417 | B89: 135.89999 | C89: 136.39999 | D89: 130.39999 | E89: 131.60001 | F89: 131.10509 | G89: 343546 | H89: =(G89-'Descriptive Stats'!$B$55)/('Descriptive Stats'!$B$56-'Descriptive Stats'!$B$55) -> 0.016098672 | I89: =E89/E88 -> 0.97553752 | J89: =I89-1 -> -0.024462477 | K89: =C89-D89 -> 6 | L89: =(K89-'Descriptive Stats'!$B$60)/('Descriptive Stats'!$B$61-'Descriptive Stats'!$B$60) -> 0.14658936 | M89: =((E89-E88)/E88)*100 -> -2.4462477 | N89: =(M89-'Descriptive Stats'!$B$65)/('Descriptive Stats'!$B$66-'Descriptive Stats'!$B$65) -> 0.29702047 | O89: =((G89-G88)/G88)*100 -> 26.978718 | Q89: 0 | U89: 20/11/23 | V89: 7.252 | W89: 7.23 | X89: 7.257 | Y89: 7.224
A90: 44418 | B90: 131.85001 | C90: 132.64999 | D90: 121 | E90: 122.95 | F90: 122.4876 | G90: 964165 | H90: =(G90-'Descriptive Stats'!$B$55)/('Descriptive Stats'!$B$56-'Descriptive Stats'!$B$55) -> 0.051010152 | I90: =E90/E89 -> 0.93427045 | J90: =I90-1 -> -0.065729549 | K90: =C90-D90 -> 11.649994 | L90: =(K90-'Descriptive Stats'!$B$60)/('Descriptive Stats'!$B$61-'Descriptive Stats'!$B$60) -> 0.31059501 | M90: =((E90-E89)/E89)*100 -> -6.5729549 | N90: =(M90-'Descriptive Stats'!$B$65)/('Descriptive Stats'!$B$66-'Descriptive Stats'!$B$65) -> 0.14189666 | O90: =((G90-G89)/G89)*100 -> 180.65092 | Q90: 0 | U90: 17/11/23 | V90: 7.212 | W90: 7.226 | X90: 7.23 | Y90: 7.194
A91: 44419 | B91: 122.3 | C91: 129.5 | D91: 118 | E91: 125.9 | F91: 125.42651 | G91: 636124 | H91: =(G91-'Descriptive Stats'!$B$55)/('Descriptive Stats'!$B$56-'Descriptive Stats'!$B$55) -> 0.032556968 | I91: =E91/E90 -> 1.0239935 | J91: =I91-1 -> 0.023993535 | K91: =C91-D91 -> 11.5 | L91: =(K91-'Descriptive Stats'!$B$60)/('Descriptive Stats'!$B$61-'Descriptive Stats'!$B$60) -> 0.30624104 | M91: =((E91-E90)/E90)*100 -> 2.3993535 | N91: =(M91-'Descriptive Stats'!$B$65)/('Descriptive Stats'!$B$66-'Descriptive Stats'!$B$65) -> 0.47916765 | O91: =((G91-G90)/G90)*100 -> -34.023326 | Q91: 0 | U91: 16/11/23 | V91: 7.232 | W91: 7.236 | X91: 7.236 | Y91: 7.22
A92: 44420 | B92: 127 | C92: 129.85001 | D92: 126.45 | E92: 128.7 | F92: 128.21597 | G92: 341699 | H92: =(G92-'Descriptive Stats'!$B$55)/('Descriptive Stats'!$B$56-'Descriptive Stats'!$B$55) -> 0.015994773 | I92: =E92/E91 -> 1.0222398 | J92: =I92-1 -> 0.022239833 | K92: =C92-D92 -> 3.400009 | L92: =(K92-'Descriptive Stats'!$B$60)/('Descriptive Stats'!$B$61-'Descriptive Stats'!$B$60) -> 0.071117916 | M92: =((E92-E91)/E91)*100 -> 2.2239833 | N92: =(M92-'Descriptive Stats'!$B$65)/('Descriptive Stats'!$B$66-'Descriptive Stats'!$B$65) -> 0.47257545 | O92: =((G92-G91)/G91)*100 -> -46.284215 | Q92: 0 | U92: 15/11/23 | V92: 7.225 | W92: 7.262 | X92: 7.262 | Y92: 7.22
A93: 44421 | B93: 129.2 | C93: 130 | D93: 126.45 | E93: 127.7 | F93: 127.21974 | G93: 238997 | H93: =(G93-'Descriptive Stats'!$B$55)/('Descriptive Stats'!$B$56-'Descriptive Stats'!$B$55) -> 0.010217511 | I93: =E93/E92 -> 0.99222999 | J93: =I93-1 -> -0.007770008 | K93: =C93-D93 -> 3.550003 | L93: =(K93-'Descriptive Stats'!$B$60)/('Descriptive Stats'!$B$61-'Descriptive Stats'!$B$60) -> 0.075471879 | M93: =((E93-E92)/E92)*100 -> -0.7770008 | N93: =(M93-'Descriptive Stats'!$B$65)/('Descriptive Stats'!$B$66-'Descriptive Stats'!$B$65) -> 0.35976782 | O93: =((G93-G92)/G92)*100 -> -30.056278 | Q93: 0 | U93: 13/11/23 | V93: 7.283 | W93: 7.316 | X93: 7.316 | Y93: 7.281
A94: 44424 | B94: 126.55 | C94: 127.95 | D94: 124.4 | E94: 125.05 | F94: 124.57971 | G94: 147945 | H94: =(G94-'Descriptive Stats'!$B$55)/('Descriptive Stats'!$B$56-'Descriptive Stats'!$B$55) -> 0.0050955924 | I94: =E94/E93 -> 0.97924828 | J94: =I94-1 -> -0.020751715 | K94: =C94-D94 -> 3.549995 | L94: =(K94-'Descriptive Stats'!$B$60)/('Descriptive Stats'!$B$61-'Descriptive Stats'!$B$60) -> 0.075471647 | M94: =((E94-E93)/E93)*100 -> -2.0751715 | N94: =(M94-'Descriptive Stats'!$B$65)/('Descriptive Stats'!$B$66-'Descriptive Stats'!$B$65) -> 0.3109693 | O94: =((G94-G93)/G93)*100 -> -38.097549 | Q94: 0 | U94: 45210 | V94: 7.3 | W94: 7.293 | X94: 7.305 | Y94: 7.288
A95: 44425 | B95: 125.45 | C95: 125.85 | D95: 119.3 | E95: 122.05 | F95: 121.591 | G95: 216331 | H95: =(G95-'Descriptive Stats'!$B$55)/('Descriptive Stats'!$B$56-'Descriptive Stats'!$B$55) -> 0.0089424879 | I95: =E95/E94 -> 0.9760096 | J95: =I95-1 -> -0.023990403 | K95: =C95-D95 -> 6.549995 | L95: =(K95-'Descriptive Stats'!$B$60)/('Descriptive Stats'!$B$61-'Descriptive Stats'!$B$60) -> 0.16255438 | M95: =((E95-E94)/E94)*100 -> -2.3990403 | N95: =(M95-'Descriptive Stats'!$B$65)/('Descriptive Stats'!$B$66-'Descriptive Stats'!$B$65) -> 0.298795 | O95: =((G95-G94)/G94)*100 -> 46.223935 | Q95: 0 | U95: 45180 | V95: 7.269 | W95: 7.256 | X95: 7.276 | Y95: 7.246
A96: 44426 | B96: 122.6 | C96: 122.6 | D96: 118.35 | E96: 119.15 | F96: 118.7019 | G96: 239704 | H96: =(G96-'Descriptive Stats'!$B$55)/('Descriptive Stats'!$B$56-'Descriptive Stats'!$B$55) -> 0.010257282 | I96: =E96/E95 -> 0.97623924 | J96: =I96-1 -> -0.023760761 | K96: =C96-D96 -> 4.25 | L96: =(K96-'Descriptive Stats'!$B$60)/('Descriptive Stats'!$B$61-'Descriptive Stats'!$B$60) -> 0.095791097 | M96: =((E96-E95)/E95)*100 -> -2.3760761 | N96: =(M96-'Descriptive Stats'!$B$65)/('Descriptive Stats'!$B$66-'Descriptive Stats'!$B$65) -> 0.29965823 | O96: =((G96-G95)/G95)*100 -> 10.804277 | Q96: 0 | U96: 45149 | V96: 7.266 | W96: 7.273 | X96: 7.281 | Y96: 7.255
A97: 44428 | B97: 117.5 | C97: 119.2 | D97: 114.5 | E97: 115.15 | F97: 114.71694 | G97: 334138 | H97: =(G97-'Descriptive Stats'!$B$55)/('Descriptive Stats'!$B$56-'Descriptive Stats'!$B$55) -> 0.015569447 | I97: =E97/E96 -> 0.96642887 | J97: =I97-1 -> -0.033571128 | K97: =C97-D97 -> 4.699997 | L97: =(K97-'Descriptive Stats'!$B$60)/('Descriptive Stats'!$B$61-'Descriptive Stats'!$B$60) -> 0.10885342 | M97: =((E97-E96)/E96)*100 -> -3.3571128 | N97: =(M97-'Descriptive Stats'!$B$65)/('Descriptive Stats'!$B$66-'Descriptive Stats'!$B$65) -> 0.26278085 | O97: =((G97-G96)/G96)*100 -> 39.396089 | Q97: 0 | U97: 45118 | V97: 7.28 | W97: 7.318 | X97: 7.318 | Y97: 7.277
A98: 44431 | B98: 115.35 | C98: 125.65 | D98: 112.05 | E98: 122.75 | F98: 122.28836 | G98: 755091 | H98: =(G98-'Descriptive Stats'!$B$55)/('Descriptive Stats'!$B$56-'Descriptive Stats'!$B$55) -> 0.03924918 | I98: =E98/E97 -> 1.0660008 | J98: =I98-1 -> 0.06600085 | K98: =C98-D98 -> 13.599999 | L98: =(K98-'Descriptive Stats'!$B$60)/('Descriptive Stats'!$B$61-'Descriptive Stats'!$B$60) -> 0.36719893 | M98: =((E98-E97)/E97)*100 -> 6.600085 | N98: =(M98-'Descriptive Stats'!$B$65)/('Descriptive Stats'!$B$66-'Descriptive Stats'!$B$65) -> 0.63707405 | O98: =((G98-G97)/G97)*100 -> 125.98178 | Q98: 0 | U98: 45088 | V98: 7.305 | W98: 7.301 | X98: 7.307 | Y98: 7.294
A99: 44432 | B99: 124.05 | C99: 124.8 | D99: 118.5 | E99: 119.45 | F99: 119.00077 | G99: 389980 | H99: =(G99-'Descriptive Stats'!$B$55)/('Descriptive Stats'!$B$56-'Descriptive Stats'!$B$55) -> 0.018710709 | I99: =E99/E98 -> 0.97311607 | J99: =I99-1 -> -0.026883935 | K99: =C99-D99 -> 6.300003 | L99: =(K99-'Descriptive Stats'!$B$60)/('Descriptive Stats'!$B$61-'Descriptive Stats'!$B$60) -> 0.15529772 | M99: =((E99-E98)/E98)*100 -> -2.6883935 | N99: =(M99-'Descriptive Stats'!$B$65)/('Descriptive Stats'!$B$66-'Descriptive Stats'!$B$65) -> 0.28791816 | O99: =((G99-G98)/G98)*100 -> -48.353245 | Q99: 0 | U99: 44996 | V99: 7.317 | W99: 7.324 | X99: 7.324 | Y99: 7.309
A100: 44433 | B100: 120.95 | C100: 120.95 | D100: 116 | E100: 116.7 | F100: 116.26111 | G100: 306628 | H100: =(G100-'Descriptive Stats'!$B$55)/('Descriptive Stats'!$B$56-'Descriptive Stats'!$B$55) -> 0.014021936 | I100: =E100/E99 -> 0.97697781 | J100: =I100-1 -> -0.023022186 | K100: =C100-D100 -> 4.949997 | L100: =(K100-'Descriptive Stats'!$B$60)/('Descriptive Stats'!$B$61-'Descriptive Stats'!$B$60) -> 0.11611031 | M100: =((E100-E99)/E99)*100 -> -2.3022186 | N100: =(M100-'Descriptive Stats'!$B$65)/('Descriptive Stats'!$B$66-'Descriptive Stats'!$B$65) -> 0.30243455 | O100: =((G100-G99)/G99)*100 -> -21.373404 | Q100: 0 | U100: 44968 | V100: 7.322 | W100: 7.323 | X100: 7.335 | Y100: 7.318
...

Sheet Historical Data Monthly
A1: Date | B1: Open | C1: High | D1: Low | E1: Close | F1: Adj Close | G1: Volume | H1: HPR | I1: HPY
A2: 44287 | B2: 106.5 | C2: 121.25 | D2: 102 | E2: 111.7 | F2: 111.27992 | G2: 18016486
A3: 44317 | B3: 111.05 | C3: 157.8 | D3: 111.05 | E3: 135.10001 | F3: 134.59192 | G3: 30618661 | H3: =E3/E2 -> 1.2094898 | I3: =H3-1 -> 0.20948979
A4: 44348 | B4: 137.5 | C4: 150.5 | D4: 133.05 | E4: 136.60001 | F4: 136.08627 | G4: 19306625 | H4: =E4/E3 -> 1.0111029 | I4: =H4-1 -> 0.011102886
A5: 44378 | B5: 136.7 | C5: 148.60001 | D5: 130.5 | E5: 138.55 | F5: 138.02895 | G5: 16815794 | H5: =E5/E4 -> 1.0142752 | I5: =H5-1 -> 0.014275234
A6: 44409 | B6: 141.95 | C6: 142 | D6: 112.05 | E6: 132.89999 | F6: 132.40018 | G6: 11505147 | H6: =E6/E5 -> 0.95922043 | I6: =H6-1 -> -0.040779566
A7: 44440 | B7: 134 | C7: 140 | D7: 120.75 | E7: 125.95 | F7: 125.47633 | G7: 12245363 | H7: =E7/E6 -> 0.94770506 | I7: =H7-1 -> -0.052294938
A8: 44470 | B8: 125.45 | C8: 149.7 | D8: 125 | E8: 134.35001 | F8: 134.35001 | G8: 14081301 | H8: =E8/E7 -> 1.0666932 | I8: =H8-1 -> 0.066693205
A9: 44501 | B9: 134.95 | C9: 159.89999 | D9: 121.15 | E9: 122.75 | F9: 122.75 | G9: 17825231 | H9: =E9/E8 -> 0.91365831 | I9: =H9-1 -> -0.086341686
A10: 44531 | B10: 123.5 | C10: 126.1 | D10: 102.1 | E10: 111.8 | F10: 111.8 | G10: 12946094 | H10: =E10/E9 -> 0.91079432 | I10: =H10-1 -> -0.089205678
A11: 44562 | B11: 112 | C11: 125.45 | D11: 109.5 | E11: 109.95 | F11: 109.95 | G11: 10311626 | H11: =E11/E10 -> 0.98345254 | I11: =H11-1 -> -0.016547459
A12: 44593 | B12: 110.05 | C12: 119.2 | D12: 95.099998 | E12: 100.5 | F12: 100.5 | G12: 6988108 | H12: =E12/E11 -> 0.91405187 | I12: =H12-1 -> -0.085948133
A13: 44621 | B13: 100.5 | C13: 105.75 | D13: 95 | E13: 96.75 | F13: 96.75 | G13: 9704704 | H13: =E13/E12 -> 0.96268657 | I13: =H13-1 -> -0.037313433
A14: 44652 | B14: 96.599998 | C14: 112.4 | D14: 96.599998 | E14: 100.95 | F14: 100.95 | G14: 7983568 | H14: =E14/E13 -> 1.0434108 | I14: =H14-1 -> 0.043410822
... A37: 45352 | B37: 245.55 | C37: 250.8 | D37: 188.39999 | E37: 207.89999 | F37: 207.89999 | G37: 23064241 | H37: =E37/E36 -> 0.85555553 | I37: =H37-1 -> -0.14444447

Sheet NIFTY 50 
A1: NIFTY 50 DAILY | L1: NIFTY 50 MONTHLY
A2: Date | B2: Open | C2: High | D2: Low | E2: Close | F2: Adj Close | G2: Volume | H2: HPR | I2: HPY | J2: CHG % | L2: Date | M2: Open | N2: High | O2: Low | P2: Close | Q2: Adj Close | R2: Volume | S2: HPR | T2: HPY
A3: 44287 | B3: 14798.4 | C3: 14883.2 | D3: 14692.45 | E3: 14867.35 | F3: 14867.35 | G3: 445000 | L3: 44287 | M3: 14798.4 | N3: 15044.35 | O3: 14151.4 | P3: 14631.1 | Q3: 14631.1 | R3: 9344700
A4: 44291 | B4: 14837.7 | C4: 14849.85 | D4: 14459.5 | E4: 14637.8 | F4: 14637.8 | G4: 509700 | H4: =(E4/E3) -> 0.98456014 | I4: =H4-1 -> -0.01543986 | J4: =((E4-E3)/E3)*100 -> -1.543986 | L4: 44317 | M4: 14481.05 | N4: 15606.35 | O4: 14416.25 | P4: 15582.8 | Q4: 15582.8 | R4: 9859900 | S4: =P4/P3 -> 1.0650464 | T4: =S4-1 -> 0.065046389
A5: 44292 | B5: 14737 | C5: 14779.1 | D5: 14573.9 | E5: 14683.5 | F5: 14683.5 | G5: 475300 | H5: =(E5/E4) -> 1.0031221 | I5: =H5-1 -> 0.0031220672 | J5: =((E5-E4)/E4)*100 -> 0.31220672 | L5: 44348 | M5: 15629.65 | N5: 15915.65 | O5: 15450.9 | P5: 15721.5 | Q5: 15721.5 | R5: 8079100 | S5: =P5/P4 -> 1.0089009 | T5: =S5-1 -> 0.008900852
A6: 44293 | B6: 14716.45 | C6: 14879.8 | D6: 14649.85 | E6: 14819.05 | F6: 14819.05 | G6: 0 | H6: =(E6/E5) -> 1.0092314 | I6: =H6-1 -> 0.009231437 | J6: =((E6-E5)/E5)*100 -> 0.9231437 | L6: 44378 | M6: 15755.05 | N6: 15962.25 | O6: 15513.45 | P6: 15763.05 | Q6: 15763.05 | R6: 5756800 | S6: =P6/P5 -> 1.0026429 | T6: =S6-1 -> 0.0026428652
A7: 44294 | B7: 14875.65 | C7: 14984.15 | D7: 14821.1 | E7: 14873.8 | F7: 14873.8 | G7: 514800 | H7: =(E7/E6) -> 1.0036946 | I7: =H7-1 -> 0.0036945689 | J7: =((E7-E6)/E6)*100 -> 0.36945689 | L7: 44409 | M7: 15874.9 | N7: 17153.5 | O7: 15834.65 | P7: 17132.199 | Q7: 17132.199 | R7: 6349900 | S7: =P7/P6 -> 1.0868582 | T7: =S7-1 -> 0.086858154
A8: 44295 | B8: 14882.65 | C8: 14918.45 | D8: 14785.65 | E8: 14834.85 | F8: 14834.85 | G8: 504100 | H8: =(E8/E7) -> 0.99738129 | I8: =H8-1 -> -0.0026187119 | J8: =((E8-E7)/E7)*100 -> -0.26187119 | L8: 44440 | M8: 17185.6 | N8: 17947.65 | O8: 17055.051 | P8: 17618.15 | Q8: 17618.15 | R8: 6955600 | S8: =P8/P7 -> 1.0283648 | T8: =S8-1 -> 0.028364786
A9: 44298 | B9: 14644.65 | C9: 14652.5 | D9: 14248.7 | E9: 14310.8 | F9: 14310.8 | G9: 650200 | H9: =(E9/E8) -> 0.96467441 | I9: =H9-1 -> -0.035325589 | J9: =((E9-E8)/E8)*100 -> -3.5325589 | L9: 44470 | M9: 17531.9 | N9: 18604.449 | O9: 17452.9 | P9: 17671.65 | Q9: 17671.65 | R9: 7651200 | S9: =P9/P8 -> 1.0030366 | T9: =S9-1 -> 0.0030366411
A10: 44299 | B10: 14364.9 | C10: 14528.9 | D10: 14274.9 | E10: 14504.8 | F10: 14504.8 | G10: 605100 | H10: =(E10/E9) -> 1.0135562 | I10: =H10-1 -> 0.013556196 | J10: =((E10-E9)/E9)*100 -> 1.3556196 | L10: 44501 | M10: 17783.15 | N10: 18210.15 | O10: 16782.4 | P10: 16983.199 | Q10: 16983.199 | R10: 5853100 | S10: =P10/P9 -> 0.96104206 | T10: =S10-1 -> -0.038957944
A11: 44301 | B11: 14522.4 | C11: 14597.55 | D11: 14353.2 | E11: 14581.45 | F11: 14581.45 | G11: 568000 | H11: =(E11/E10) -> 1.0052845 | I11: =H11-1 -> 0.0052844845 | J11: =((E11-E10)/E10)*100 -> 0.52844845 | L11: 44531 | M11: 17104.4 | N11: 17639.5 | O11: 16410.199 | P11: 17354.051 | Q11: 17354.051 | R11: 5499300 | S11: =P11/P10 -> 1.0218364 | T11: =S11-1 -> 0.021836378
A12: 44302 | B12: 14599.6 | C12: 14697.7 | D12: 14559 | E12: 14617.85 | F12: 14617.85 | G12: 577200 | H12: =(E12/E11) -> 1.0024963 | I12: =H12-1 -> 0.0024962822 | J12: =((E12-E11)/E11)*100 -> 0.24962822 | L12: 44562 | M12: 17387.15 | N12: 18350.949 | O12: 16836.801 | P12: 17339.85 | Q12: 17339.85 | R12: 5435500 | S12: =P12/P11 -> 0.99918168 | T12: =S12-1 -> -0.0008183203
A13: 44305 | B13: 14306.6 | C13: 14382.3 | D13: 14191.4 | E13: 14359.45 | F13: 14359.45 | G13: 512300 | H13: =(E13/E12) -> 0.98232302 | I13: =H13-1 -> -0.017676979 | J13: =((E13-E12)/E12)*100 -> -1.7676979 | L13: 44593 | M13: 17529.449 | N13: 17794.6 | O13: 16203.25 | P13: 16793.9 | Q13: 16793.9 | R13: 5620100 | S13: =P13/P12 -> 0.96851477 | T13: =S13-1 -> -0.031485234
A14: 44306 | B14: 14526.7 | C14: 14526.95 | D14: 14207.3 | E14: 14296.4 | F14: 14296.4 | G14: 467400 | H14: =(E14/E13) -> 0.99560918 | I14: =H14-1 -> -0.004390823 | J14: =((E14-E13)/E13)*100 -> -0.4390823 | L14: 44621 | M14: 16593.1 | N14: 17559.801 | O14: 15671.45 | P14: 17464.75 | Q14: 17464.75 | R14: 7959500 | S14: =P14/P13 -> 1.039946 | T14: =S14-1 -> 0.039946028
A15: 44308 | B15: 14219.15 | C15: 14424.75 | D15: 14151.4 | E15: 14406.15 | F15: 14406.15 | G15: 524600 | H15: =(E15/E14) -> 1.0076768 | I15: =H15-1 -> 0.0076767576 | J15: =((E15-E14)/E14)*100 -> 0.76767576 | L15: 44652 | M15: 17436.9 | N15: 18114.65 | O15: 16824.699 | P15: 17102.551 | Q15: 17102.551 | R15: 5658100 | S15: =P15/P14 -> 0.97926113 | T15: =S15-1 -> -0.020738872
... A38: 44342 | B38: 15257.05 | C38: 15319.9 | D38: 15194.95 | E38: 15301.45 | F38: 15301.45 | G38: 384000 | H38: =(E38/E37) -> 1.006115 | I38: =H38-1 -> 0.0061150215 | J38: =((E38-E37)/E37)*100 -> 0.61150215 | L38: 45352 | M38: 22048.301 | N38: 22526.6 | O38: 21710.199 | P38: 22326.9 | Q38: 22326.9 | R38: 6700100 | S38: =P38/P37 -> 1.0156531 | T38: =S38-1 -> 0.015653129
A39: 44343 | B39: 15323.95 | C39: 15384.55 | D39: 15272.5 | E39: 15337.85 | F39: 15337.85 | G39: 0 | H39: =(E39/E38) -> 1.0023788 | I39: =H39-1 -> 0.0023788212 | J39: =((E39-E38)/E38)*100 -> 0.23788212
A40: 44344 | B40: 15421.2 | C40: 15469.65 | D40: 15394.75 | E40: 15435.65 | F40: 15435.65 | G40: 468100 | H40: =(E40/E39) -> 1.0063764 | I40: =H40-1 -> 0.0063764338 | J40: =((E40-E39)/E39)*100 -> 0.63764338
A41: 44347 | B41: 15437.75 | C41: 15606.35 | D41: 15374 | E41: 15582.8 | F41: 15582.8 | G41: 436000 | H41: =(E41/E40) -> 1.0095331 | I41: =H41-1 -> 0.009533088 | J41: =((E41-E40)/E40)*100 -> 0.9533088
A42: 44348 | B42: 15629.65 | C42: 15660.75 | D42: 15528.3 | E42: 15574.85 | F42: 15574.85 | G42: 409600 | H42: =(E42/E41) -> 0.99948981 | I42: =H42-1 -> -0.00051019047 | J42: =((E42-E41)/E41)*100 -> -0.051019047
A43: 44349 | B43: 15520.35 | C43: 15597.45 | D43: 15459.85 | E43: 15576.2 | F43: 15576.2 | G43: 428600 | H43: =(E43/E42) -> 1.0000867 | I43: =H43-1 -> 8.6715829e-05 | J43: =((E43-E42)/E42)*100 -> 0.0086715829
A44: 44350 | B44: 15655.55 | C44: 15705.1 | D44: 15611 | E44: 15690.35 | F44: 15690.35 | G44: 410200 | H44: =(E44/E43) -> 1.0073285 | I44: =H44-1 -> 0.0073284506 | J44: =((E44-E43)/E43)*100 -> 0.73284506
A45: 44351 | B45: 15712.5 | C45: 15733.6 | D45: 15622.35 | E45: 15670.25 | F45: 15670.25 | G45: 414200 | H45: =(E45/E44) -> 0.99871898 | I45: =H45-1 -> -0.0012810173 | J45: =((E45-E44)/E44)*100 -> -0.12810173
A46: 44354 | B46: 15725.1 | C46: 15773.45 | D46: 15678.1 | E46: 15751.65 | F46: 15751.65 | G46: 394000 | H46: =(E46/E45) -> 1.0051946 | I46: =H46-1 -> 0.0051945815 | J46: =((E46-E45)/E45)*100 -> 0.51945815
A47: 44355 | B47: 15773.9 | C47: 15778.8 | D47: 15680 | E47: 15740.1 | F47: 15740.1 | G47: 378200 | H47: =(E47/E46) -> 0.99926669 | I47: =H47-1 -> -0.00073330614 | J47: =((E47-E46)/E46)*100 -> -0.073330614
A48: 44356 | B48: 15766.3 | C48: 15800.45 | D48: 15566.9 | E48: 15635.35 | F48: 15635.35 | G48: 457900 | H48: =(E48/E47) -> 0.99334502 | I48: =H48-1 -> -0.0066549769 | J48: =((E48-E47)/E47)*100 -> -0.66549769
A49: 44357 | B49: 15692.1 | C49: 15751.25 | D49: 15648.5 | E49: 15737.75 | F49: 15737.75 | G49: 298300 | H49: =(E49/E48) -> 1.0065493 | I49: =H49-1 -> 0.0065492869 | J49: =((E49-E48)/E48)*100 -> 0.65492869
A50: 44358 | B50: 15796.45 | C50: 15835.55 | D50: 15749.8 | E50: 15799.35 | F50: 15799.35 | G50: 363000 | H50: =(E50/E49) -> 1.0039141 | I50: =H50-1 -> 0.0039141306 | J50: =((E50-E49)/E49)*100 -> 0.39141306
... A742: 45379 | B742: 22163.6 | C742: 22516 | D742: 22163.6 | E742: 22326.9 | F742: 22326.9 | G742: 410500 | H742: =(E742/E741) -> 1.009187 | I742: =H742-1 -> 0.0091870011 | J742: =((E742-E741)/E741)*100 -> 0.91870011

Sheet Descriptive Stats
C1: GRAPHS HERE
A2: Measures of Risk and Return | C2: Considering the exceptionally low volatility, minimal market correlation, and negative return measures, this stock is likely a: Stable-Value Stock: These stocks are known for their low volatility and reliable dividends. The minimal correlation with the market and low average daily return suggest this could be the case. However, the negative alpha and Sharpe Ratio indicate underperformance, which is not ideal for a value stock. Cash Equivalent: This is a possibility if the stock price barely moves and offers a return close to the risk-free rate (represented by the market return in this case). However, companies typically don't issue stock that behaves like a cash equivalent. Sharpe ratio (0.030) suggests a positive but modest risk-adjusted performance for the stock. This means the investment's returns are exceeding the risk-free rate, but the margin relative to its volatility is lower. A beta(0.082) this close to zero suggests the stock's price movements have minimal correlation with the market (represented by the market return) Standard Deviation (0.0294): This is exceptionally low, indicating extremely low volatility in the daily stock price movements. The difference in beta values for monthly (0.121) and daily sampling (0.081) suggests the stock's risk profile might be more sensitive to short-term market noise compared to its long-term fundamentals.
A3: Standard Deviation | B3: =stdev('Historical Data Daily'!J:J) -> 0.02936242
A4: Annualised Standard Deviation | B4: =B3*(365)^1/2 -> 5.3586416
A5: Mean | B5: =AVERAGE('Historical Data Daily'!J:J) -> 0.0012656677
A6: Beta Daily Sampling | B6: =COVAR('Historical Data Daily'!J3:J741,'NIFTY 50 '!I4:I742)/VAR('NIFTY 50 '!I4:I742) -> 0.93514318
A7: Beta Monthly Sampling | B7: =COVAR('Historical Data Monthly'!I2:I37,'NIFTY 50 '!T3:T38)/var('NIFTY 50 '!T3:T38) -> 1.6744687
A8: Sharpe Ratio | B8: =(B10-(B14/100))/B4 -> 0.030160201
A9: Alpha | B9: =B12 - (B14 + B6*(B13-B14)) -> -0.44927893
A10: Average Annual Return | B10: =('Historical Data Daily'!E741/'Historical Data Daily'!E2)^(1/3) -1 -> 0.23100024
A11: Coefficient of Variation | B11: =(B3/B5) -> 23.199154
A12: Average Return | B12: =AVERAGEA('Historical Data Daily'!J:J) -> 0.0012639574
A13: Market return | B13: =average('NIFTY 50 '!I:I) -> 0.00058793461
A14: Risk free rate | B14: =AVERAGE('Historical Data Daily'!V:V) -> 6.9382534
A17: Descriptive Stats on Close of the Company | C17: The standard deviation is 48.19, which is less than half the mean closing price of 133.42. This suggests that the stock may be relatively stable, with prices not fluctuating dramatically.
A18: Mean | B18: =AVERAGE('Historical Data Daily'!E2:E741) -> 133.41696
A19: Min Value | B19: =min('Historical Data Daily'!E2:E741) -> 68.300003
A20: Max Value | B20: =max('Historical Data Daily'!E2:E741) -> 280.54999
A21: Standard Deviation | B21: =STDEV('Historical Data Daily'!E2:E741) -> 48.186483
A24: Descriptive Stats on correlation of NIFTY 50 and Company's Stock Price | C24: Based on the correlation of 0.739, the company's stock price has a strong positive correlation with NIFTY 50. A correlation coefficient closer to 1 signifies a stronger positive correlation, meaning the stock price mostly moves in tandem with the NIFTY 50. Given the strong positive correlation, this stock appears to be a cyclical stock. Cyclical stocks tend to amplify the market's movements.
A25: Correlation | B25: =CORREL('Historical Data Daily'!E2:E741, 'NIFTY 50 '!E3:E742) -> 0.73835701
A28: Daily Movement in stock price (Spread: High-Low) | B28: ( Sentiment Analysis) | C28: Moderate Volatility: The stock exhibits moderate volatility, suggesting it's not a low-risk, stable investment but also not an extremely risky, high-fluctuation stock. Limited Sentiment Impact: The negligible correlation between sentiment analysis and price movement indicates that short-term price movements are likely driven by factors other than immediate corporate announcements. Based on the analysis, this stock could be: Growth Stock: These aim for high capital appreciation and might experience moderate volatility due to potential for high future earnings but uncertainty in the short term. Sectoral Stock: Its performance might be more tied to its industry's health than overall market sentiment.
A29: Mean | B29: =AVERAGE('Historical Data Daily'!K:K) -> 6.0075671
A30: Median | B30: =MEDIAN('Historical Data Daily'!K:K) -> 4.9000015
A31: Max Value | B31: =max('Historical Data Daily'!K:K) -> 35.399994
A32: Min Value | B32: =min('Historical Data Daily'!K:K) -> 0.949997
A33: Standard Deviation | B33: =stdev('Historical Data Daily'!K:K) -> 4.3134309
A34: Correlation between corporate announcements and volatility in a day | B34: =correl('Historical Data Daily'!K:K, 'Historical Data Daily'!Q:Q) -> 0.027374891
C36: DATE
A37: Lifetime High | B37: =max('Historical Data Daily'!C2:C741) -> 289.75 | C37: 45334
A38: Lifetime Low | B38: =min('Historical Data Daily'!D2:D741) -> 65.5 | C38: 44743
A39: 52 Week High | B39: =max('Historical Data Daily'!C499:C741) -> 289.75 | C39: 45334
A40: 52 Week Low | B40: =min('Historical Data Daily'!D499:D741) -> 74.400002 | C40: 44755
A44: Volatility of Stock | C44: In this case, with a weak positive correlation, the stock's price movements might be influenced by a combination of factors: Company Fundamentals, Industry Trends, Overall Market Conditions
A45: Correlation btw Volume and Change occurred in Stock Price | B45: =CORREL('Historical Data Daily'!N:N,'Historical Data Daily'!H:H) -> 0.489663
A48: TIme | B48: Daily Sampling | C48: Monthly Sampling | D48: 2021-2022: High daily beta (1.049) and a negative monthly beta (-0.003) indicate a complex relationship with the market. The investment might have been somewhat independent in the long term (negative monthly beta) but still susceptible to short-term market movements (high daily beta). The investment might have been in a growth phase or undergoing significant changes, leading to price movements not fully reflected in the overall market. 2022-2023 & 2023-2024: Both daily and monthly betas are very close to zero. This suggests the investment's price movements became largely independent of the market during these periods. The investment's fundamentals might have matured, or the market sector it operates in might have become less volatile. This could explain the near-zero beta, indicating minimal correlation with the market.
A49: 2021-2024 | B49: =B6 -> 0.93514318 | C49: =B7 -> 1.6744687
A50: 2021-2022 | B50: =COVAR('Historical Data Daily'!J2:J249,'NIFTY 50 '!I3:I250) / VAR('NIFTY 50 '!I3:I250) -> 1.049452 | C50: =COVAR('Historical Data Monthly'!E2:E13,'NIFTY 50 '!P3:P14) / VAR('NIFTY 50 '!P3:P14) -> -0.0032544937
A51: 2022-2023 | B51: =COVAR('Historical Data Daily'!E250:E498,'NIFTY 50 '!E251:E499)/var('NIFTY 50 '!E251:E499) -> 0.008999608 | C51: =COVAR('Historical Data Monthly'!E14:E25,'NIFTY 50 '!P15:P26) / VAR('NIFTY 50 '!P15:Z26) -> 1.0668364e-09
A52: 2023-2024 | B52: =COVAR('Historical Data Daily'!E499:E741,'NIFTY 50 '!E500:E742)/var('NIFTY 50 '!E500:E742) -> 0.031893889 | C52: =COVAR('Historical Data Monthly'!E14:E37,'NIFTY 50 '!P15:P38)/var('NIFTY 50 '!P15:P38) -> 0.02784931
A54: Volume
A55: min | B55: =min('Historical Data Daily'!G2:G741) -> 57361
A56: Max | B56: =max('Historical Data Daily'!G2:G741) -> 17834293
A59: Daily Range
A60: min | B60: =min('Historical Data Daily'!K3:K741) -> 0.949997
A61: max | B61: =max('Historical Data Daily'!K3:K741) -> 35.399994
A64: CHG%
A65: min | B65: =min('Historical Data Daily'!M3:M741) -> -10.347785
A66: max | B66: =max('Historical Data Daily'!M3:M741) -> 16.254884

Sheet Technical Analysis
M1: Date | N1: 10 SMA of Close | O1: Std Dev of Close | P1: EMA (26) | Q1: EMA (12) | R1: MACD | S1: Signal Line | T1: MACD-Signal Line | U1: Upper Band | V1: Lower Band
A2: STRATEGY | B2: TA Strategy | M2: 44287 | P2: 111.45 | Q2: 111.45 | R2: =Q2-P2 -> 0 | S2: 0 | T2: 0
M3: 44291 | P3: =('Historical Data Daily'!E3-P2)*'Historical Data Daily'!$S$13 + P2 -> 111.76852 | Q3: =('Historical Data Daily'!E3-Q2)*'Historical Data Daily'!$S$12 + Q2 -> 112.11154 | R3: =Q3-P3 -> 0.34302018 | S3: =(R3-S2)*'Historical Data Daily'!$S$14 + S2 -> 0.068604036 | T3: =R3-S3 -> 0.27441615
M4: 44292 | P4: =('Historical Data Daily'!E4-P3)*'Historical Data Daily'!$S$13 + P3 -> 112.05974 | Q4: =('Historical Data Daily'!E4-Q3)*'Historical Data Daily'!$S$12 + Q3 -> 112.66361 | R4: =Q4-P4 -> 0.60387028 | S4: =(R4-S3)*'Historical Data Daily'!$S$14 + S3 -> 0.17565729 | T4: =R4-S4 -> 0.428213
M5: 44293 | P5: =('Historical Data Daily'!E5-P4)*'Historical Data Daily'!$S$13 + P4 -> 112.27013 | Q5: =('Historical Data Daily'!E5-Q4)*'Historical Data Daily'!$S$12 + Q4 -> 113.00767 | R5: =Q5-P5 -> 0.73754104 | S5: =(R5-S4)*'Historical Data Daily'!$S$14 + S4 -> 0.28803404 | T5: =R5-S5 -> 0.44950701
M6: 44294 | P6: =('Historical Data Daily'!E6-P5)*'Historical Data Daily'!$S$13 + P5 -> 112.55752 | Q6: =('Historical Data Daily'!E6-Q5)*'Historical Data Daily'!$S$12 + Q5 -> 113.4911 | R6: =Q6-P6 -> 0.93357892 | S6: =(R6-S5)*'Historical Data Daily'!$S$14 + S5 -> 0.41714301 | T6: =R6-S6 -> 0.51643591
M7: 44295 | P7: =('Historical Data Daily'!E7-P6)*'Historical Data Daily'!$S$13 + P6 -> 112.84586 | Q7: =('Historical Data Daily'!E7-Q6)*'Historical Data Daily'!$S$12 + Q6 -> 113.94632 | R7: =Q7-P7 -> 1.100462 | S7: =(R7-S6)*'Historical Data Daily'!$S$14 + S6 -> 0.55380681 | T7: =R7-S7 -> 0.54665519
J8: PRICE MOVEMENT CHART | M8: 44298 | P8: =('Historical Data Daily'!E8-P7)*'Historical Data Daily'!$S$13 + P7 -> 112.22024 | Q8: =('Historical Data Daily'!E8-Q7)*'Historical Data Daily'!$S$12 + Q7 -> 112.47765 | R8: =Q8-P8 -> 0.25741681 | S8: =(R8-S7)*'Historical Data Daily'!$S$14 + S7 -> 0.49452881 | T8: =R8-S8 -> -0.237112
M9: 44299 | P9: =('Historical Data Daily'!E9-P8)*'Historical Data Daily'!$S$13 + P8 -> 111.99652 | Q9: =('Historical Data Daily'!E9-Q8)*'Historical Data Daily'!$S$12 + Q8 -> 111.9734 | R9: =Q9-P9 -> -0.023116623 | S9: =(R9-S8)*'Historical Data Daily'!$S$14 + S8 -> 0.39099972 | T9: =R9-S9 -> -0.41411635
M10: 44301 | P10: =('Historical Data Daily'!E10-P9)*'Historical Data Daily'!$S$13 + P9 -> 111.63381 | Q10: =('Historical Data Daily'!E10-Q9)*'Historical Data Daily'!$S$12 + Q9 -> 111.22365 | R10: =Q10-P10 -> -0.41016562 | S10: =(R10-S9)*'Historical Data Daily'!$S$14 + S9 -> 0.23076665 | T10: =R10-S10 -> -0.64093228
M11: 44302 | N11: =AVERAGE('Historical Data Daily'!E2:E11) -> 112.34 | O11: =STDEV('Historical Data Daily'!E2:E11) -> 4.2430858 | P11: =('Historical Data Daily'!E11-P10)*'Historical Data Daily'!$S$13 + P10 -> 111.68316 | Q11: =('Historical Data Daily'!E11-Q10)*'Historical Data Daily'!$S$12 + Q10 -> 111.38924 | R11: =Q11-P11 -> -0.29391968 | S11: =(R11-S10)*'Historical Data Daily'!$S$14 + S10 -> 0.12582939 | T11: =R11-S11 -> -0.41974906 | U11: =N11+O11*2 -> 120.82617 | V11: =N11-O11*2 -> 103.85383
M12: 44305 | N12: =AVERAGE('Historical Data Daily'!E3:E12) -> 112.05 | O12: =STDEV('Historical Data Daily'!E3:E12) -> 4.4066234 | P12: =('Historical Data Daily'!E12-P11)*'Historical Data Daily'!$S$13 + P11 -> 111.45107 | Q12: =('Historical Data Daily'!E12-Q11)*'Historical Data Daily'!$S$12 + Q11 -> 110.95243 | R12: =Q12-P12 -> -0.49863958 | S12: =(R12-S11)*'Historical Data Daily'!$S$14 + S11 -> 0.00093559457 | T12: =R12-S12 -> -0.49957517 | U12: =N12+O12*2 -> 120.86325 | V12: =N12-O12*2 -> 103.23675
M13: 44306 | N13: =AVERAGE('Historical Data Daily'!E4:E13) -> 111.165 | O13: =STDEV('Historical Data Daily'!E4:E13) -> 4.4692182 | P13: =('Historical Data Daily'!E13-P12)*'Historical Data Daily'!$S$13 + P12 -> 111.11396 | Q13: =('Historical Data Daily'!E13-Q12)*'Historical Data Daily'!$S$12 + Q12 -> 110.32898 | R13: =Q13-P13 -> -0.78497417 | S13: =(R13-S12)*'Historical Data Daily'!$S$14 + S12 -> -0.15624636 | T13: =R13-S13 -> -0.62872781 | U13: =N13+O13*2 -> 120.10344 | V13: =N13-O13*2 -> 102.22656
M14: 44308 | N14: =AVERAGE('Historical Data Daily'!E5:E14) -> 110.275 | O14: =STDEV('Historical Data Daily'!E5:E14) -> 4.3503668 | P14: =('Historical Data Daily'!E14-P13)*'Historical Data Daily'!$S$13 + P13 -> 110.7944 | Q14: =('Historical Data Daily'!E14-Q13)*'Historical Data Daily'!$S$12 + Q13 -> 109.78606 | R14: =Q14-P14 -> -1.0083419 | S14: =(R14-S13)*'Historical Data Daily'!$S$14 + S13 -> -0.32666548 | T14: =R14-S14 -> -0.68167647 | U14: =N14+O14*2 -> 118.97573 | V14: =N14-O14*2 -> 101.57427
M15: 44309 | N15: =AVERAGE('Historical Data Daily'!E6:E15) -> 109.96 | O15: =STDEV('Historical Data Daily'!E6:E15) -> 4.0841694 | P15: =('Historical Data Daily'!E15-P14)*'Historical Data Daily'!$S$13 + P14 -> 110.86519 | Q15: =('Historical Data Daily'!E15-Q14)*'Historical Data Daily'!$S$12 + Q14 -> 110.08821 | R15: =Q15-P15 -> -0.77698256 | S15: =(R15-S14)*'Historical Data Daily'!$S$14 + S14 -> -0.41672889 | T15: =R15-S15 -> -0.36025367 | U15: =N15+O15*2 -> 118.12834 | V15: =N15-O15*2 -> 101.79166
M16: 44312 | N16: =AVERAGE('Historical Data Daily'!E7:E16) -> 109.775 | O16: =STDEV('Historical Data Daily'!E7:E16) -> 3.8049852 | P16: =('Historical Data Daily'!E16-P15)*'Historical Data Daily'!$S$13 + P15 -> 111.11962 | Q16: =('Historical Data Daily'!E16-Q15)*'Historical Data Daily'!$S$12 + Q15 -> 110.73618 | R16: =Q16-P16 -> -0.38344454 | S16: =(R16-S15)*'Historical Data Daily'!$S$14 + S15 -> -0.41007202 | T16: =R16-S16 -> 0.026627486 | U16: =N16+O16*2 -> 117.38497 | V16: =N16-O16*2 -> 102.16503
M17: 44313 | N17: =AVERAGE('Historical Data Daily'!E8:E17) -> 109.32 | O17: =STDEV('Historical Data Daily'!E8:E17) -> 3.1303358 | P17: =('Historical Data Daily'!E17-P16)*'Historical Data Daily'!$S$13 + P16 -> 111.17743 | Q17: =('Historical Data Daily'!E17-Q16)*'Historical Data Daily'!$S$12 + Q16 -> 110.91523 | R17: =Q17-P17 -> -0.26220036 | S17: =(R17-S16)*'Historical Data Daily'!$S$14 + S16 -> -0.38049769 | T17: =R17-S17 -> 0.11829733 | U17: =N17+O17*2 -> 115.58067 | V17: =N17-O17*2 -> 103.05933
M18: 44314 | N18: =AVERAGE('Historical Data Daily'!E9:E18) -> 110.295 | O18: =STDEV('Historical Data Daily'!E9:E18) -> 2.9402812 | P18: =('Historical Data Daily'!E18-P17)*'Historical Data Daily'!$S$13 + P17 -> 111.39762 | Q18: =('Historical Data Daily'!E18-Q17)*'Historical Data Daily'!$S$12 + Q17 -> 111.41288 | R18: =Q18-P18 -> 0.015266738 | S18: =(R18-S17)*'Historical Data Daily'!$S$14 + S17 -> -0.3013448 | T18: =R18-S18 -> 0.31661154 | U18: =N18+O18*2 -> 116.17556 | V18: =N18-O18*2 -> 104.41444
M19: 44315 | N19: =AVERAGE('Historical Data Daily'!E10:E19) -> 110.58 | O19: =STDEV('Historical Data Daily'!E10:E19) -> 2.9604059 | P19: =('Historical Data Daily'!E19-P18)*'Historical Data Daily'!$S$13 + P18 -> 111.44594 | Q19: =('Historical Data Daily'!E19-Q18)*'Historical Data Daily'!$S$12 + Q18 -> 111.5109 | R19: =Q19-P19 -> 0.064960221 | S19: =(R19-S18)*'Historical Data Daily'!$S$14 + S18 -> -0.2280838 | T19: =R19-S19 -> 0.29304402 | U19: =N19+O19*2 -> 116.50081 | V19: =N19-O19*2 -> 104.65919
M20: 44316 | N20: =AVERAGE('Historical Data Daily'!E11:E20) -> 111.04 | O20: =STDEV('Historical Data Daily'!E11:E20) -> 2.7060424 | P20: =('Historical Data Daily'!E20-P19)*'Historical Data Daily'!$S$13 + P19 -> 111.46476 | Q20: =('Historical Data Daily'!E20-Q19)*'Historical Data Daily'!$S$12 + Q19 -> 111.53999 | R20: =Q20-P20 -> 0.075232867 | S20: =(R20-S19)*'Historical Data Daily'!$S$14 + S19 -> -0.16742047 | T20: =R20-S20 -> 0.24265333 | U20: =N20+O20*2 -> 116.45209 | V20: =N20-O20*2 -> 105.62792
M21: 44319 | N21: =AVERAGE('Historical Data Daily'!E12:E21) -> 111.205 | O21: =STDEV('Historical Data Daily'!E12:E21) -> 2.83847 | P21: =('Historical Data Daily'!E21-P20)*'Historical Data Daily'!$S$13 + P20 -> 111.64885 | Q21: =('Historical Data Daily'!E21-Q20)*'Historical Data Daily'!$S$12 + Q20 -> 111.91076 | R21: =Q21-P21 -> 0.26191106 | S21: =(R21-S20)*'Historical Data Daily'!$S$14 + S20 -> -0.08155416 | T21: =R21-S21 -> 0.34346522 | U21: =N21+O21*2 -> 116.88194 | V21: =N21-O21*2 -> 105.52806
M22: 44320 | N22: =AVERAGE('Historical Data Daily'!E13:E22) -> 111.885 | O22: =STDEV('Historical Data Daily'!E13:E22) -> 2.9443014 | P22: =('Historical Data Daily'!E22-P21)*'Historical Data Daily'!$S$13 + P21 -> 111.92301 | Q22: =('Historical Data Daily'!E22-Q21)*'Historical Data Daily'!$S$12 + Q21 -> 112.43988 | R22: =Q22-P22 -> 0.51686516 | S22: =(R22-S21)*'Historical Data Daily'!$S$14 + S21 -> 0.038129703 | T22: =R22-S22 -> 0.47873545 | U22: =N22+O22*2 -> 117.7736 | V22: =N22-O22*2 -> 105.9964
... M35: 44340 | N35: =AVERAGE('Historical Data Daily'!E26:E35) -> 143.715 | O35: =STDEV('Historical Data Daily'!E26:E35) -> 3.5863202 | P35: =('Historical Data Daily'!E35-P34)*'Historical Data Daily'!$S$13 + P34 -> 131.16212 | Q35: =('Historical Data Daily'!E35-Q34)*'Historical Data Daily'!$S$12 + Q34 -> 139.06969 | R35: =Q35-P35 -> 7.9075726 | S35: =(R35-S34)*'Historical Data Daily'!$S$14 + S34 -> 7.7651296 | T35: =R35-S35 -> 0.14244301 | U35: =N35+O35*2 -> 150.88764 | V35: =N35-O35*2 -> 136.54236
J36: Bollinger Bands | M36: 44341 | N36: =AVERAGE('Historical Data Daily'!E27:E36) -> 144.48 | O36: =STDEV('Historical Data Daily'!E27:E36) -> 2.9280442 | P36: =('Historical Data Daily'!E36-P35)*'Historical Data Daily'!$S$13 + P35 -> 132.21677 | Q36: =('Historical Data Daily'!E36-Q35)*'Historical Data Daily'!$S$12 + Q35 -> 140.04358 | R36: =Q36-P36 -> 7.826808 | S36: =(R36-S35)*'Historical Data Daily'!$S$14 + S35 -> 7.7774652 | T36: =R36-S36 -> 0.04934274 | U36: =N36+O36*2 -> 150.33609 | V36: =N36-O36*2 -> 138.62391
M37: 44342 | N37: =AVERAGE('Historical Data Daily'!E28:E37) -> 143.88 | O37: =STDEV('Historical Data Daily'!E28:E37) -> 3.0572482 | P37: =('Historical Data Daily'!E37-P36)*'Historical Data Daily'!$S$13 + P36 -> 132.83775 | Q37: =('Historical Data Daily'!E37-Q36)*'Historical Data Daily'!$S$12 + Q36 -> 140.12919 | R37: =Q37-P37 -> 7.2914315 | S37: =(R37-S36)*'Historical Data Daily'!$S$14 + S36 -> 7.6802585 | T37: =R37-S37 -> -0.38882702 | U37: =N37+O37*2 -> 149.9945 | V37: =N37-O37*2 -> 137.7655
M38: 44343 | N38: =AVERAGE('Historical Data Daily'!E29:E38) -> 143.03 | O38: =STDEV('Historical Data Daily'!E29:E38) -> 2.3817822 | P38: =('Historical Data Daily'!E38-P37)*'Historical Data Daily'!$S$13 + P37 -> 133.45348 | Q38: =('Historical Data Daily'!E38-Q37)*'Historical Data Daily'!$S$12 + Q37 -> 140.28623 | R38: =Q38-P38 -> 6.8327574 | S38: =(R38-S37)*'Historical Data Daily'!$S$14 + S37 -> 7.5107583 | T38: =R38-S38 -> -0.67800088 | U38: =N38+O38*2 -> 147.79356 | V38: =N38-O38*2 -> 138.26643
M39: 44344 | N39: =AVERAGE('Historical Data Daily'!E30:E39) -> 142.245 | O39: =STDEV('Historical Data Daily'!E30:E39) -> 2.6627526 | P39: =('Historical Data Daily'!E39-P38)*'Historical Data Daily'!$S$13 + P38 -> 133.78285 | Q39: =('Historical Data Daily'!E39-Q38)*'Historical Data Daily'!$S$12 + Q38 -> 139.91912 | R39: =Q39-P39 -> 6.1362719 | S39: =(R39-S38)*'Historical Data Daily'!$S$14 + S38 -> 7.235861 | T39: =R39-S39 -> -1.0995891 | U39: =N39+O39*2 -> 147.5705 | V39: =N39-O39*2 -> 136.91949
M40: 44347 | N40: =AVERAGE('Historical Data Daily'!E31:E40) -> 141.08 | O40: =STDEV('Historical Data Daily'!E31:E40) -> 2.999924 | P40: =('Historical Data Daily'!E40-P39)*'Historical Data Daily'!$S$13 + P39 -> 133.88042 | Q40: =('Historical Data Daily'!E40-Q39)*'Historical Data Daily'!$S$12 + Q39 -> 139.17772 | R40: =Q40-P40 -> 5.2973025 | S40: =(R40-S39)*'Historical Data Daily'!$S$14 + S39 -> 6.8481493 | T40: =R40-S40 -> -1.5508468 | U40: =N40+O40*2 -> 147.07985 | V40: =N40-O40*2 -> 135.08015
M41: 44348 | N41: =AVERAGE('Historical Data Daily'!E32:E41) -> 140.68 | O41: =STDEV('Historical Data Daily'!E32:E41) -> 2.8912865 | P41: =('Historical Data Daily'!E41-P40)*'Historical Data Daily'!$S$13 + P40 -> 134.30409 | Q41: =('Historical Data Daily'!E41-Q40)*'Historical Data Daily'!$S$12 + Q40 -> 139.24269 | R41: =Q41-P41 -> 4.9385965 | S41: =(R41-S40)*'Historical Data Daily'!$S$14 + S40 -> 6.4662387 | T41: =R41-S41 -> -1.5276422 | U41: =N41+O41*2 -> 146.46257 | V41: =N41-O41*2 -> 134.89743
M42: 44349 | N42: =AVERAGE('Historical Data Daily'!E33:E42) -> 140.305 | O42: =STDEV('Historical Data Daily'!E33:E42) -> 2.6218553 | P42: =('Historical Data Daily'!E42-P41)*'Historical Data Daily'!$S$13 + P41 -> 134.75564 | Q42: =('Historical Data Daily'!E42-Q41)*'Historical Data Daily'!$S$12 + Q41 -> 139.42073 | R42: =Q42-P42 -> 4.6650955 | S42: =(R42-S41)*'Historical Data Daily'!$S$14 + S41 -> 6.1060101 | T42: =R42-S42 -> -1.4409146 | U42: =N42+O42*2 -> 145.54871 | V42: =N42-O42*2 -> 135.06129
M43: 44350 | N43: =AVERAGE('Historical Data Daily'!E34:E43) -> 140.185 | O43: =STDEV('Historical Data Daily'!E34:E43) -> 2.619057 | P43: =('Historical Data Daily'!E43-P42)*'Historical Data Daily'!$S$13 + P42 -> 135.12189 | Q43: =('Historical Data Daily'!E43-Q42)*'Historical Data Daily'!$S$12 + Q42 -> 139.4637 | R43: =Q43-P43 -> 4.3418104 | S43: =(R43-S42)*'Historical Data Daily'!$S$14 + S42 -> 5.7531702 | T43: =R43-S43 -> -1.4113598 | U43: =N43+O43*2 -> 145.42311 | V43: =N43-O43*2 -> 134.94689
M44: 44351 | N44: =AVERAGE('Historical Data Daily'!E35:E44) -> 140.055 | O44: =STDEV('Historical Data Daily'!E35:E44) -> 2.6311622 | P44: =('Historical Data Daily'!E44-P43)*'Historical Data Daily'!$S$13 + P43 -> 135.42767 | Q44: =('Historical Data Daily'!E44-Q43)*'Historical Data Daily'!$S$12 + Q43 -> 139.43082 | R44: =Q44-P44 -> 4.0031478 | S44: =(R44-S43)*'Historical Data Daily'!$S$14 + S43 -> 5.4031657 | T44: =R44-S44 -> -1.4000179 | U44: =N44+O44*2 -> 145.31732 | V44: =N44-O44*2 -> 134.79267
M45: 44354 | N45: =AVERAGE('Historical Data Daily'!E36:E45) -> 139.785 | O45: =STDEV('Historical Data Daily'!E36:E45) -> 2.6105583 | P45: =('Historical Data Daily'!E45-P44)*'Historical Data Daily'!$S$13 + P44 -> 135.67377 | Q45: =('Historical Data Daily'!E45-Q44)*'Historical Data Daily'!$S$12 + Q44 -> 139.32608 | R45: =Q45-P45 -> 3.6523079 | S45: =(R45-S44)*'Historical Data Daily'!$S$14 + S44 -> 5.0529941 | T45: =R45-S45 -> -1.4006862 | U45: =N45+O45*2 -> 145.00612 | V45: =N45-O45*2 -> 134.56388
M46: 44355 | N46: =AVERAGE('Historical Data Daily'!E37:E46) -> 139.33 | O46: =STDEV('Historical Data Daily'!E37:E46) -> 1.791057 | P46: =('Historical Data Daily'!E46-P45)*'Historical Data Daily'!$S$13 + P45 -> 136.0572 | Q46: =('Historical Data Daily'!E46-Q45)*'Historical Data Daily'!$S$12 + Q45 -> 139.56053 | R46: =Q46-P46 -> 3.5033334 | S46: =(R46-S45)*'Historical Data Daily'!$S$14 + S45 -> 4.743062 | T46: =R46-S46 -> -1.2397286 | U46: =N46+O46*2 -> 142.91211 | V46: =N46-O46*2 -> 135.74789
M47: 44356 | N47: =AVERAGE('Historical Data Daily'!E38:E47) -> 139.16 | O47: =STDEV('Historical Data Daily'!E38:E47) -> 1.7369818 | P47: =('Historical Data Daily'!E47-P46)*'Historical Data Daily'!$S$13 + P46 -> 136.26777 | Q47: =('Historical Data Daily'!E47-Q46)*'Historical Data Daily'!$S$12 + Q46 -> 139.45891 | R47: =Q47-P47 -> 3.191135 | S47: =(R47-S46)*'Historical Data Daily'!$S$14 + S46 -> 4.4326766 | T47: =R47-S47 -> -1.2415416 | U47: =N47+O47*2 -> 142.63396 | V47: =N47-O47*2 -> 135.68604
M48: 44357 | N48: =AVERAGE('Historical Data Daily'!E39:E48) -> 139.23 | O48: =STDEV('Historical Data Daily'!E39:E48) -> 1.837299 | P48: =('Historical Data Daily'!E48-P47)*'Historical Data Daily'!$S$13 + P47 -> 136.68127 | Q48: =('Historical Data Daily'!E48-Q47)*'Historical Data Daily'!$S$12 + Q47 -> 139.82677 | R48: =Q48-P48 -> 3.1454975 | S48: =(R48-S47)*'Historical Data Daily'!$S$14 + S47 -> 4.1752408 | T48: =R48-S48 -> -1.0297433 | U48: =N48+O48*2 -> 142.9046 | V48: =N48-O48*2 -> 135.5554
... M63: 44378 | N63: =AVERAGE('Historical Data Daily'!E54:E63) -> 137.795 | O63: =STDEV('Historical Data Daily'!E54:E63) -> 1.4528596 | P63: =('Historical Data Daily'!E63-P62)*'Historical Data Daily'!$S$13 + P62 -> 138.05759 | Q63: =('Historical Data Daily'!E63-Q62)*'Historical Data Daily'!$S$12 + Q62 -> 138.09635 | R63: =Q63-P63 -> 0.03876347 | S63: =(R63-S62)*'Historical Data Daily'!$S$14 + S62 -> 0.9563937 | T63: =R63-S63 -> -0.91763023 | U63: =N63+O63*2 -> 140.70072 | V63: =N63-O63*2 -> 134.88928
M64: 44379 | N64: =AVERAGE('Historical Data Daily'!E55:E64) -> 137.515 | O64: =STDEV('Historical Data Daily'!E55:E64) -> 1.0276837 | P64: =('Historical Data Daily'!E64-P63)*'Historical Data Daily'!$S$13 + P63 -> 138.04962 | Q64: =('Historical Data Daily'!F64-Q63)*'Historical Data Daily'!$S$12 + Q63 -> 137.99402 | R64: =Q64-P64 -> -0.055598347 | S64: =(R64-S63)*'Historical Data Daily'!$S$14 + S63 -> 0.75399529 | T64: =R64-S64 -> -0.80959364 | U64: =N64+O64*2 -> 139.57037 | V64: =N64-O64*2 -> 135.45963
J65: MACD | M65: 44382 | N65: =AVERAGE('Historical Data Daily'!E56:E65) -> 137.305 | O65: =STDEV('Historical Data Daily'!E56:E65) -> 0.84309028 | P65: =('Historical Data Daily'!E65-P64)*'Historical Data Daily'!$S$13 + P64 -> 137.97928 | Q65: =('Historical Data Daily'!F65-Q64)*'Historical Data Daily'!$S$12 + Q64 -> 137.77716 | R65: =Q65-P65 -> -0.20212212 | S65: =(R65-S64)*'Historical Data Daily'!$S$14 + S64 -> 0.56277181 | T65: =R65-S65 -> -0.76489393 | U65: =N65+O65*2 -> 138.99118 | V65: =N65-O65*2 -> 135.61882
M66: 44383 | N66: =AVERAGE('Historical Data Daily'!E57:E66) -> 136.97 | O66: =STDEV('Historical Data Daily'!E57:E66) -> 0.99028332 | P66: =('Historical Data Daily'!E66-P65)*'Historical Data Daily'!$S$13 + P65 -> 137.766 | Q66: =('Historical Data Daily'!F66-Q65)*'Historical Data Daily'!$S$12 + Q65 -> 137.28712 | R66: =Q66-P66 -> -0.47887923 | S66: =(R66-S65)*'Historical Data Daily'!$S$14 + S65 -> 0.3544416 | T66: =R66-S66 -> -0.83332084 | U66: =N66+O66*2 -> 138.95057 | V66: =N66-O66*2 -> 134.98943
M67: 44384 | N67: =AVERAGE('Historical Data Daily'!E58:E67) -> 136.645 | O67: =STDEV('Historical Data Daily'!E58:E67) -> 1.2139104 | P67: =('Historical Data Daily'!E67-P66)*'Historical Data Daily'!$S$13 + P66 -> 137.52407 | Q67: =('Historical Data Daily'!F67-Q66)*'Historical Data Daily'!$S$12 + Q66 -> 136.78051 | R67: =Q67-P67 -> -0.74356093 | S67: =(R67-S66)*'Historical Data Daily'!$S$14 + S66 -> 0.1348411 | T67: =R67-S67 -> -0.87840202 | U67: =N67+O67*2 -> 139.07282 | V67: =N67-O67*2 -> 134.21718
M68: 44385 | N68: =AVERAGE('Historical Data Daily'!E59:E68) -> 136.44 | O68: =STDEV('Historical Data Daily'!E59:E68) -> 1.1983306 | P68: =('Historical Data Daily'!E68-P67)*'Historical Data Daily'!$S$13 + P67 -> 137.38155 | Q68: =('Historical Data Daily'!F68-Q67)*'Historical Data Daily'!$S$12 + Q67 -> 136.52044 | R68: =Q68-P68 -> -0.86110981 | S68: =(R68-S67)*'Historical Data Daily'!$S$14 + S67 -> -0.064349086 | T68: =R68-S68 -> -0.79676073 | U68: =N68+O68*2 -> 138.83666 | V68: =N68-O68*2 -> 134.04334
M69: 44386 | N69: =AVERAGE('Historical Data Daily'!E60:E69) -> 136.355 | O69: =STDEV('Historical Data Daily'!E60:E69) -> 1.2726712 | P69: =('Historical Data Daily'!E69-P68)*'Historical Data Daily'!$S$13 + P68 -> 137.20514 | Q69: =('Historical Data Daily'!F69-Q68)*'Historical Data Daily'!$S$12 + Q68 -> 136.20842 | R69: =Q69-P69 -> -0.9967212 | S69: =(R69-S68)*'Historical Data Daily'!$S$14 + S68 -> -0.25082351 | T69: =R69-S69 -> -0.74589769 | U69: =N69+O69*2 -> 138.90034 | V69: =N69-O69*2 -> 133.80966
M70: 44389 | N70: =AVERAGE('Historical Data Daily'!E61:E70) -> 136.215 | O70: =STDEV('Historical Data Daily'!E61:E70) -> 1.2016297 | P70: =('Historical Data Daily'!E70-P69)*'Historical Data Daily'!$S$13 + P69 -> 137.12698 | Q70: =('Historical Data Daily'!F70-Q69)*'Historical Data Daily'!$S$12 + Q69 -> 136.12065 | R70: =Q70-P70 -> -1.0063258 | S70: =(R70-S69)*'Historical Data Daily'!$S$14 + S69 -> -0.40192397 | T70: =R70-S70 -> -0.60440185 | U70: =N70+O70*2 -> 138.61826 | V70: =N70-O70*2 -> 133.81174
M71: 44390 | N71: =AVERAGE('Historical Data Daily'!E62:E71) -> 136.07 | O71: =STDEV('Historical Data Daily'!E62:E71) -> 1.046475 | P71: =('Historical Data Daily'!E71-P70)*'Historical Data Daily'!$S$13 + P70 -> 137.08054 | Q71: =('Historical Data Daily'!F71-Q70)*'Historical Data Daily'!$S$12 + Q70 -> 136.10004 | R71: =Q71-P71 -> -0.98049904 | S71: =(R71-S70)*'Historical Data Daily'!$S$14 + S70 -> -0.51763898 | T71: =R71-S71 -> -0.46286006 | U71: =N71+O71*2 -> 138.16295 | V71: =N71-O71*2 -> 133.97705
M72: 44391 | N72: =AVERAGE('Historical Data Daily'!E63:E72) -> 136.47 | O72: =STDEV('Historical Data Daily'!E63:E72) -> 1.779389 | P72: =('Historical Data Daily'!E72-P71)*'Historical Data Daily'!$S$13 + P71 -> 137.34124 | Q72: =('Historical Data Daily'!F72-Q71)*'Historical Data Daily'!$S$12 + Q71 -> 136.71099 | R72: =Q72-P72 -> -0.63024814 | S72: =(R72-S71)*'Historical Data Daily'!$S$14 + S71 -> -0.54016082 | T72: =R72-S72 -> -0.090087328 | U72: =N72+O72*2 -> 140.02878 | V72: =N72-O72*2 -> 132.91122
M73: 44392 | N73: =AVERAGE('Historical Data Daily'!E64:E73) -> 137.06 | O73: =STDEV('Historical Data Daily'!E64:E73) -> 2.5086311 | P73: =('Historical Data Daily'!E73-P72)*'Historical Data Daily'!$S$13 + P72 -> 137.69374 | Q73: =('Historical Data Daily'!F73-Q72)*'Historical Data Daily'!$S$12 + Q72 -> 137.45785 | R73: =Q73-P73 -> -0.23588673 | S73: =(R73-S72)*'Historical Data Daily'!$S$14 + S72 -> -0.479306 | T73: =R73-S73 -> 0.24341927 | U73: =N73+O73*2 -> 142.07726 | V73: =N73-O73*2 -> 132.04274
M74: 44393 | N74: =AVERAGE('Historical Data Daily'!E65:E74) -> 137.595 | O74: =STDEV('Historical Data Daily'!E65:E74) -> 3.1958712 | P74: =('Historical Data Daily'!E74-P73)*'Historical Data Daily'!$S$13 + P73 -> 138.10902 | Q74: =('Historical Data Daily'!F74-Q73)*'Historical Data Daily'!$S$12 + Q73 -> 138.27373 | R74: =Q74-P74 -> 0.16471527 | S74: =(R74-S73)*'Historical Data Daily'!$S$14 + S73 -> -0.35050174 | T74: =R74-S74 -> 0.51521702 | U74: =N74+O74*2 -> 143.98675 | V74: =N74-O74*2 -> 131.20326
M75: 44396 | N75: =AVERAGE('Historical Data Daily'!E66:E75) -> 138.065 | O75: =STDEV('Historical Data Daily'!E66:E75) -> 3.4504483 | P75: =('Historical Data Daily'!E75-P74)*'Historical Data Daily'!$S$13 + P74 -> 138.38242 | Q75: =('Historical Data Daily'!F75-Q74)*'Historical Data Daily'!$S$12 + Q74 -> 138.73419 | R75: =Q75-P75 -> 0.35176905 | S75: =(R75-S74)*'Historical Data Daily'!$S$14 + S74 -> -0.21004759 | T75: =R75-S75 -> 0.56181663 | U75: =N75+O75*2 -> 144.9659 | V75: =N75-O75*2 -> 131.16411
M76: 44397 | N76: =AVERAGE('Historical Data Daily'!E67:E76) -> 138.385 | O76: =STDEV('Historical Data Daily'!E67:E76) -> 3.2895519 | P76: =('Historical Data Daily'!E76-P75)*'Historical Data Daily'!$S$13 + P75 -> 138.37632 | Q76: =('Historical Data Daily'!F76-Q75)*'Historical Data Daily'!$S$12 + Q75 -> 138.58738 | R76: =Q76-P76 -> 0.21105639 | S76: =(R76-S75)*'Historical Data Daily'!$S$14 + S75 -> -0.12582679 | T76: =R76-S76 -> 0.33688318 | U76: =N76+O76*2 -> 144.96411 | V76: =N76-O76*2 -> 131.8059
M77: 44399 | N77: =AVERAGE('Historical Data Daily'!E68:E77) -> 139.18 | O77: =STDEV('Historical Data Daily'!E68:E77) -> 3.2059157 | P77: =('Historical Data Daily'!E77-P76)*'Historical Data Daily'!$S$13 + P76 -> 138.67807 | Q77: =('Historical Data Daily'!F77-Q76)*'Historical Data Daily'!$S$12 + Q76 -> 139.09921 | R77: =Q77-P77 -> 0.42113328 | S77: =(R77-S76)*'Historical Data Daily'!$S$14 + S76 -> -0.016434776 | T77: =R77-S77 -> 0.43756806 | U77: =N77+O77*2 -> 145.59183 | V77: =N77-O77*2 -> 132.76817
... M93: 44421 | N93: =AVERAGE('Historical Data Daily'!E84:E93) -> 131.45 | O93: =STDEV('Historical Data Daily'!E84:E93) -> 4.8509438 | P93: =('Historical Data Daily'!E93-P92)*'Historical Data Daily'!$S$13 + P92 -> 134.26383 | Q93: =('Historical Data Daily'!F93-Q92)*'Historical Data Daily'!$S$12 + Q92 -> 130.96258 | R93: =Q93-P93 -> -3.301249 | S93: =(R93-S92)*'Historical Data Daily'!$S$14 + S92 -> -2.1518996 | T93: =R93-S93 -> -1.1493494 | U93: =N93+O93*2 -> 141.15189 | V93: =N93-O93*2 -> 121.74811
J94: RSI | M94: 44424 | N94: =AVERAGE('Historical Data Daily'!E85:E94) -> 130.26 | O94: =STDEV('Historical Data Daily'!E85:E94) -> 4.8112583 | P94: =('Historical Data Daily'!E94-P93)*'Historical Data Daily'!$S$13 + P93 -> 133.58132 | Q94: =('Historical Data Daily'!F94-Q93)*'Historical Data Daily'!$S$12 + Q93 -> 129.9806 | R94: =Q94-P94 -> -3.6007232 | S94: =(R94-S93)*'Historical Data Daily'!$S$14 + S93 -> -2.4416644 | T94: =R94-S94 -> -1.1590588 | U94: =N94+O94*2 -> 139.88252 | V94: =N94-O94*2 -> 120.63748
M95: 44425 | N95: =AVERAGE('Historical Data Daily'!E86:E95) -> 128.85 | O95: =STDEV('Historical Data Daily'!E86:E95) -> 4.9572042 | P95: =('Historical Data Daily'!E95-P94)*'Historical Data Daily'!$S$13 + P94 -> 132.72715 | Q95: =('Historical Data Daily'!F95-Q94)*'Historical Data Daily'!$S$12 + Q94 -> 128.68989 | R95: =Q95-P95 -> -4.0372598 | S95: =(R95-S94)*'Historical Data Daily'!$S$14 + S94 -> -2.7607834 | T95: =R95-S95 -> -1.2764763 | U95: =N95+O95*2 -> 138.76441 | V95: =N95-O95*2 -> 118.93559
M96: 44426 | N96: =AVERAGE('Historical Data Daily'!E87:E96) -> 127.3 | O96: =STDEV('Historical Data Daily'!E87:E96) -> 5.3498691 | P96: =('Historical Data Daily'!E96-P95)*'Historical Data Daily'!$S$13 + P95 -> 131.72144 | Q96: =('Historical Data Daily'!F96-Q95)*'Historical Data Daily'!$S$12 + Q95 -> 127.15328 | R96: =Q96-P96 -> -4.5681597 | S96: =(R96-S95)*'Historical Data Daily'!$S$14 + S95 -> -3.1222587 | T96: =R96-S96 -> -1.445901 | U96: =N96+O96*2 -> 137.99974 | V96: =N96-O96*2 -> 116.60026
M97: 44428 | N97: =AVERAGE('Historical Data Daily'!E88:E97) -> 125.315 | O97: =STDEV('Historical Data Daily'!E88:E97) -> 5.8359052 | P97: =('Historical Data Daily'!E97-P96)*'Historical Data Daily'!$S$13 + P96 -> 130.49392 | Q97: =('Historical Data Daily'!F97-Q96)*'Historical Data Daily'!$S$12 + Q96 -> 125.24 | R97: =Q97-P97 -> -5.2539284 | S97: =(R97-S96)*'Historical Data Daily'!$S$14 + S96 -> -3.5485926 | T97: =R97-S97 -> -1.7053358 | U97: =N97+O97*2 -> 136.98681 | V97: =N97-O97*2 -> 113.64319
M98: 44431 | N98: =AVERAGE('Historical Data Daily'!E89:E98) -> 124.1 | O98: =STDEV('Historical Data Daily'!E89:E98) -> 4.7896299 | P98: =('Historical Data Daily'!E98-P97)*'Historical Data Daily'!$S$13 + P97 -> 129.9203 | Q98: =('Historical Data Daily'!F98-Q97)*'Historical Data Daily'!$S$12 + Q97 -> 124.7859 | R98: =Q98-P98 -> -5.1344021 | S98: =(R98-S97)*'Historical Data Daily'!$S$14 + S97 -> -3.8657545 | T98: =R98-S98 -> -1.2686476 | U98: =N98+O98*2 -> 133.67926 | V98: =N98-O98*2 -> 114.52074
M99: 44432 | N99: =AVERAGE('Historical Data Daily'!E90:E99) -> 122.885 | O99: =STDEV('Historical Data Daily'!E90:E99) -> 4.1776546 | P99: =('Historical Data Daily'!E99-P98)*'Historical Data Daily'!$S$13 + P98 -> 129.14472 | Q99: =('Historical Data Daily'!F99-Q98)*'Historical Data Daily'!$S$12 + Q98 -> 123.89588 | R99: =Q99-P99 -> -5.2488436 | S99: =(R99-S98)*'Historical Data Daily'!$S$14 + S98 -> -4.1423724 | T99: =R99-S99 -> -1.1064713 | U99: =N99+O99*2 -> 131.24031 | V99: =N99-O99*2 -> 114.52969
M100: 44433 | N100: =AVERAGE('Historical Data Daily'!E91:E100) -> 122.26 | O100: =STDEV('Historical Data Daily'!E91:E100) -> 4.6118081 | P100: =('Historical Data Daily'!E100-P99)*'Historical Data Daily'!$S$13 + P99 -> 128.22289 | Q100: =('Historical Data Daily'!F100-Q99)*'Historical Data Daily'!$S$12 + Q99 -> 122.7213 | R100: =Q100-P100 -> -5.5015922 | S100: =(R100-S99)*'Historical Data Daily'!$S$14 + S99 -> -4.4142163 | T100: =R100-S100 -> -1.0873759 | U100: =N100+O100*2 -> 131.48362 | V100: =N100-O100*2 -> 113.03638
M101: 44434 | N101: =AVERAGE('Historical Data Daily'!E92:E101) -> 121.41 | O101: =STDEV('Historical Data Daily'!E92:E101) -> 4.6495392 | P101: =('Historical Data Daily'!E101-P100)*'Historical Data Daily'!$S$13 + P100 -> 127.4212 | Q101: =('Historical Data Daily'!F101-Q100)*'Historical Data Daily'!$S$12 + Q100 -> 121.83471 | R101: =Q101-P101 -> -5.5864841 | S101: =(R101-S100)*'Historical Data Daily'!$S$14 + S100 -> -4.6486699 | T101: =R101-S101 -> -0.93781421 | U101: =N101+O101*2 -> 130.70908 | V101: =N101-O101*2 -> 112.11092
M102: 44435 | N102: =AVERAGE('Historical Data Daily'!E93:E102) -> 120.4 | O102: =STDEV('Historical Data Daily'!E93:E102) -> 3.9315673 | P102: =('Historical Data Daily'!E102-P101)*'Historical Data Daily'!$S$13 + P101 -> 126.76777 | Q102: =('Historical Data Daily'!F102-Q101)*'Historical Data Daily'!$S$12 + Q101 -> 121.26844 | R102: =Q102-P102 -> -5.4993301 | S102: =(R102-S101)*'Historical Data Daily'!$S$14 + S101 -> -4.8188019 | T102: =R102-S102 -> -0.68052818 | U102: =N102+O102*2 -> 128.26313 | V102: =N102-O102*2 -> 112.53687
M103: 44438 | N103: =AVERAGE('Historical Data Daily'!E94:E103) -> 119.47 | O103: =STDEV('Historical Data Daily'!E94:E103) -> 3.0032582 | P103: =('Historical Data Daily'!E103-P102)*'Historical Data Daily'!$S$13 + P102 -> 126.14794 | Q103: =('Historical Data Daily'!F103-Q102)*'Historical Data Daily'!$S$12 + Q102 -> 120.75864 | R103: =Q103-P103 -> -5.3892988 | S103: =(R103-S102)*'Historical Data Daily'!$S$14 + S102 -> -4.9329013 | T103: =R103-S103 -> -0.45639747 | U103: =N103+O103*2 -> 125.47652 | V103: =N103-O103*2 -> 113.46348
M104: 44439 | N104: =AVERAGE('Historical Data Daily'!E95:E104) -> 120.255 | O104: =STDEV('Historical Data Daily'!E95:E104) -> 4.9915718 | P104: =('Historical Data Daily'!E104-P103)*'Historical Data Daily'!$S$13 + P103 -> 126.64809 | Q104: =('Historical Data Daily'!F104-Q103)*'Historical Data Daily'!$S$12 + Q103 -> 122.54965 | R104: =Q104-P104 -> -4.0984453 | S104: =(R104-S103)*'Historical Data Daily'!$S$14 + S103 -> -4.7660101 | T104: =R104-S104 -> 0.66756481 | U104: =N104+O104*2 -> 130.23814 | V104: =N104-O104*2 -> 110.27186
M105: 44440 | N105: =AVERAGE('Historical Data Daily'!E96:E105) -> 121.12 | O105: =STDEV('Historical Data Daily'!E96:E105) -> 5.9873551 | P105: =('Historical Data Daily'!E105-P104)*'Historical Data Daily'!$S$13 + P104 -> 126.94823 | Q105: =('Historical Data Daily'!F105-Q104)*'Historical Data Daily'!$S$12 + Q104 -> 123.72793 | R105: =Q105-P105 -> -3.2203064 | S105: =(R105-S104)*'Historical Data Daily'!$S$14 + S104 -> -4.4568694 | T105: =R105-S105 -> 1.236563 | U105: =N105+O105*2 -> 133.09471 | V105: =N105-O105*2 -> 109.14529
M106: 44441 | N106: =AVERAGE('Historical Data Daily'!E97:E106) -> 122.76 | O106: =STDEV('Historical Data Daily'!E97:E106) -> 7.4541853 | P106: =('Historical Data Daily'!E106-P105)*'Historical Data Daily'!$S$13 + P105 -> 127.5854 | Q106: =('Historical Data Daily'!F106-Q105)*'Historical Data Daily'!$S$12 + Q105 -> 125.46828 | R106: =Q106-P106 -> -2.1171213 | S106: =(R106-S105)*'Historical Data Daily'!$S$14 + S105 -> -3.9889197 | T106: =R106-S106 -> 1.8717984 | U106: =N106+O106*2 -> 137.66837 | V106: =N106-O106*2 -> 107.85163
... M120: 44462 | N120: =AVERAGE('Historical Data Daily'!E111:E120) -> 128.49 | O120: =STDEV('Historical Data Daily'!E111:E120) -> 3.0263461 | P120: =('Historical Data Daily'!E120-P119)*'Historical Data Daily'!$S$13 + P119 -> 128.44499 | Q120: =('Historical Data Daily'!F120-Q119)*'Historical Data Daily'!$S$12 + Q119 -> 127.59284 | R120: =Q120-P120 -> -0.85215384 | S120: =(R120-S119)*'Historical Data Daily'!$S$14 + S119 -> -0.41955607 | T120: =R120-S120 -> -0.43259778 | U120: =N120+O120*2 -> 134.54269 | V120: =N120-O120*2 -> 122.43731
M121: Dividend Payment | N121: =AVERAGE('Historical Data Daily'!E112:E121) -> 127.745 | O121: =STDEV('Historical Data Daily'!E112:E121) -> 3.1318649 | P121: =('Historical Data Daily'!E121-P120)*'Historical Data Daily'!$S$13 + P120 -> 128.11574 | Q121: =('Historical Data Daily'!F121-Q120)*'Historical Data Daily'!$S$12 + Q120 -> 127.0401 | R121: =Q121-P121 -> -1.0756397 | S121: =(R121-S120)*'Historical Data Daily'!$S$14 + S120 -> -0.5507728 | T121: =R121-S121 -> -0.52486693 | U121: =N121+O121*2 -> 134.00873 | V121: =N121-O121*2 -> 121.48127
M122: 44466 | N122: =AVERAGE('Historical Data Daily'!E113:E122) -> 126.635 | O122: =STDEV('Historical Data Daily'!E113:E122) -> 2.8601719 | P122: =('Historical Data Daily'!E122-P121)*'Historical Data Daily'!$S$13 + P121 -> 127.68494 | Q122: =('Historical Data Daily'!F122-Q121)*'Historical Data Daily'!$S$12 + Q121 -> 126.31085 | R122: =Q122-P122 -> -1.3740898 | S122: =(R122-S121)*'Historical Data Daily'!$S$14 + S121 -> -0.7154362 | T122: =R122-S122 -> -0.65865361 | U122: =N122+O122*2 -> 132.35534 | V122: =N122-O122*2 -> 120.91466
J123: ATR | M123: 44467 | N123: =AVERAGE('Historical Data Daily'!E114:E123) -> 126.175 | O123: =STDEV('Historical Data Daily'!E114:E123) -> 2.3942337 | P123: =('Historical Data Daily'!E123-P122)*'Historical Data Daily'!$S$13 + P122 -> 127.59717 | Q123: =('Historical Data Daily'!F123-Q122)*'Historical Data Daily'!$S$12 + Q122 -> 126.33995 | R123: =Q123-P123 -> -1.2572166 | S123: =(R123-S122)*'Historical Data Daily'!$S$14 + S122 -> -0.82379228 | T123: =R123-S123 -> -0.4334243 | U123: =N123+O123*2 -> 130.96347 | V123: =N123-O123*2 -> 121.38653
M124: 44468 | N124: =AVERAGE('Historical Data Daily'!E115:E124) -> 125.83 | O124: =STDEV('Historical Data Daily'!E115:E124) -> 2.0070977 | P124: =('Historical Data Daily'!E124-P123)*'Historical Data Daily'!$S$13 + P123 -> 127.5159 | Q124: =('Historical Data Daily'!F124-Q123)*'Historical Data Daily'!$S$12 + Q123 -> 126.36457 | R124: =Q124-P124 -> -1.151322 | S124: =(R124-S123)*'Historical Data Daily'!$S$14 + S123 -> -0.88929822 | T124: =R124-S124 -> -0.26202376 | U124: =N124+O124*2 -> 129.8442 | V124: =N124-O124*2 -> 121.8158
M125: 44469 | N125: =AVERAGE('Historical Data Daily'!E116:E125) -> 125.625 | O125: =STDEV('Historical Data Daily'!E116:E125) -> 1.860144 | P125: =('Historical Data Daily'!E125-P124)*'Historical Data Daily'!$S$13 + P124 -> 127.3999 | Q125: =('Historical Data Daily'!F125-Q124)*'Historical Data Daily'!$S$12 + Q124 -> 126.30079 | R125: =Q125-P125 -> -1.0991105 | S125: =(R125-S124)*'Historical Data Daily'!$S$14 + S124 -> -0.93126068 | T125: =R125-S125 -> -0.16784985 | U125: =N125+O125*2 -> 129.34529 | V125: =N125-O125*2 -> 121.90471
M126: 44470 | N126: =AVERAGE('Historical Data Daily'!E117:E126) -> 125.305 | O126: =STDEV('Historical Data Daily'!E117:E126) -> 1.3807093 | P126: =('Historical Data Daily'!E126-P125)*'Historical Data Daily'!$S$13 + P125 -> 127.29991 | Q126: =('Historical Data Daily'!F126-Q125)*'Historical Data Daily'!$S$12 + Q125 -> 126.26221 | R126: =Q126-P126 -> -1.037701 | S126: =(R126-S125)*'Historical Data Daily'!$S$14 + S125 -> -0.95254873 | T126: =R126-S126 -> -0.085152222 | U126: =N126+O126*2 -> 128.06642 | V126: =N126-O126*2 -> 122.54358
M127: 44473 | N127: =AVERAGE('Historical Data Daily'!E118:E127) -> 125.515 | O127: =STDEV('Historical Data Daily'!E118:E127) -> 1.6698389 | P127: =('Historical Data Daily'!E127-P126)*'Historical Data Daily'!$S$13 + P126 -> 127.3777 | Q127: =('Historical Data Daily'!F127-Q126)*'Historical Data Daily'!$S$12 + Q126 -> 126.58341 | R127: =Q127-P127 -> -0.79428637 | S127: =(R127-S126)*'Historical Data Daily'!$S$14 + S126 -> -0.92089626 | T127: =R127-S127 -> 0.12660989 | U127: =N127+O127*2 -> 128.85468 | V127: =N127-O127*2 -> 122.17532
M128: 44474 | N128: =AVERAGE('Historical Data Daily'!E119:E128) -> 125.935 | O128: =STDEV('Historical Data Daily'!E119:E128) -> 2.2785277 | P128: =('Historical Data Daily'!E128-P127)*'Historical Data Daily'!$S$13 + P127 -> 127.60157 | Q128: =('Historical Data Daily'!F128-Q127)*'Historical Data Daily'!$S$12 + Q127 -> 127.17058 | R128: =Q128-P128 -> -0.43099343 | S128: =(R128-S127)*'Historical Data Daily'!$S$14 + S127 -> -0.8229157 | T128: =R128-S128 -> 0.39192226 | U128: =N128+O128*2 -> 130.49206 | V128: =N128-O128*2 -> 121.37795
M129: 44475 | N129: =AVERAGE('Historical Data Daily'!E120:E129) -> 126.325 | O129: =STDEV('Historical Data Daily'!E120:E129) -> 2.3385933 | P129: =('Historical Data Daily'!E129-P128)*'Historical Data Daily'!$S$13 + P128 -> 127.66071 | Q129: =('Historical Data Daily'!F129-Q128)*'Historical Data Daily'!$S$12 + Q128 -> 127.35972 | R129: =Q129-P129 -> -0.30099477 | S129: =(R129-S128)*'Historical Data Daily'!$S$14 + S128 -> -0.71853151 | T129: =R129-S129 -> 0.41753674 | U129: =N129+O129*2 -> 131.00219 | V129: =N129-O129*2 -> 121.64781
M130: 44476 | N130: =AVERAGE('Historical Data Daily'!E121:E130) -> 127.155 | O130: =STDEV('Historical Data Daily'!E121:E130) -> 3.0895389 | P130: =('Historical Data Daily'!E130-P129)*'Historical Data Daily'!$S$13 + P129 -> 128.06362 | Q130: =('Historical Data Daily'!F130-Q129)*'Historical Data Daily'!$S$12 + Q129 -> 128.24284 | R130: =Q130-P130 -> 0.17921591 | S130: =(R130-S129)*'Historical Data Daily'!$S$14 + S129 -> -0.53898203 | T130: =R130-S130 -> 0.71819793 | U130: =N130+O130*2 -> 133.33408 | V130: =N130-O130*2 -> 120.97592
M131: 44477 | N131: =AVERAGE('Historical Data Daily'!E122:E131) -> 128.135 | O131: =STDEV('Historical Data Daily'!E122:E131) -> 3.5040497 | P131: =('Historical Data Daily'!E131-P130)*'Historical Data Daily'!$S$13 + P130 -> 128.48854 | Q131: =('Historical Data Daily'!F131-Q130)*'Historical Data Daily'!$S$12 + Q130 -> 129.09779 | R131: =Q131-P131 -> 0.60924721 | S131: =(R131-S130)*'Historical Data Daily'!$S$14 + S130 -> -0.30933618 | T131: =R131-S131 -> 0.91858339 | U131: =N131+O131*2 -> 135.1431 | V131: =N131-O131*2 -> 121.1269
M132: 44480 | N132: =AVERAGE('Historical Data Daily'!E123:E132) -> 129.44 | O132: =STDEV('Historical Data Daily'!E123:E132) -> 3.5195348 | P132: =('Historical Data Daily'!E132-P131)*'Historical Data Daily'!$S$13 + P131 -> 128.9968 | Q132: =('Historical Data Daily'!F132-Q131)*'Historical Data Daily'!$S$12 + Q131 -> 130.05967 | R132: =Q132-P132 -> 1.0628703 | S132: =(R132-S131)*'Historical Data Daily'!$S$14 + S131 -> -0.034894882 | T132: =R132-S132 -> 1.0977652 | U132: =N132+O132*2 -> 136.47907 | V132: =N132-O132*2 -> 122.40093
M133: 44481 | N133: =AVERAGE('Historical Data Daily'!E124:E133) -> 130.36 | O133: =STDEV('Historical Data Daily'!E124:E133) -> 3.8523309 | P133: =('Historical Data Daily'!E133-P132)*'Historical Data Daily'!$S$13 + P132 -> 129.49333 | Q133: =('Historical Data Daily'!F133-Q132)*'Historical Data Daily'!$S$12 + Q132 -> 130.92741 | R133: =Q133-P133 -> 1.43408 | S133: =(R133-S132)*'Historical Data Daily'!$S$14 + S132 -> 0.2589001 | T133: =R133-S133 -> 1.1751799 | U133: =N133+O133*2 -> 138.06466 | V133: =N133-O133*2 -> 122.65534
M134: 44482 | N134: =AVERAGE('Historical Data Daily'!E125:E134) -> 132.325 | O134: =STDEV('Historical Data Daily'!E125:E134) -> 6.0495743 | P134: =('Historical Data Daily'!E134-P133)*'Historical Data Daily'!$S$13 + P133 -> 130.72716 | Q134: =('Historical Data Daily'!F134-Q133)*'Historical Data Daily'!$S$12 + Q133 -> 133.26935 | R134: =Q134-P134 -> 2.5421891 | S134: =(R134-S133)*'Historical Data Daily'!$S$14 + S133 -> 0.7155579 | T134: =R134-S134 -> 1.8266312 | U134: =N134+O134*2 -> 144.42415 | V134: =N134-O134*2 -> 120.22585
M135: 44483 | N135: =AVERAGE('Historical Data Daily'!E126:E135) -> 133.87 | O135: =STDEV('Historical Data Daily'!E126:E135) -> 6.2112868 | P135: =('Historical Data Daily'!E135-P134)*'Historical Data Daily'!$S$13 + P134 -> 131.51774 | Q135: =('Historical Data Daily'!F135-Q134)*'Historical Data Daily'!$S$12 + Q134 -> 134.52021 | R135: =Q135-P135 -> 3.0024775 | S135: =(R135-S134)*'Historical Data Daily'!$S$14 + S134 -> 1.1729418 | T135: =R135-S135 -> 1.8295357 | U135: =N135+O135*2 -> 146.29257 | V135: =N135-O135*2 -> 121.44743
... M150: 44508 | N150: =AVERAGE('Historical Data Daily'!E141:E150) -> 134.96 | O150: =STDEV('Historical Data Daily'!E141:E150) -> 2.7815674 | P150: =('Historical Data Daily'!E150-P149)*'Historical Data Daily'!$S$13 + P149 -> 133.65937 | Q150: =('Historical Data Daily'!F150-Q149)*'Historical Data Daily'!$S$12 + Q149 -> 135.035 | R150: =Q150-P150 -> 1.3756311 | S150: =(R150-S149)*'Historical Data Daily'!$S$14 + S149 -> 1.3914137 | T150: =R150-S150 -> -0.015782606 | U150: =N150+O150*2 -> 140.52313 | V150: =N150-O150*2 -> 129.39686
J151: RISING WEDGE | M151: 44509 | N151: =AVERAGE('Historical Data Daily'!E142:E151) -> 136 | O151: =STDEV('Historical Data Daily'!E142:E151) -> 2.1325521 | P151: =('Historical Data Daily'!E151-P150)*'Historical Data Daily'!$S$13 + P150 -> 134.0772 | Q151: =('Historical Data Daily'!F151-Q150)*'Historical Data Daily'!$S$12 + Q150 -> 135.69116 | R151: =Q151-P151 -> 1.6139603 | S151: =(R151-S150)*'Historical Data Daily'!$S$14 + S150 -> 1.435923 | T151: =R151-S151 -> 0.17803733 | U151: =N151+O151*2 -> 140.2651 | V151: =N151-O151*2 -> 131.7349
M152: 44510 | N152: =AVERAGE('Historical Data Daily'!E143:E152) -> 136.91 | O152: =STDEV('Historical Data Daily'!E143:E152) -> 3.4815225 | P152: =('Historical Data Daily'!E152-P151)*'Historical Data Daily'!$S$13 + P151 -> 134.86778 | Q152: =('Historical Data Daily'!F152-Q151)*'Historical Data Daily'!$S$12 + Q151 -> 137.08483 | R152: =Q152-P152 -> 2.2170504 | S152: =(R152-S151)*'Historical Data Daily'!$S$14 + S151 -> 1.5921485 | T152: =R152-S152 -> 0.62490194 | U152: =N152+O152*2 -> 143.87305 | V152: =N152-O152*2 -> 129.94696
M153: 44511 | N153: =AVERAGE('Historical Data Daily'!E144:E153) -> 138.78 | O153: =STDEV('Historical Data Daily'!E144:E153) -> 6.7214892 | P153: =('Historical Data Daily'!E153-P152)*'Historical Data Daily'!$S$13 + P152 -> 136.37016 | Q153: =('Historical Data Daily'!F153-Q152)*'Historical Data Daily'!$S$12 + Q152 -> 139.86408 | R153: =Q153-P153 -> 3.4939205 | S153: =(R153-S152)*'Historical Data Daily'!$S$14 + S152 -> 1.9725029 | T153: =R153-S153 -> 1.5214176 | U153: =N153+O153*2 -> 152.22298 | V153: =N153-O153*2 -> 125.33702
M154: 44512 | N154: =AVERAGE('Historical Data Daily'!E145:E154) -> 140.74 | O154: =STDEV('Historical Data Daily'!E145:E154) -> 7.4118056 | P154: =('Historical Data Daily'!E154-P153)*'Historical Data Daily'!$S$13 + P153 -> 137.51311 | Q154: =('Historical Data Daily'!F154-Q153)*'Historical Data Daily'!$S$12 + Q153 -> 141.70038 | R154: =Q154-P154 -> 4.1872648 | S154: =(R154-S153)*'Historical Data Daily'!$S$14 + S153 -> 2.4154553 | T154: =R154-S154 -> 1.7718095 | U154: =N154+O154*2 -> 155.56361 | V154: =N154-O154*2 -> 125.91639
M155: 44515 | N155: =AVERAGE('Historical Data Daily'!E146:E155) -> 141.985 | O155: =STDEV('Historical Data Daily'!E146:E155) -> 7.2633411 | P155: =('Historical Data Daily'!E155-P154)*'Historical Data Daily'!$S$13 + P154 -> 138.20103 | Q155: =('Historical Data Daily'!F155-Q154)*'Historical Data Daily'!$S$12 + Q154 -> 142.48494 | R155: =Q155-P155 -> 4.2839048 | S155: =(R155-S154)*'Historical Data Daily'!$S$14 + S154 -> 2.7891452 | T155: =R155-S155 -> 1.4947596 | U155: =N155+O155*2 -> 156.51168 | V155: =N155-O155*2 -> 127.45832
M156: 44516 | N156: =AVERAGE('Historical Data Daily'!E147:E156) -> 142.29 | O156: =STDEV('Historical Data Daily'!E147:E156) -> 7.1853542 | P156: =('Historical Data Daily'!E156-P155)*'Historical Data Daily'!$S$13 + P155 -> 138.48244 | Q156: =('Historical Data Daily'!F156-Q155)*'Historical Data Daily'!$S$12 + Q155 -> 142.41033 | R156: =Q156-P156 -> 3.9278942 | S156: =(R156-S155)*'Historical Data Daily'!$S$14 + S155 -> 3.016895 | T156: =R156-S156 -> 0.91099921 | U156: =N156+O156*2 -> 156.66071 | V156: =N156-O156*2 -> 127.91929
M157: 44517 | N157: =AVERAGE('Historical Data Daily'!E148:E157) -> 142.955 | O157: =STDEV('Historical Data Daily'!E148:E157) -> 6.875578 | P157: =('Historical Data Daily'!E157-P156)*'Historical Data Daily'!$S$13 + P156 -> 138.81707 | Q157: =('Historical Data Daily'!F157-Q156)*'Historical Data Daily'!$S$12 + Q156 -> 142.50105 | R157: =Q157-P157 -> 3.6839783 | S157: =(R157-S156)*'Historical Data Daily'!$S$14 + S156 -> 3.1503116 | T157: =R157-S157 -> 0.53366663 | U157: =N157+O157*2 -> 156.70616 | V157: =N157-O157*2 -> 129.20384
M158: 44518 | N158: =AVERAGE('Historical Data Daily'!E149:E158) -> 143.625 | O158: =STDEV('Historical Data Daily'!E149:E158) -> 6.2529648 | P158: =('Historical Data Daily'!E158-P157)*'Historical Data Daily'!$S$13 + P157 -> 138.98988 | Q158: =('Historical Data Daily'!F158-Q157)*'Historical Data Daily'!$S$12 + Q157 -> 142.29319 | R158: =Q158-P158 -> 3.3033146 | S158: =(R158-S157)*'Historical Data Daily'!$S$14 + S157 -> 3.1809122 | T158: =R158-S158 -> 0.12240234 | U158: =N158+O158*2 -> 156.13093 | V158: =N158-O158*2 -> 131.11907
M159: 44522 | N159: =AVERAGE('Historical Data Daily'!E150:E159) -> 143.36 | O159: =STDEV('Historical Data Daily'!E150:E159) -> 6.613066 | P159: =('Historical Data Daily'!E159-P158)*'Historical Data Daily'!$S$13 + P158 -> 138.64248 | Q159: =('Historical Data Daily'!F159-Q158)*'Historical Data Daily'!$S$12 + Q158 -> 141.06347 | R159: =Q159-P159 -> 2.4209911 | S159: =(R159-S158)*'Historical Data Daily'!$S$14 + S158 -> 3.028928 | T159: =R159-S159 -> -0.60793687 | U159: =N159+O159*2 -> 156.58613 | V159: =N159-O159*2 -> 130.13387
M160: 44523 | N160: =AVERAGE('Historical Data Daily'!E151:E160) -> 143.325 | O160: =STDEV('Historical Data Daily'!E151:E160) -> 6.6609236 | P160: =('Historical Data Daily'!E160-P159)*'Historical Data Daily'!$S$13 + P159 -> 138.37267 | Q160: =('Historical Data Daily'!F160-Q159)*'Historical Data Daily'!$S$12 + Q159 -> 140.13063 | R160: =Q160-P160 -> 1.7579627 | S160: =(R160-S159)*'Historical Data Daily'!$S$14 + S159 -> 2.7747349 | T160: =R160-S160 -> -1.0167723 | U160: =N160+O160*2 -> 156.64685 | V160: =N160-O160*2 -> 130.00315
M161: 44524 | N161: =AVERAGE('Historical Data Daily'!E152:E161) -> 142.935 | O161: =STDEV('Historical Data Daily'!E152:E161) -> 7.0268947 | P161: =('Historical Data Daily'!E161-P160)*'Historical Data Daily'!$S$13 + P160 -> 138.15247 | Q161: =('Historical Data Daily'!F161-Q160)*'Historical Data Daily'!$S$12 + Q160 -> 139.40284 | R161: =Q161-P161 -> 1.2503705 | S161: =(R161-S160)*'Historical Data Daily'!$S$14 + S160 -> 2.4698621 | T161: =R161-S161 -> -1.2194915 | U161: =N161+O161*2 -> 156.98879 | V161: =N161-O161*2 -> 128.88121
M162: 44525 | N162: =AVERAGE('Historical Data Daily'!E153:E162) -> 141.885 | O162: =STDEV('Historical Data Daily'!E153:E162) -> 7.4944811 | P162: =('Historical Data Daily'!E162-P161)*'Historical Data Daily'!$S$13 + P161 -> 137.8634 | Q162: =('Historical Data Daily'!F162-Q161)*'Historical Data Daily'!$S$12 + Q161 -> 138.6101 | R162: =Q162-P162 -> 0.7466977 | S162: =(R162-S161)*'Historical Data Daily'!$S$14 + S161 -> 2.1252292 | T162: =R162-S162 -> -1.3785315 | U162: =N162+O162*2 -> 156.87396 | V162: =N162-O162*2 -> 126.89604
M163: 44526 | N163: =AVERAGE('Historical Data Daily'!E154:E163) -> 139.06 | O163: =STDEV('Historical Data Daily'!E154:E163) -> 7.2593929 | P163: =('Historical Data Daily'!E163-P162)*'Historical Data Daily'!$S$13 + P162 -> 137.05129 | Q163: =('Historical Data Daily'!F163-Q162)*'Historical Data Daily'!$S$12 + Q162 -> 136.80854 | R163: =Q163-P163 -> -0.24275176 | S163: =(R163-S162)*'Historical Data Daily'!$S$14 + S162 -> 1.651633 | T163: =R163-S163 -> -1.8943848 | U163: =N163+O163*2 -> 153.57879 | V163: =N163-O163*2 -> 124.54121
... M182: 44553 | N182: =AVERAGE('Historical Data Daily'!E173:E182) -> 113.34 | O182: =STDEV('Historical Data Daily'!E173:E182) -> 5.9468389 | P182: =('Historical Data Daily'!E182-P181)*'Historical Data Daily'!$S$13 + P181 -> 119.53308 | Q182: =('Historical Data Daily'!F182-Q181)*'Historical Data Daily'!$S$12 + Q181 -> 113.26979 | R182: =Q182-P182 -> -6.2632862 | S182: =(R182-S181)*'Historical Data Daily'!$S$14 + S181 -> -5.5274509 | T182: =R182-S182 -> -0.73583532 | U182: =N182+O182*2 -> 125.23368 | V182: =N182-O182*2 -> 101.44632
J183: DESCENDING TRIANGLE | M183: 44554 | N183: =AVERAGE('Historical Data Daily'!E174:E183) -> 112.24 | O183: =STDEV('Historical Data Daily'!E174:E183) -> 5.8827819 | P183: =('Historical Data Daily'!E183-P182)*'Historical Data Daily'!$S$13 + P182 -> 118.64915 | Q183: =('Historical Data Daily'!F183-Q182)*'Historical Data Daily'!$S$12 + Q182 -> 112.39752 | R183: =Q183-P183 -> -6.2516304 | S183: =(R183-S182)*'Historical Data Daily'!$S$14 + S182 -> -5.6722868 | T183: =R183-S183 -> -0.57934359 | U183: =N183+O183*2 -> 124.00556 | V183: =N183-O183*2 -> 100.47444
M184: 44557 | N184: =AVERAGE('Historical Data Daily'!E175:E184) -> 111.155 | O184: =STDEV('Historical Data Daily'!E175:E184) -> 5.5825856 | P184: =('Historical Data Daily'!E184-P183)*'Historical Data Daily'!$S$13 + P183 -> 117.8381 | Q184: =('Historical Data Daily'!F184-Q183)*'Historical Data Daily'!$S$12 + Q183 -> 111.67482 | R184: =Q184-P184 -> -6.1632775 | S184: =(R184-S183)*'Historical Data Daily'!$S$14 + S183 -> -5.7704849 | T184: =R184-S184 -> -0.3927926 | U184: =N184+O184*2 -> 122.32017 | V184: =N184-O184*2 -> 99.989829
M185: 44558 | N185: =AVERAGE('Historical Data Daily'!E176:E185) -> 110.165 | O185: =STDEV('Historical Data Daily'!E176:E185) -> 4.4807653 | P185: =('Historical Data Daily'!E185-P184)*'Historical Data Daily'!$S$13 + P184 -> 117.31305 | Q185: =('Historical Data Daily'!F185-Q184)*'Historical Data Daily'!$S$12 + Q184 -> 111.53254 | R185: =Q185-P185 -> -5.7805134 | S185: =(R185-S184)*'Historical Data Daily'!$S$14 + S184 -> -5.7724906 | T185: =R185-S185 -> -0.0080227433 | U185: =N185+O185*2 -> 119.12653 | V185: =N185-O185*2 -> 101.20347
M186: 44559 | N186: =AVERAGE('Historical Data Daily'!E177:E186) -> 109.475 | O186: =STDEV('Historical Data Daily'!E177:E186) -> 3.4613947 | P186: =('Historical Data Daily'!E186-P185)*'Historical Data Daily'!$S$13 + P185 -> 116.89357 | Q186: =('Historical Data Daily'!F186-Q185)*'Historical Data Daily'!$S$12 + Q185 -> 111.55061 | R186: =Q186-P186 -> -5.3429571 | S186: =(R186-S185)*'Historical Data Daily'!$S$14 + S185 -> -5.6865839 | T186: =R186-S186 -> 0.34362684 | U186: =N186+O186*2 -> 116.39779 | V186: =N186-O186*2 -> 102.55221
...

Sheet Balance Sheet
A1: Field | B1: 45374 | C1: 45373 | D1: 45372
A2: Total Stockholders Fund | B2: 807.91 | C2: 554.03 | D2: 928.14
A3: Common Stock | B3: 117.2 | C3: 95.2 | D3: 83.94
A4: Reserves and Surplus ~ | B4: 690.71 | C4: 458.83 | D4: 844.2
A5: Retained Earning ~ | B5: 690.71 | C5: -138.56 | D5: 392.78
A6: Capital Surplus 1 | B6: 760.02 | C6: 583.77 | D6: 444.79
A7: Other Shareholders Equity I | B7: 690.71 | C7: 13.62 | D7: 451.43
A8: Accumulated Other Comprehensive Income I | B8: 22.07 | C8: 0
A9: Total Non Current Liabilities \ | B9: 271.26 | C9: 277.69 | D9: 46.11
A10: Long Term Debt L | B10: 255.23 | C10: 259.63 | D10: 33.32
A11: Other Non Current Liabilities I~ | C11: 0
A12: Capital Lease Obligation | B12: 6.56 | C12: 5.22 | D12: 2.62
A13: Total Current Liabilities | B13: 588.43 | C13: 563.31 | D13: 708.28
A14: Short Long Term Debt ~ | B14: 334.21 | C14: 258.05 | D14: 317.52
A15: Accounts Payable I~ | B15: 152.58 | C15: 225.86 | D15: 304.13
A16: Other Current Liabilities | B16: 59.94 | C16: 49.62 | D16: 45.12
A17: Total Liabilities | B17: 859.69 | C17: 841 | D17: 754.39
A18: Liabilities & Sh Holder Eq I | B18: 1667.6
A19: Total Non Current Assets I~ | B19: 552.93 | C19: 497.56 | D19: 496.66
A20: Tangible Assets ~ | C20: 553.64 | D20: 926.2
A21: Property Plant Equipment I~ | B21: 480.62 | C21: 468.42 | D21: 474.37
A22: Intangible Assets I | B22: 0.195 | C22: 0.388 | D22: 1.94
A23: Long term Investment
A24: Other Non Current Assets ~ | B24: 7.18 | C24: 6.85 | D24: 68.08
A25: Total Current Assets | B25: 1114.67 | C25: 897.47 | D25: 1185.87
A26: Inventory _ | B26: 573.55 | C26: 478.74 | D26: 694.79
A27: Net Receivable I | B27: 168.23 | C27: 125.31 | D27: 158.95
A28: Cash And Cash Equivalents I | B28: 15.3 | C28: 84 | D28: 18.65
A29: Cash I | B29: -6.56 | C29: 79.67 | D29: 6.95
A30: Short term Investment ^ | B30: 1.5 | C30: 4.33 | D30: 11.71
A31: Other Current Assets I | B31: 357.59 | C31: 133.96 | D31: 472.43
A32: Total Assets | B32: 1667.6 | C32: 1395.03 | D32: 1682.53
A33: Net Working Capital | B33: 526.24 | C33: 334.16 | D33: 477.59
A34: Net Invested Capital | B34: 1397.36 | C34: 1071.71 | D34: 1278.98
A35: Common Share Oustanding | B35: 10.82 | C35: 9.54 | D35: 8.41
... A37: Net Debt | B37: 589.45 | C37: 438.01 | D37: 376.74

Sheet Income Statement
A1: Field | B1: 45374 | C1: 45373 | D1: 45372
A2: Total Revenue/Income | B2: 2892.62 | C2: 2071.75 | D2: 1841.76
A3: Cost Of Revenue | B3: 2323.19 | C3: 2080.51 | D3: 1355.34
A4: Gross Profit | B4: 569.43 | C4: -8.76 | D4: 438.83
A5: Total Operating Expense | B5: 2872.16 | C5: 2614.85 | D5: 1814.55
A6: Selling General Administrative Expenses 区 | B6: 98.06 | C6: 80.14 | D6: 16.73
A7: Other Operating Expenses I | B7: 2696.74 | C7: 314.64 | D7: 1710.5
A8: Sell And Marketing Exp ~ | B8: 77.37 | D8: 39.34
A9: Depreciation And Amortization I | B9: 57.28 | C9: 53.77 | D9: 51.8
A10: Operating Income/Profit l | B10: 75.62 | C10: -492.13 | D10: 83.67
A11: Interest Income I™ | B11: 55.16 | C11: 4.36 | D11: 45.77
A12: Total Other Income Expense Net L | B12: -55.16 | C12: -29.92 | D12: 42.95
A13: EBITDA | B13: 163.5 | C13: -417.33 | D13: 137.23
A14: Reconciled Depreciation ~ | B14: 57.28 | C14: 53.77 | D14: 51.8
A15: EBIT ~ | B15: 106.22 | C15: -471.1 | D15: 85.44
A16: Interest Expense | B16: 55.16 | C16: 50.96 | D16: 45.77
A17: Income/Profit Before Tax I~ | B17: 51.06 | C17: -522.05 | D17: 40.72
A18: Income Tax Expense ~ | B18: -2.19 | C18: 10.44 | D18: 20.02
A19: Tax Provision I~ | B19: -2.19 | C19: 10.44 | D19: 20.02
A20: Net Income From Continuing Operation ~ | B20: 53.25 | C20: -532.5 | D20: 20.71
... A23: EPS (Earning Per Share) | B23: 4.92 | C23: -55.83 | D23: 2.46

Sheet Ratio Analysis
A1: Ratio | B1: Mar-23 | C1: Mar-22 | D1: Mar-21 | E1: Analysis
A2: LIQUIDITY RATIOS
A3: Cash ratio | B3: ='Balance Sheet'!B28/'Balance Sheet'!B13 -> 0.026001394 | C3: ='Balance Sheet'!C28/'Balance Sheet'!C13 -> 0.1491186 | D3: ='Balance Sheet'!D28/'Balance Sheet'!D13 -> 0.026331394 | E3: Low Cash Ratio and Quick Ratio: Ideally, these ratios should be above 1. However, all values provided are below 1, indicating the company might have difficulty meeting its short-term obligations with its most liquid assets (cash and equivalents for quick ratio) in all three years. This raises concerns about the company's short-term financial health. Fluctuation in Liquidity: Improvement in 2022: While still low, the ratios show some improvement in 2022 compared to 2021. However, the 2023 figures are back down, suggesting inconsistency.
A4: Quick ratio | B4: =('Balance Sheet'!B25-'Balance Sheet'!B26)/'Balance Sheet'!B13 -> 0.91959961 | C4: =('Balance Sheet'!C25-'Balance Sheet'!C26)/'Balance Sheet'!C13 -> 0.74333848 | D4: =('Balance Sheet'!D25-'Balance Sheet'!D26)/'Balance Sheet'!D13 -> 0.69334162
A5: Current ratio | B5: ='Balance Sheet'!B25/'Balance Sheet'!B13 -> 1.894312 | C5: ='Balance Sheet'!C25/'Balance Sheet'!C13 -> 1.593208 | D5: ='Balance Sheet'!D25/'Balance Sheet'!D13 -> 1.6742955
A6: ACTIVITY RATIOS
A7: Asset turnover | B7: ='Income Statement'!B2/'Balance Sheet'!B32 -> 1.7346006 | C7: ='Income Statement'!C2/'Balance Sheet'!C32 -> 1.4850935 | D7: ='Income Statement'!D2/'Balance Sheet'!D32 -> 1.0946372 | E7: High Asset Turnover: This is a positive sign across all years. It indicates the company generates more sales per dollar of assets compared to the industry average (further analysis with industry benchmarks is recommended). However, high asset turnover can also suggest the company is over-leveraging its assets to generate sales, which can be risky if not managed properly. Declining Inventory Turnover: This indicates the company is taking longer to sell its inventory over time. This could be due to several factors, such as slow-moving products, overstocking, or declining demand. It can lead to increased holding costs and reduced cash flow. Declining Accounts Receivable Turnover: Similar to inventory turnover, this suggests it's taking longer to collect payments from customers. This can strain cash flow and lead to bad debts. Accounts Payable Turnover: Inconsistent Accounts Payable Turnover: This makes it difficult to assess the company's ability to manage its supplier payments.
A8: Accounts receivables turnover | B8: ='Income Statement'!B2/'Balance Sheet'!B27 -> 17.194436 | C8: ='Income Statement'!C2/'Balance Sheet'!C27 -> 16.532998 | D8: ='Income Statement'!D2/'Balance Sheet'!D27 -> 11.58704
A9: Inventory turnover | B9: ='Income Statement'!B5/'Balance Sheet'!B26 -> 5.007689 | C9: ='Income Statement'!C5/'Balance Sheet'!C26 -> 5.4619418 | D9: ='Income Statement'!D5/'Balance Sheet'!D26 -> 2.6116524
A10: Accounts payables turnover | B10: ='Income Statement'!B5/'Balance Sheet'!B15 -> 18.823961 | C10: ='Income Statement'!C5/'Balance Sheet'!C15 -> 11.577305 | D10: ='Income Statement'!D5/'Balance Sheet'!D15 -> 5.9663631
A11: EFFICIENCY RATIOS
A12: Days receivables | B12: =365/B8 -> 21.227797 | C12: =365/C8 -> 22.07706 | D12: =365/D8 -> 31.500711 | E12: High Asset Turnover: This is a positive sign, indicating the company generates more sales per dollar of assets compared to the industry average. However, it might also suggest the company is over-leveraging its assets to generate sales, which can be risky. Cash Conversion Cycle: While showing improvement in 2023 compared to 2022, it remains higher than the industry average. This means it takes a long time to convert inventory into cash, putting a strain on short-term liquidity.
A13: Days inventory | B13: =365/B9 -> 72.887914 | C13: =365/C9 -> 66.826051 | D13: =365/D9 -> 139.75826
A14: Days payables | B14: =365/B10 -> 19.39018 | C14: =365/C10 -> 31.5272 | D14: =365/D10 -> 61.176297
A15: Cash conversion cycle (days) | B15: =B12+B13-B14 -> 74.72553 | C15: =C12+C13-C14 -> 57.375911 | D15: =D12+D13-D14 -> 110.08267
A16: FINANCIAL LEVERAGE
A17: Debt to total assets | B17: ='Balance Sheet'!B37/'Balance Sheet'!B32 -> 0.35347206 | C17: ='Balance Sheet'!C37/'Balance Sheet'!C32 -> 0.31397891 | D17: ='Balance Sheet'!D37/'Balance Sheet'!D32 -> 0.2239128 | E17: Debt to Total Assets: This ratio is moderate and has been decreasing, indicating a potential improvement in the company's debt management. However, historical data (if available) would provide a clearer picture.
A18: Total debt to EBITDA | B18: ='Balance Sheet'!B37/'Income Statement'!B13 -> 3.6051988 | C18: ='Balance Sheet'!C37/'Income Statement'!C13 -> -1.0495531 | D18: ='Balance Sheet'!D37/'Income Statement'!D13 -> 2.7453181
A19: PROFITABILITY RATIOS
A20: ROCE % | B20: 9.84 | C20: -56.64 | D20: 8.77 | E20: Negative ROCE, ROE, ROA, and Net Margin in 2022: This indicates substantial losses in 2022, raising serious concerns about the company's ability to generate profits. The positive values in 2021 suggest a potential turnaround attempt, but the negative figures in 2022 show a setback. Inconsistent Profitability: Profitability ratios fluctuate significantly across the three years, indicating a lack of stability and difficulty in sustaining profitability. Positive Values in 2023: While positive ROCE, ROE, ROA, Net Margin, and Operating Margin in 2023 offer a glimmer of hope, it's just one year of data, and the magnitude of the improvement compared to 2022 is relatively small.
A21: ROE % | B21: 6.59 | C21: -96.11 | D21: 2.23
A22: ROA % | B22: 3.19 | C22: -38.17 | D22: 1.23
A23: ROIC % | B23: 3.81 | C23: -49.69 | D23: 1.62
A24: Operating Margin % | B24: 2.61 | C24: -23.75 | D24: 4.54
A25: Net Margin % | B25: 1.84 | C25: -25.7 | D25: 1.12
A26: EBITDA Margin % | B26: 5.65 | C26: -20.14 | D26: 7.45
A27: Asset Turnover % | B27: 188.9 | C27: 134.64 | D27: 109.39
A28: Free cash flow To Revenue % | B28: -8.81 | C28: -8.91 | D28: 3.02
A29: Dividend Payout Ratio % | B29: 0 | C29: -0.896 | D29: 20.31
A30: Cash Flow TO Assets % | B30: -11.64 | C30: -10.68 | D30: 5.94
A31: GROWTH AND VALUATION
A32: Enterprise value to EBITDA | B32: 24.73 | C32: 114.99 | D32: - | E32: EV/EBITDA: A high ratio (24.73 in 2021) suggests the market might be overvaluing the company based on its current profitability. The lower values in 2023 could indicate a correction. P/E Ratio: This ratio is unreliable in 2022 due to negative EPS. The 2021 value (16.33) might not be reflective of the company's current situation. Price to Sales (P/S Ratio): This ratio has increased over time, indicating the stock price might be rising faster than the company's sales growth. This could be due to investor optimism about a potential turnaround, but it also suggests potential overvaluation. Price to Cash Flow (P/CF Ratio): Negative values in 2021 and 2022 indicate the company is burning cash rather than generating it. The positive value in 2023 might suggest some improvement, but further data is needed. Retention Ratio: This ratio shows the portion of earnings the company retains for reinvestment. While positive values in 2022 and 2023 indicate reinvestment, the company might need to prioritize profitability before significant growth is achievable. Price/Earnings Growth (PEG Ratio): Negative values in most years suggest the company's stock price is not justified by its current or projected earnings growth. Cost of Equity (CAPM): This provides a benchmark for the company's expected return on equity. While minor fluctuations are seen, it doesn't offer significant insights in this context.
A33: P/E ratio | B33: 16.33 | C33: - | D33: -
A34: EPS | B34: 4.92 | C34: -55.83 | D34: 2.46
A35: EPS Cash | B35: 10.21 | C35: -50.26 | D35: 8.62
A36: Price By Book | B36: 0.975 | C36: 1.67 | D36: 0.957
A37: Price To Sales | B37: 0.272 | C37: 0.445 | D37: 0.482
A38: Earning Yield | B38: 6.76 | C38: -57.71 | D38: 2.33
A39: Price To Cash Flow | B39: -4.06 | C39: -6.19 | D39: 8.88
A40: Retention Ratio | B40: 0 | C40: 1.01 | D40: 0.797
A41: Price / EPS (PE) | B41: 14.79 | C41: -1.73 | D41: 42.9
A42: Price / Earning Growth (PEG) | B42: -0.136 | C42: 0.0007 | D42: -0.551
A43: Enterprise Value to Revenue Ratio | B43: 0.481 | C43: 0.649 | D43: 0.687
A44: Enterprise Value to EBITDA Ratio | B44: 8.5 | C44: -3.22 | D44: 9.21
A45: Market Capitalization To Sales Ratio | B45: 0.272 | C45: 0.445 | D45: 0.482
A46: Cost Of equity (CAPM) | B46: 0.163 | C46: 0.155 | D46: 0.158

Sheet Company Stock Analysis Fundamen
A1: FUNDAMENTAL ANALYSIS | B1: Significant Weaknesses: Profitability: Negative profitability ratios (ROCE, ROE, ROA, Net Margin) in 2022 indicate substantial losses, raising serious doubts about the company's ability to generate sustainable profits. While there's some improvement in 2023, it's too early to determine its sustainability. Liquidity: Consistently low cash and quick ratios suggest difficulty meeting short-term obligations, raising concerns about the company's ability to pay its bills on time. Operational Inefficiency: Declining inventory and accounts receivable turnovers indicate challenges in managing inventory and collecting payments from customers. This can strain cash flow and limit operational efficiency. High Leverage (Partially Mitigated): Debt-to-total-assets ratio shows some improvement, but the historical data is limited for a more definitive assessment. However, the company still relies on debt financing, which can magnify risks. Limited Positives: High Asset Turnover: The company generates more sales per dollar of assets compared to the industry average (further industry benchmark analysis recommended). However, this might indicate over-leveraging assets, requiring careful management. Investment Decision: Considering the substantial profitability and liquidity concerns, operational inefficiencies, and potential leverage risks, this company appears to be a poor investment choice at this time. The potential for future growth is uncertain, and the risks seem to outweigh any potential rewards. Predictive Analysis: Short-term: The stock price is likely to remain volatile and could experience downward pressure in the near future due to the significant financial weaknesses. Long-term: Predicting the long-term movement is difficult. If the company can demonstrably improve its profitability, liquidity, operational efficiency, and manage its debt effectively, there's a chance for future growth. However, this is a highly speculative scenario, and significant and sustained improvements are crucial before the stock becomes an attractive investment.
A2: TECHNICAL ANALYSIS | B2: On the basis of MACD, RSI and recent formation of cup and Handle, the signal is bulllish.
A3: Descriptive Stats | B3: Positive signs: Low Volatility: The exceptionally low standard deviation indicates minimal daily price fluctuations, making it a potentially attractive option for risk-averse investors seeking stability. Minimal Market Correlation (Beta): The beta close to zero suggests the stock's price movements are largely independent of the overall market. This can be beneficial during market downturns. Negative signs: Negative Returns (Alpha): The negative alpha implies the stock underperforms relative to the expected return based on its beta. This is a major concern for any investor. Strong Correlation with NIFTY 50 (at least on a monthly basis): This contradicts the initial suggestion of minimal market correlation. It indicates the stock might still be vulnerable to broader market trends, especially in the long run. Uncertainties: Limited Sentiment Impact: While positive, this doesn't guarantee future performance or identify clear drivers of price movements. Investment Prediction (Cautious): Predicting future price movements with certainty is impossible. However, given the mixed signals: Short-term: The low volatility suggests minimal downside risk in the near future. However, the lack of a clear driver for price appreciation makes significant upside unlikely. Long-term: The negative alpha raises concerns. Investment Suitability: Risk-averse investors: The low volatility might be appealing, but the negative returns are a significant drawback. Growth investors: The stock doesn't seem like a good fit due to the lack of a clear growth story and negative alpha. Value investors: The negative alpha suggests the stock might already be overvalued.
A6: Investment Decision | B6: Fundamental Analysis (Strong Sell Signal): The fundamental weaknesses outweigh any technical positives. The company struggles with profitability, liquidity, operational efficiency, and potential leverage risks. These factors significantly increase the risk of the company failing or its stock price experiencing a major decline. Technical Analysis (Mixed Signals): The low volatility and minimal market correlation might be attractive to risk-averse investors in the short term. However, the negative alpha, potentially conflicting market correlation data, and limited upside potential paint a concerning picture. Overall Recommendation (Cautious - Avoid for Now): Given the significant fundamental weaknesses, the negative alpha in technical analysis, and the lack of a clear growth story, this company appears to be a poor investment choice at this time. The potential rewards don't seem to justify the high risks involved.

Sheet Portfolio Analysis
B1: Parag Milk Foods Ltd | F1: HDFC Bank Ltd | J1: Hindustan Unilever Ltd | N1: Reliance Industries Ltd | R1: Tata Steel Ltd | V1: NIFTY 50 | AB1: Part (A) | AD1: Variance Covariance Matrix to calculate the Std Dev of the Portfolio
B2: Date | C2: Open | D2: Close | E2: HPY | F2: Date | G2: Open | H2: Close | I2: HPY | J2: Date | K2: Open | L2: Close | M2: HPY | N2: Date | O2: Open | P2: Close | Q2: HPY | R2: Date | S2: Open | T2: Close | U2: HPY | V2: Date | W2: Open | X2: Close | Y2: HPY | AB2: Total Close Price on first day | AE2: Parag Milk Food Ltd | AF2: HDFC Bank Ltd | AG2: HUL | AH2: Reliance Ind Ltd | AI2: Tata Steel Ltd | AK2: YEARLY ANALYSIS
B3: 44287 | C3: 106.5 | D3: 111.45 | F3: 44287 | G3: 1499.4 | H3: 1486.75 | J3: 44287 | K3: 2446.8 | L3: 2399.1 | N3: 44287 | O3: 1862.613 | P3: 1866.167 | R3: 44287 | S3: 82.1 | T3: 86.305 | V3: 44287 | W3: 14798.4 | X3: 14867.35 | AB3: =SUM(T3,P3,L3,H3) -> 5838.322 | AD3: Parag Milk Food Ltd | AE3: =COVAR(E:E,E:E) -> 0.00086098519 | AF3: =COVAR(E:E,I:I) -> 4.4819616e-05 | AG3: =COVAR(E:E,M:M) -> 3.3837318e-05 | AH3: =COVAR(E:E,Q:Q) -> 7.8400355e-05 | AI3: =COVAR(E:E,U:U) -> 0.000137185
B4: 44291 | C4: 114.05 | D4: 115.75 | E4: =(D4/D3)-1 -> 0.038582324 | F4: 44291 | G4: 1480 | H4: 1449.6 | I4: =(H4/H3)-1 -> -0.024987389 | J4: 44291 | K4: 2400 | L4: 2373.2 | M4: =(L4/L3)-1 -> -0.010795715 | N4: 44291 | O4: 1869.028 | P4: 1839.169 | Q4: =(P4/P3)-1 -> -0.014467087 | R4: 44291 | S4: 86.2 | T4: 86.775 | U4: =(T4/T3)-1 -> 0.0054458027 | V4: 44291 | W4: 14837.7 | X4: 14637.8 | Y4: =(X4/X3)-1 -> -0.015439873 | AB4: (Required to caluclate price weighted returns) | AD4: HDFC Bank Ltd | AE4: =COVAR(I:I,E:E) -> 4.4819616e-05 | AF4: =COVAR(I:I,I:I) -> 0.00018802258 | AG4: =COVAR(I:I,M:M) -> 4.2574122e-05 | AH4: =COVAR(I:I,Q:Q) -> 7.1267767e-05 | AI4: =COVAR(I:I,U:U) -> 8.3090055e-05 | AK4: Parag Milk Foods Ltd | AO4: HDFC Bank Ltd | AS4: Hindustan Unilever Ltd | AW4: Reliance Industries Ltd | BA4: Tata Steel Ltd | BE4: NIFTY 50
B5: 44292 | C5: 115.8 | D5: 115.7 | E5: =(D5/D4)-1 -> -0.00043196544 | F5: 44292 | G5: 1460 | H5: 1440.25 | I5: =(H5/H4)-1 -> -0.0064500552 | J5: 44292 | K5: 2382.3 | L5: 2408.3 | M5: =(L5/L4)-1 -> 0.014790157 | N5: 44292 | O5: 1849.691 | P5: 1831.508 | Q5: =(P5/P4)-1 -> -0.0041654682 | R5: 44292 | S5: 87.55 | T5: 86.285 | U5: =(T5/T4)-1 -> -0.0056467877 | V5: 44292 | W5: 14737 | X5: 14683.5 | Y5: =(X5/X4)-1 -> 0.0031220539 | AD5: HUL | AE5: =COVAR(M:M,E:E) -> 3.3837318e-05 | AF5: =COVAR(M:M,I:I) -> 4.2574122e-05 | AG5: =COVAR(M:M,M:M) -> 0.00015990365 | AH5: =COVAR(M:M,Q:Q) -> 3.895733e-05 | AI5: =COVAR(M:M,U:U) -> 1.833529e-05 | AK5: Date | AL5: Open | AM5: Close | AN5: HPY | AO5: Date | AP5: Open | AQ5: Close | AR5: HPY | AS5: Date | AT5: Open | AU5: Close | AV5: HPY | AW5: Date | AX5: Open | AY5: Close | AZ5: HPY | BA5: Date | BB5: Open | BC5: Close | BD5: HPY | BE5: Date | BF5: Open | BG5: Close | BH5: HPY
B6: 44293 | C6: 116.45 | D6: 114.9 | E6: =(D6/D5)-1 -> -0.0069144339 | F6: 44293 | G6: 1439.3 | H6: 1447.2 | I6: =(H6/H5)-1 -> 0.0048255511 | J6: 44293 | K6: 2417 | L6: 2405.25 | M6: =(L6/L5)-1 -> -0.0012664535 | N6: 44293 | O6: 1845.999 | P6: 1848.63 | Q6: =(P6/P5)-1 -> 0.0093485805 | R6: 44293 | S6: 86.95 | T6: 87.485 | U6: =(T6/T5)-1 -> 0.0139074 | V6: 44293 | W6: 14716.45 | X6: 14819.05 | Y6: =(X6/X5)-1 -> 0.0092314503 | AD6: Reliance Ind Ltd | AE6: =COVAR(Q:Q,E:E) -> 7.8400355e-05 | AF6: =COVAR(Q:Q,I:I) -> 7.1267767e-05 | AG6: =COVAR(Q:Q,M:M) -> 3.895733e-05 | AH6: =COVAR(Q:Q,Q:Q) -> 0.00021075534 | AI6: =COVAR(Q:Q,U:U) -> 0.00011750687 | AK6: 44287 | AL6: 106.5 | AM6: 111.45 | AO6: 44287 | AP6: 1499.4 | AQ6: 1486.75 | AS6: 44287 | AT6: 2446.8 | AU6: 2399.1 | AW6: 44287 | AX6: 1862.613 | AY6: 1866.167 | BA6: 44287 | BB6: 82.1 | BC6: 86.305 | BE6: 44287 | BF6: 14798.4 | BG6: 14867.35
B7: 44294 | C7: 115.85 | D7: 116.15 | E7: =(D7/D6)-1 -> 0.010879025 | F7: 44294 | G7: 1453 | H7: 1432.8 | I7: =(H7/H6)-1 -> -0.0099502488 | J7: 44294 | K7: 2406 | L7: 2409.9 | M7: =(L7/L6)-1 -> 0.001933271 | N7: 44294 | O7: 1856.152 | P7: 1850.937 | Q7: =(P7/P6)-1 -> 0.0012479512 | R7: 44294 | S7: 88.4 | T7: 91.84 | U7: =(T7/T6)-1 -> 0.049779962 | V7: 44294 | W7: 14875.65 | X7: 14873.8 | Y7: =(X7/X6)-1 -> 0.0036945688 | AD7: Tata Steel Ltd | AE7: =COVAR(U:U,E:E) -> 0.000137185 | AF7: =COVAR(U:U,I:I) -> 8.3090055e-05 | AG7: =COVAR(U:U,M:M) -> 1.833529e-05 | AH7: =COVAR(U:U,Q:Q) -> 0.00011750687 | AI7: =COVAR(U:U,U:U) -> 0.00045937481 | AK7: 44651 | AL7: 97.15 | AM7: 96.75 | AN7: =(AM7/AM6)-1 -> -0.13189771 | AO7: 44651 | AP7: 1471 | AQ7: 1470.35 | AR7: =(AQ7/AQ6)-1 -> -0.011030772 | AS7: 44651 | AT7: 2019.4 | AU7: 2048.65 | AV7: =(AU7/AU6)-1 -> -0.14607561 | AW7: 44651 | AX7: 2459.748 | AY7: 2431.873 | AZ7: =(AY7/AY6)-1 -> 0.30313793 | BA7: 44651 | BB7: 130.8 | BC7: 130.72 | BD7: =(BC7/BC6)-1 -> 0.51462835 | BE7: 44651 | BF7: 17519.2 | BG7: 17464.75 | BH7: =(BG7/BG6)-1 -> 0.17470497
B8: 44295 | C8: 116 | D8: 116.45 | E8: =(D8/D7)-1 -> 0.002582867 | F8: 44295 | G8: 1426 | H8: 1421.75 | I8: =(H8/H7)-1 -> -0.007712172 | J8: 44295 | K8: 2424 | L8: 2476 | M8: =(L8/L7)-1 -> 0.027428524 | N8: 44295 | O8: 1844.569 | P8: 1829.432 | Q8: =(P8/P7)-1 -> -0.01161844 | R8: 44295 | S8: 92.1 | T8: 89.95 | U8: =(T8/T7)-1 -> -0.020579268 | V8: 44295 | W8: 14882.65 | X8: 14834.85 | Y8: =(X8/X7)-1 -> -0.0026186987 | AK8: 44652 | AL8: 96.6 | AM8: 100.5 | AO8: 44652 | AP8: 1476.4 | AQ8: 1506 | AS8: 44652 | AT8: 2054.9 | AU8: 2078.15 | AW8: 44652 | AX8: 2433.027 | AY8: 2451.349 | BA8: 44652 | BB8: 131 | BC8: 131.71 | BE8: 44652 | BF8: 17436.9 | BG8: 17670.45
B9: 44298 | C9: 113.5 | D9: 104.4 | E9: =(D9/D8)-1 -> -0.10347789 | F9: 44298 | G9: 1393 | H9: 1367.05 | I9: =(H9/H8)-1 -> -0.038473712 | J9: 44298 | K9: 2441.5 | L9: 2462 | M9: =(L9/L8)-1 -> -0.0056542811 | N9: 44298 | O9: 1808.156 | P9: 1763.991 | Q9: =(P9/P8)-1 -> -0.035771212 | R9: 44298 | S9: 87.655 | T9: 85.155 | U9: =(T9/T8)-1 -> -0.053307393 | V9: 44298 | W9: 14644.65 | X9: 14310.8 | Y9: =(X9/X8)-1 -> -0.035325602 | AK9: 45016 | AL9: 72.7 | AM9: 72.75 | AN9: =(AM9/AM8)-1 -> -0.2761194 | AO9: 45016 | AP9: 1595.6 | AQ9: 1609.55 | AR9: =(AQ9/AQ8)-1 -> 0.0687583 | AS9: 45016 | AT9: 2558.8 | AU9: 2560.35 | AV9: =(AU9/AU8)-1 -> 0.2320333 | AW9: 45016 | AX9: 2081.364 | AY9: 2151.558 | AZ9: =(AY9/AY8)-1 -> -0.12229634 | BA9: 45016 | BB9: 105 | BC9: 104.5 | BD9: =(BC9/BC8)-1 -> -0.20659024 | BE9: 45016 | BF9: 17210.35 | BG9: 17359.75 | BH9: =(BG9/BG8)-1 -> -0.017583027
B10: 44299 | C10: 105.05 | D10: 109.2 | E10: =(D10/D9)-1 -> 0.045977011 | F10: 44299 | G10: 1368 | H10: 1400.35 | I10: =(H10/H9)-1 -> 0.024359021 | J10: 44299 | K10: 2470 | L10: 2454.4 | M10: =(L10/L9)-1 -> -0.0030869212 | N10: 44299 | O10: 1775.851 | P10: 1783.051 | Q10: =(P10/P9)-1 -> 0.010805044 | R10: 44299 | S10: 86.2 | T10: 87.9 | U10: =(T10/T9)-1 -> 0.032235336 | V10: 44299 | W10: 14364.9 | X10: 14504.8 | Y10: =(X10/X9)-1 -> 0.013556195 | AK10: 45019 | AL10: 74.8 | AM10: 77.45 | AO10: 45019 | AP10: 1607.55 | AQ10: 1610.55 | AS10: 45019 | AT10: 2570 | AU10: 2536.1 | AW10: 45019 | AX10: 2164.434 | AY10: 2151.927 | BA10: 45019 | BB10: 105.1 | BC10: 104.1 | BE10: 45019 | BF10: 17427.95 | BG10: 17398.05
B11: 44301 | C11: 108.15 | D11: 107.1 | E11: =(D11/D10)-1 -> -0.019230769 | F11: 44301 | G11: 1405 | H11: 1430.1 | I11: =(H11/H10)-1 -> 0.021244689 | J11: 44301 | K11: 2497 | L11: 2460.65 | M11: =(L11/L10)-1 -> 0.0025464472 | N11: 44301 | O11: 1777.974 | P11: 1794.588 | Q11: =(P11/P10)-1 -> 0.0064703702 | R11: 44301 | S11: 89.2 | T11: 89.82 | U11: =(T11/T10)-1 -> 0.021843003 | V11: 44301 | W11: 14522.4 | X11: 14581.45 | Y11: =(X11/X10)-1 -> 0.0052844576 | AB11: Calculating Returns, Weights, Std Dev and Beta of Individual Securities | AK11: 45379 | AL11: 213 | AM11: 207.9 | AN11: =(AM11/AM10)-1 -> 1.6843125 | AO11: 45379 | AP11: 1440.7 | AQ11: 1447.9 | AR11: =(AQ11/AQ10)-1 -> -0.10099034 | AS11: 45379 | AT11: 2245 | AU11: 2264.35 | AV11: =(AU11/AU10)-1 -> -0.10715271 | AW11: 45379 | AX11: 2985.75 | AY11: 2971.7 | AZ11: =(AY11/AY10)-1 -> 0.38094833 | BA11: 45379 | BB11: 152.7 | BC11: 155.85 | BD11: =(BC11/BC10)-1 -> 0.49711816 | BE11: 45379 | BF11: 22163.6 | BG11: 22326.9 | BH11: =(BG11/BG10)-1 -> 0.28329899
B12: 44302 | C12: 107.9 | D12: 112.3 | E12: =(D12/D11)-1 -> 0.048552754 | F12: 44302 | G12: 1434.95 | H12: 1428.65 | I12: =(H12/H11)-1 -> -0.0010139151 | J12: 44302 | K12: 2469.9 | L12: 2458.9 | M12: =(L12/L11)-1 -> -0.0007111942 | N12: 44302 | O12: 1787.481 | P12: 1783.328 | Q12: =(P12/P11)-1 -> -0.0062744206 | R12: 44302 | S12: 90.38 | T12: 89.025 | U12: =(T12/T11)-1 -> -0.0088510354 | V12: 44302 | W12: 14599.6 | X12: 14617.85 | Y12: =(X12/X11)-1 -> 0.0024963224 | AB12: Security | AC12: Returns | AD12: Weights | AE12: Weighted Return | AF12: Risk(Std Dev) | AG12: Beta | AH12: Weighted Beta
B13: 44305 | C13: 108.9 | D13: 108.55 | E13: =(D13/D12)-1 -> -0.033392698 | F13: 44305 | G13: 1390 | H13: 1412.4 | I13: =(H13/H12)-1 -> -0.011374374 | J13: 44305 | K13: 2440 | L13: 2436.65 | M13: =(L13/L12)-1 -> -0.0090487616 | N13: 44305 | O13: 1757.391 | P13: 1755.268 | Q13: =(P13/P12)-1 -> -0.015734627 | R13: 44305 | S13: 86.98 | T13: 88.805 | U13: =(T13/T12)-1 -> -0.002471216 | V13: 44305 | W13: 14306.6 | X13: 14359.45 | Y13: =(X13/X12)-1 -> -0.017677018 | AB13: Parag Milk Foods Ltd | AC13: =AVERAGE(E:E) -> 0.0012656678 | AD13: 0.3 | AE13: =(AC13*AD13) -> 0.00037970034 | AF13: =STDEV(E:E) -> 0.029362422 | AG13: =COVAR(E:E,Y:Y)/VAR(Y:Y) -> 0.93514347 | AH13: =AG13*AD13 -> 0.28054304
B14: 44306 | C14: 109.15 | D14: 106.9 | E14: =(D14/D13)-1 -> -0.015200368 | F14: 44306 | G14: 1425 | H14: 1391.4 | I14: =(H14/H13)-1 -> -0.014868309 | J14: 44306 | K14: 2456 | L14: 2397.45 | M14: =(L14/L13)-1 -> -0.016087661 | N14: 44306 | O14: 1763.391 | P14: 1754.761 | Q14: =(P14/P13)-1 -> -0.00028884478 | R14: 44306 | S14: 90 | T14: 89.4 | U14: =(T14/T13)-1 -> 0.0067000732 | V14: 44306 | W14: 14526.7 | X14: 14296.4 | Y14: =(X14/X13)-1 -> -0.0043908367 | AB14: HDFC Bank Ltd | AC14: =AVERAGE(I:I) -> 5.8250538e-05 | AD14: =0.7*(H3/AB3) -> 0.17825755 | AE14: =(AC14*AD14) -> 1.0383599e-05 | AF14: =STDEV(I:I) -> 0.013721419 | AG14: =COVAR(I:I,Y:Y)/VAR(Y:Y) -> 1.1132767 | AH14: =AG14*AD14 -> 0.19844998 | AL14: Return (21-22) | AM14: Return (22-23) | AN14: Return (23-24) | AO14: Weights | AP14: Weighted Return (21-22) | AQ14: Weighted Return (22-23) | AR14: Weighted Return (23-24)
B15: 44308 | C15: 106.9 | D15: 106.8 | E15: =(D15/D14)-1 -> -0.00093545369 | F15: 44308 | G15: 1380 | H15: 1422.5 | I15: =(H15/H14)-1 -> 0.022351588 | J15: 44308 | K15: 2390 | L15: 2349.4 | M15: =(L15/L14)-1 -> -0.020042128 | N15: 44308 | O15: 1746.546 | P15: 1759.607 | Q15: =(P15/P14)-1 -> 0.0027616296 | R15: 44308 | S15: 89.995 | T15: 92.14 | U15: =(T15/T14)-1 -> 0.03064877 | V15: 44308 | W15: 14219.15 | X15: 14406.15 | Y15: =(X15/X14)-1 -> 0.0076767578 | AB15: Hindustan Unilever Ltd | AC15: =AVERAGE(M:M) -> 1.7995846e-06 | AD15: =0.7*(L3/AB3) -> 0.28764601 | AE15: =(AC15*AD15) -> 5.1764331e-07 | AF15: =STDEV(M:M) -> 0.012653866 | AG15: =COVAR(M:M,Y:Y)/VAR(Y:Y) -> 0.61771585 | AH15: =AG15*AD15 -> 0.1776835 | AK15: Parag Milk Foods Ltd | AL15: -0.13189771 | AM15: -0.2761194 | AN15: 1.6843125 | AO15: 0.3 | AP15: =AL15*AO15 -> -0.039569314 | AQ15: =AM15*AO15 -> -0.082835821 | AR15: =AN15*AO15 -> 0.50529374
B16: 44309 | C16: 107.45 | D16: 111.75 | E16: =(D16/D15)-1 -> 0.046348315 | F16: 44309 | G16: 1409 | H16: 1414.15 | I16: =(H16/H15)-1 -> -0.0058699473 | J16: 44309 | K16: 2340 | L16: 2307.75 | M16: =(L16/L15)-1 -> -0.017727931 | N16: 44309 | O16: 1759.237 | P16: 1757.714 | Q16: =(P16/P15)-1 -> -0.0010758084 | R16: 44309 | S16: 92.98 | T16: 92.56 | U16: =(T16/T15)-1 -> 0.0045582809 | V16: 44309 | W16: 14326.35 | X16: 14341.35 | Y16: =(X16/X15)-1 -> -0.0044980789 | AB16: Reliance Industries Ltd | AC16: =AVERAGE(Q:Q) -> 0.0007348725 | AD16: =0.7*(P3/AB3) -> 0.22374869 | AE16: =(AC16*AD16) -> 0.00016442676 | AF16: =STDEV(Q:Q) -> 0.014527247 | AG16: =COVAR(Q:Q,Y:Y)/VAR(Y:Y) -> 1.1255285 | AH16: =AG16*AD16 -> 0.25183552 | AK16: HDFC Bank Ltd | AL16: -0.011030772 | AM16: 0.0687583 | AN16: -0.10099034 | AO16: 0.17825755 | AP16: =AL16*AO16 -> -0.0019663184 | AQ16: =AM16*AO16 -> 0.012256686 | AR16: =AN16*AO16 -> -0.018002292
B17: 44312 | C17: 112.45 | D17: 114.3 | E17: =(D17/D16)-1 -> 0.022818792 | F17: 44312 | G17: 1413 | H17: 1404.8 | I17: =(H17/H16)-1 -> -0.0066117456 | J17: 44312 | K17: 2324 | L17: 2360.65 | M17: =(L17/L16)-1 -> 0.02292276 | N17: 44312 | O17: 1772.159 | P17: 1788.635 | Q17: =(P17/P16)-1 -> 0.017591599 | R17: 44312 | S17: 93.5 | T17: 94.075 | U17: =(T17/T16)-1 -> 0.016367761 | V17: 44312 | W17: 14449.45 | X17: 14485 | Y17: =(X17/X16)-1 -> 0.010016491 | AB17: Tata Steel Ltd | AC17: =AVERAGE(U:U) -> 0.0010307844 | AD17: =0.7*(T3/AB3) -> 0.010347751 | AE17: =(AC17*AD17) -> 1.0666299e-05 | AF17: =STDEV(U:U) -> 0.021447547 | AG17: =COVAR(U:U,Y:Y)/VAR(Y:Y) -> 1.356409 | AH17: =AG17*AD17 -> 0.014035782 | AK17: Hindustan Unilever Ltd | AL17: -0.14607561 | AM17: 0.2320333 | AN17: -0.10715271 | AO17: 0.28764601 | AP17: =AL17*AO17 -> -0.042018066 | AQ17: =AM17*AO17 -> 0.066743451 | AR17: =AN17*AO17 -> -0.03082205
B18: 44313 | C18: 115 | D18: 111.9 | E18: =(D18/D17)-1 -> -0.020997375 | F18: 44313 | G18: 1407.25 | H18: 1438.7 | I18: =(H18/H17)-1 -> 0.024131549 | J18: 44313 | K18: 2363 | L18: 2379.85 | M18: =(L18/L17)-1 -> 0.0081333531 | N18: 44313 | O18: 1790.619 | P18: 1835.523 | Q18: =(P18/P17)-1 -> 0.026214404 | R18: 44313 | S18: 94.83 | T18: 97.775 | U18: =(T18/T17)-1 -> 0.039330322 | V18: 44313 | W18: 14493.8 | X18: 14653.05 | Y18: =(X18/X17)-1 -> 0.011601657 | AB18: Nifty 50 | AC18: =AVERAGE(Y:Y) -> 0.00058793455 | AF18: =STDEV(Y:Y) -> 0.0086608488 | AG18: 1 | AK18: Reliance Industries Ltd | AL18: 0.30313793 | AM18: -0.12229634 | AN18: 0.38094833 | AO18: 0.22374869 | AP18: =AL18*AO18 -> 0.067826715 | AQ18: =AM18*AO18 -> -0.027363645 | AR18: =AN18*AO18 -> 0.08523669
B19: 44314 | C19: 113.3 | D19: 114.15 | E19: =(D19/D18)-1 -> 0.020107239 | F19: 44314 | G19: 1436.25 | H19: 1476.8 | I19: =(H19/H18)-1 -> 0.026482241 | J19: 44314 | K19: 2380 | L19: 2406.55 | M19: =(L19/L18)-1 -> 0.011219194 | N19: 44314 | O19: 1844.015 | P19: 1843.507 | Q19: =(P19/P18)-1 -> 0.004349714 | R19: 44314 | S19: 98.5 | T19: 97.14 | U19: =(T19/T18)-1 -> -0.0064945027 | V19: 44314 | W19: 14710.5 | X19: 14864.55 | Y19: =(X19/X18)-1 -> 0.014433855 | AK19: Tata Steel Ltd | AL19: 0.51462835 | AM19: -0.20659024 | AN19: 0.49711816 | AO19: 0.010347751 | AP19: =AL19*AO19 -> 0.0053252459 | AQ19: =AM19*AO19 -> -0.0021377442 | AR19: =AN19*AO19 -> 0.0051440547
B20: 44315 | C20: 115 | D20: 112.05 | E20: =(D20/D19)-1 -> -0.018396846 | F20: 44315 | G20: 1486.2 | H20: 1472.5 | I20: =(H20/H19)-1 -> -0.002911701 | J20: 44315 | K20: 2433 | L20: 2407.6 | M20: =(L20/L19)-1 -> 0.00043630924 | N20: 44315 | O20: 1867.136 | P20: 1868.198 | Q20: =(P20/P19)-1 -> 0.013393494 | R20: 44315 | S20: 98.3 | T20: 103.135 | U20: =(T20/T19)-1 -> 0.06171505 | V20: 44315 | W20: 14979 | X20: 14894.9 | Y20: =(X20/X19)-1 -> 0.0020417705 | AD20: PORTFOLIO PARAMETERS | AK20: Nifty 50 | AL20: 0.17470497 | AM20: -0.017583027 | AN20: 0.28329899
B21: 44316 | C21: 111 | D21: 111.7 | E21: =(D21/D20)-1 -> -0.0031236055 | F21: 44316 | G21: 1445 | H21: 1412.3 | I21: =(H21/H20)-1 -> -0.040882852 | J21: 44316 | K21: 2410 | L21: 2353.75 | M21: =(L21/L20)-1 -> -0.022366672 | N21: 44316 | O21: 1853.845 | P21: 1840.923 | Q21: =(P21/P20)-1 -> -0.01459963 | R21: 44316 | S21: 102.4 | T21: 103.4 | U21: =(T21/T20)-1 -> 0.0025694478 | V21: 44316 | W21: 14747.35 | X21: 14631.1 | Y21: =(X21/X20)-1 -> -0.01771076 | AD21: Portfolio Return | AE21: =SUM(AE13:AE17) -> 0.00056569464 | AK21: PORTFOLIO RETURNS | AP21: =SUM(AP15:AP20) -> -0.010401738 | AQ21: =SUM(AQ15:AQ20) -> -0.033337072 | AR21: =SUM(AR15:AR20) -> 0.54685014
B22: 44319 | C22: 111.05 | D22: 113.95 | E22: =(D22/D21)-1 -> 0.020143241 | F22: 44319 | G22: 1393 | H22: 1414.45 | I22: =(H22/H21)-1 -> 0.0015223394 | J22: 44319 | K22: 2343 | L22: 2408 | M22: =(L22/L21)-1 -> 0.023048327 | N22: 44319 | O22: 1814.617 | P22: 1808.203 | Q22: =(P22/P21)-1 -> -0.017773693 | R22: 44319 | S22: 103.195 | T22: 106.475 | U22: =(T22/T21)-1 -> 0.029738878 | V22: 44319 | W22: 14481.05 | X22: 14634.15 | Y22: =(X22/X21)-1 -> 0.00020846006 | AD22: Portfolio Variance | AE22: {=MMULT(TRANSPOSE(AD13:AD17),MMULT(AE3:AI7,AD13:AD17))} -> 0.00014532993
B23: 44320 | C23: 114.5 | D23: 115.35 | E23: =(D23/D22)-1 -> 0.01228609 | F23: 44320 | G23: 1409.95 | H23: 1388.35 | I23: =(H23/H22)-1 -> -0.018452402 | J23: 44320 | K23: 2409.2 | L23: 2407.65 | M23: =(L23/L22)-1 -> -0.00014534884 | N23: 44320 | O23: 1799.849 | P23: 1769.021 | Q23: =(P23/P22)-1 -> -0.021669027 | R23: 44320 | S23: 107.445 | T23: 106.385 | U23: =(T23/T22)-1 -> -0.00084526884 | V23: 44320 | W23: 14687.25 | X23: 14496.5 | Y23: =(X23/X22)-1 -> -0.009406081 | AD23: Portfolio Std Dev (Risk) | AE23: =SQRT(AE22) -> 0.012055286 | AP23: Clearly portfolio returns have significantly increased in subsequent years
B24: 44321 | C24: 115.7 | D24: 134.1 | E24: =(D24/D23)-1 -> 0.16254876 | F24: 44321 | G24: 1401 | H24: 1402.6 | I24: =(H24/H23)-1 -> 0.010263982 | J24: 44321 | K24: 2434 | L24: 2394.65 | M24: =(L24/L23)-1 -> -0.0053994559 | N24: 44321 | O24: 1775.251 | P24: 1772.252 | Q24: =(P24/P23)-1 -> 0.0018264339 | R24: 44321 | S24: 108.4 | T24: 107.015 | U24: =(T24/T23)-1 -> 0.0059218875 | V24: 44321 | W24: 14604.15 | X24: 14617.85 | Y24: =(X24/X23)-1 -> 0.0083709861 | AD24: Portfolio Beta | AE24: =sum(AH13:AH17) -> 0.92254782
B25: 44322 | C25: 137.5 | D25: 138.9 | E25: =(D25/D24)-1 -> 0.035794183 | F25: 44322 | G25: 1407.6 | H25: 1400.9 | I25: =(H25/H24)-1 -> -0.0012120348 | J25: 44322 | K25: 2400 | L25: 2390 | M25: =(L25/L24)-1 -> -0.0019418287 | N25: 44322 | O25: 1773.867 | P25: 1782.312 | Q25: =(P25/P24)-1 -> 0.0056763937 | R25: 44322 | S25: 105.5 | T25: 110.09 | U25: =(T25/T24)-1 -> 0.02873429 | V25: 44322 | W25: 14668.35 | X25: 14724.8 | Y25: =(X25/X24)-1 -> 0.0073163974 | AI25: Rf for 10 year Government Bond in India is at 6.93%
B26: 44323 | C26: 139.85 | D26: 135.5 | E26: =(D26/D25)-1 -> -0.024478042 | F26: 44323 | G26: 1412.95 | H26: 1414.75 | I26: =(H26/H25)-1 -> 0.0098865015 | J26: 44323 | K26: 2408.8 | L26: 2411.2 | M26: =(L26/L25)-1 -> 0.0088702929 | N26: 44323 | O26: 1788.543 | P26: 1783.005 | Q26: =(P26/P25)-1 -> 0.00038882081 | R26: 44323 | S26: 113.5 | T26: 118.235 | U26: =(T26/T25)-1 -> 0.073984921 | V26: 44323 | W26: 14816.85 | X26: 14823.15 | Y26: =(X26/X25)-1 -> 0.0066792079
B27: 44326 | C27: 139 | D27: 137.75 | E27: =(D27/D26)-1 -> 0.016605166 | F27: 44326 | G27: 1427 | H27: 1419.85 | I27: =(H27/H26)-1 -> 0.0036048772 | J27: 44326 | K27: 2423 | L27: 2432.9 | M27: =(L27/L26)-1 -> 0.0089996682 | N27: 44326 | O27: 1789.696 | P27: 1777.882 | Q27: =(P27/P26)-1 -> -0.0028732393 | R27: 44326 | S27: 121 | T27: 121.635 | U27: =(T27/T26)-1 -> 0.02875629 | V27: 44326 | W27: 14928.25 | X27: 14942.35 | Y27: =(X27/X26)-1 -> 0.0080414757 | AD27: Ratios | AE27: Portfolio | AF27: Market | AG27: Parag Milk Foods Limited
B28: 44327 | C28: 135 | D28: 146.6 | E28: =(D28/D27)-1 -> 0.064246824 | F28: 44327 | G28: 1396 | H28: 1403.55 | I28: =(H28/H27)-1 -> -0.011480086 | J28: 44327 | K28: 2425 | L28: 2402.1 | M28: =(L28/L27)-1 -> -0.012659789 | N28: 44327 | O28: 1767.544 | P28: 1784.297 | Q28: =(P28/P27)-1 -> 0.003608226 | R28: 44327 | S28: 119 | T28: 123.39 | U28: =(T28/T27)-1 -> 0.014428413 | V28: 44327 | W28: 14789.7 | X28: 14850.75 | Y28: =(X28/X27)-1 -> -0.0061302272 | AD28: Sharpe Ratio | AE28: =(AE21-AJ29)/AE23 -> 0.024113458 | AF28: =(AC18-AJ29)/AF18 -> 0.036132087 | AG28: =(AC13-AJ29)/AF13 -> 0.033739308 | AI28: Risk Free Rate | AJ28: 0.0693
B29: 44328 | C29: 146.5 | D29: 149.65 | E29: =(D29/D28)-1 -> 0.020804911 | F29: 44328 | G29: 1399.75 | H29: 1399.5 | I29: =(H29/H28)-1 -> -0.0028855402 | J29: 44328 | K29: 2389 | L29: 2328.95 | M29: =(L29/L28)-1 -> -0.030452521 | N29: 44328 | O29: 1781.482 | P29: 1765.837 | Q29: =(P29/P28)-1 -> -0.010345811 | R29: 44328 | S29: 123.195 | T29: 117.915 | U29: =(T29/T28)-1 -> -0.044371505 | V29: 44328 | W29: 14823.55 | X29: 14696.5 | Y29: =(X29/X28)-1 -> -0.010386681 | AD29: Treynor Ratio | AE29: =(AE21-AJ29)/AE24 -> 0.0003150998 | AF29: =AC18-AJ29 -> 0.00031293455 | AG29: =(AC13-AJ29)/AG13 -> 0.0010593752 | AI29: Daily Risk free rate | AJ29: =AJ28/252 -> 0.000275
B30: 44330 | C30: 151.6 | D30: 145.75 | E30: =(D30/D29)-1 -> -0.026060809 | F30: 44330 | G30: 1394.35 | H30: 1386.85 | I30: =(H30/H29)-1 -> -0.0090389425 | J30: 44330 | K30: 2328.9 | L30: 2376.85 | M30: =(L30/L29)-1 -> 0.020567208 | N30: 44330 | O30: 1779.589 | P30: 1788.127 | Q30: =(P30/P29)-1 -> 0.012622909 | R30: 44330 | S30: 118.5 | T30: 113.21 | U30: =(T30/T29)-1 -> -0.039901624 | V30: 44330 | W30: 14749.4 | X30: 14677.8 | Y30: =(X30/X29)-1 -> -0.0012724118
B31: 44333 | C31: 148.7 | D31: 146.75 | E31: =(D31/D30)-1 -> 0.0068610635 | F31: 44333 | G31: 1395.15 | H31: 1440.25 | I31: =(H31/H30)-1 -> 0.038504525 | J31: 44333 | K31: 2385 | L31: 2376.25 | M31: =(L31/L30)-1 -> -0.00025243495 | N31: 44333 | O31: 1788.127 | P31: 1809.402 | Q31: =(P31/P30)-1 -> 0.011897924 | R31: 44333 | S31: 113.8 | T31: 115.085 | U31: =(T31/T30)-1 -> 0.016562141 | V31: 44333 | W31: 14756.25 | X31: 14923.15 | Y31: =(X31/X30)-1 -> 0.01671572 | AB31: PART (B)
B32: 44334 | C32: 147.95 | D32: 143.6 | E32: =(D32/D31)-1 -> -0.021465077 | F32: 44334 | G32: 1458.95 | H32: 1476.7 | I32: =(H32/H31)-1 -> 0.025308106 | J32: 44334 | K32: 2402.1 | L32: 2374.25 | M32: =(L32/L31)-1 -> -0.00084166228 | N32: 44334 | O32: 1828.462 | P32: 1834.877 | Q32: =(P32/P31)-1 -> 0.014079237 | R32: 44334 | S32: 117.5 | T32: 118 | U32: =(T32/T31)-1 -> 0.025329105 | V32: 44334 | W32: 15067.2 | X32: 15108.1 | Y32: =(X32/X31)-1 -> 0.012393496
B33: 44335 | C33: 144.25 | D33: 144.15 | E33: =(D33/D32)-1 -> 0.0038300836 | F33: 44335 | G33: 1470.2 | H33: 1458.2 | I33: =(H33/H32)-1 -> -0.012527934 | J33: 44335 | K33: 2360 | L33: 2359.75 | M33: =(L33/L32)-1 -> -0.0061071917 | N33: 44335 | O33: 1827.539 | P33: 1843.276 | Q33: =(P33/P32)-1 -> 0.0045774185 | R33: 44335 | S33: 117.3 | T33: 116.425 | U33: =(T33/T32)-1 -> -0.013347458 | V33: 44335 | W33: 15058.6 | X33: 15030.15 | Y33: =(X33/X32)-1 -> -0.005159484 | AB33: Comparing Portfolio's Performance with the Performance of Parag Milk Foods Ltd
B34: 44336 | C34: 146.6 | D34: 140.9 | E34: =(D34/D33)-1 -> -0.022545959 | F34: 44336 | G34: 1458.35 | H34: 1432.8 | I34: =(H34/H33)-1 -> -0.017418735 | J34: 44336 | K34: 2360 | L34: 2344.15 | M34: =(L34/L33)-1 -> -0.0066108698 | N34: 44336 | O34: 1844.061 | P34: 1832.524 | Q34: =(P34/P33)-1 -> -0.0058330928 | R34: 44336 | S34: 113.11 | T34: 110.505 | U34: =(T34/T33)-1 -> -0.050848186 | V34: 44336 | W34: 15042.6 | X34: 14906.05 | Y34: =(X34/X33)-1 -> -0.0082567373 | AC34: Stock | AD34: Returns | AE34: Risk(Std Dev) | AF34: Beta | AG34: Coefficient of Variation
B35: 44337 | C35: 141 | D35: 140.55 | E35: =(D35/D34)-1 -> -0.0024840312 | F35: 44337 | G35: 1443 | H35: 1497.3 | I35: =(H35/H34)-1 -> 0.04501675 | J35: 44337 | K35: 2340 | L35: 2362.25 | M35: =(L35/L34)-1 -> 0.0077213489 | N35: 44337 | O35: 1838.615 | P35: 1848.353 | Q35: =(P35/P34)-1 -> 0.0086378132 | R35: 44337 | S35: 111.4 | T35: 111.31 | U35: =(T35/T34)-1 -> 0.0072847382 | V35: 44337 | W35: 14987.8 | X35: 15175.3 | Y35: =(X35/X34)-1 -> 0.018063135 | AC35: Parag Milk Foods Ltd | AD35: 0.0012656678 | AE35: 0.029362422 | AF35: 0.93514347 | AG35: =AE35/AD35 -> 23.199154
B36: 44340 | C36: 141 | D36: 141.45 | E36: =(D36/D35)-1 -> 0.0064034152 | F36: 44340 | G36: 1503.25 | H36: 1509.95 | I36: =(H36/H35)-1 -> 0.0084485407 | J36: 44340 | K36: 2355 | L36: 2336.55 | M36: =(L36/L35)-1 -> -0.010879458 | N36: 44340 | O36: 1853.383 | P36: 1832.754 | Q36: =(P36/P35)-1 -> -0.0084394052 | R36: 44340 | S36: 110.8 | T36: 109.2 | U36: =(T36/T35)-1 -> -0.018956069 | V36: 44340 | W36: 15211.35 | X36: 15197.7 | Y36: =(X36/X35)-1 -> 0.0014760828 | AC36: Portfolio | AD36: 0.00056569464 | AE36: 0.012055286 | AF36: 0.92254782 | AG36: =AE36/AD36 -> 21.31059
B37: 44341 | C37: 141.45 | D37: 145.4 | E37: =(D37/D36)-1 -> 0.027925062 | F37: 44341 | G37: 1510.5 | H37: 1478.95 | I37: =(H37/H36)-1 -> -0.020530481 | J37: 44341 | K37: 2355 | L37: 2344.05 | M37: =(L37/L36)-1 -> 0.0032098607 | N37: 44341 | O37: 1842.677 | P37: 1811.987 | Q37: =(P37/P36)-1 -> -0.011331035 | R37: 44341 | S37: 110.195 | T37: 110.52 | U37: =(T37/T36)-1 -> 0.012087912 | V37: 44341 | W37: 15291.75 | X37: 15208.45 | Y37: =(X37/X36)-1 -> 0.00070734387
B38: 44342 | C38: 146 | D38: 140.6 | E38: =(D38/D37)-1 -> -0.03301238 | F38: 44342 | G38: 1480 | H38: 1477.05 | I38: =(H38/H37)-1 -> -0.0012846952 | J38: 44342 | K38: 2355.75 | L38: 2354 | M38: =(L38/L37)-1 -> 0.00424479 | N38: 44342 | O38: 1822.924 | P38: 1818.355 | Q38: =(P38/P37)-1 -> 0.003514374 | R38: 44342 | S38: 109.05 | T38: 108.215 | U38: =(T38/T37)-1 -> -0.020855954 | V38: 44342 | W38: 15257.05 | X38: 15301.45 | Y38: =(X38/X37)-1 -> 0.0061150216
B39: 44343 | C39: 141.7 | D39: 141.15 | E39: =(D39/D38)-1 -> 0.0039118065 | F39: 44343 | G39: 1473.1 | H39: 1482.65 | I39: =(H39/H38)-1 -> 0.0037913408 | J39: 44343 | K39: 2353 | L39: 2326.4 | M39: =(L39/L38)-1 -> -0.011724724 | N39: 44343 | O39: 1818.586 | P39: 1823.94 | Q39: =(P39/P38)-1 -> 0.0030714574 | R39: 44343 | S39: 108.215 | T39: 109.665 | U39: =(T39/T38)-1 -> 0.013399251 | V39: 44343 | W39: 15323.95 | X39: 15337.85 | Y39: =(X39/X38)-1 -> 0.0023788595
B40: 44344 | C40: 142.2 | D40: 137.9 | E40: =(D40/D39)-1 -> -0.023025151 | F40: 44344 | G40: 1490.9 | H40: 1503.45 | I40: =(H40/H39)-1 -> 0.014028935 | J40: 44344 | K40: 2333.35 | L40: 2321.7 | M40: =(L40/L39)-1 -> -0.0020202889 | N40: 44344 | O40: 1836.769 | P40: 1933.5 | Q40: =(P40/P39)-1 -> 0.060067765 | R40: 44344 | S40: 113.1 | T40: 110.35 | U40: =(T40/T39)-1 -> 0.0062462955 | V40: 44344 | W40: 15421.2 | X40: 15435.65 | Y40: =(X40/X39)-1 -> 0.0063763826 | AC40: As you can clearly see in the table above, the returns obtained by investing in Parag Milk Foods Ltd is more than that obtained from investment in the price-weighted portfolio of securities. But the risk is significantly reduced by investing in the portfolio. The Std Dev of the portfolio is less than half the std dev of Parag Milk Foods. This clearly states that investing in the portfolio is much less riskier than the individual security and benifits of diversification can be clearly seen. The Betas of the portfolio and the individual security are almost the same. This shows that diversification can reduce the unsystematic risk / the idiosyncratic risk of the stock but not the systmatic risk.
B41: 44347 | C41: 138.05 | D41: 135.1 | E41: =(D41/D40)-1 -> -0.020304569 | F41: 44347 | G41: 1500 | H41: 1515.85 | I41: =(H41/H40)-1 -> 0.008247697 | J41: 44347 | K41: 2325 | L41: 2340.05 | M41: =(L41/L40)-1 -> 0.0079036913 | N41: 44347 | O41: 1940.145 | P41: 1993.956 | Q41: =(P41/P40)-1 -> 0.031267649 | R41: 44347 | S41: 111.2 | T41: 112.565 | U41: =(T41/T40)-1 -> 0.020072497 | V41: 44347 | W41: 15437.75 | X41: 15582.8 | Y41: =(X41/X40)-1 -> 0.0095331262
B42: 44348 | C42: 137.5 | D42: 139.6 | E42: =(D42/D41)-1 -> 0.03330866 | F42: 44348 | G42: 1520.3 | H42: 1511.7 | I42: =(H42/H41)-1 -> -0.0027377379 | J42: 44348 | K42: 2347 | L42: 2358.3 | M42: =(L42/L41)-1 -> 0.0077989787 | N42: 44348 | O42: 1999.217 | P42: 2001.894 | Q42: =(P42/P41)-1 -> 0.0039810307 | R42: 44348 | S42: 112 | T42: 110.09 | U42: =(T42/T41)-1 -> -0.021987296 | V42: 44348 | W42: 15629.65 | X42: 15574.85 | Y42: =(X42/X41)-1 -> -0.00051017789
B43: 44349 | C43: 140.4 | D43: 140.4 | E43: =(D43/D42)-1 -> 0.005730659 | F43: 44349 | G43: 1510 | H43: 1504 | I43: =(H43/H42)-1 -> -0.0050936032 | J43: 44349 | K43: 2356 | L43: 2358.8 | M43: =(L43/L42)-1 -> 0.00021201713 | N43: 44349 | O43: 1990.91 | P43: 2031.753 | Q43: =(P43/P42)-1 -> 0.014915375 | R43: 44349 | S43: 110.5 | T43: 112.405 | U43: =(T43/T42)-1 -> 0.02102825 | V43: 44349 | W43: 15520.35 | X43: 15576.2 | Y43: =(X43/X42)-1 -> 8.6678202e-05
B44: 44350 | C44: 141.5 | D44: 139.7 | E44: =(D44/D43)-1 -> -0.004985755 | F44: 44350 | G44: 1508 | H44: 1520.55 | I44: =(H44/H43)-1 -> 0.011003989 | J44: 44350 | K44: 2369 | L44: 2363.25 | M44: =(L44/L43)-1 -> 0.0018865525 | N44: 44350 | O44: 2049.982 | P44: 2039.506 | Q44: =(P44/P43)-1 -> 0.0038159166 | R44: 44350 | S44: 112.955 | T44: 112.2 | U44: =(T44/T43)-1 -> -0.0018237623 | V44: 44350 | W44: 15655.55 | X44: 15690.35 | Y44: =(X44/X43)-1 -> 0.0073284883
B45: 44351 | C45: 139.6 | D45: 139.25 | E45: =(D45/D44)-1 -> -0.0032211883 | F45: 44351 | G45: 1516 | H45: 1500.95 | I45: =(H45/H44)-1 -> -0.012890073 | J45: 44351 | K45: 2370 | L45: 2342.05 | M45: =(L45/L44)-1 -> -0.0089706971 | N45: 44351 | O45: 2044.26 | P45: 2021.831 | Q45: =(P45/P44)-1 -> -0.0086663143 | R45: 44351 | S45: 111.6 | T45: 112.07 | U45: =(T45/T44)-1 -> -0.0011586453 | V45: 44351 | W45: 15712.5 | X45: 15670.25 | Y45: =(X45/X44)-1 -> -0.0012810422
B46: 44354 | C46: 140.35 | D46: 138.75 | E46: =(D46/D45)-1 -> -0.0035906643 | F46: 44354 | G46: 1510 | H46: 1499.85 | I46: =(H46/H45)-1 -> -0.00073286918 | J46: 44354 | K46: 2354 | L46: 2339.3 | M46: =(L46/L45)-1 -> -0.001174185 | N46: 44354 | O46: 2032.445 | P46: 2055.889 | Q46: =(P46/P45)-1 -> 0.016845127 | R46: 44354 | S46: 113 | T46: 112.87 | U46: =(T46/T45)-1 -> 0.0071383956 | V46: 44354 | W46: 15725.1 | X46: 15751.65 | Y46: =(X46/X45)-1 -> 0.0051945566
B47: 44355 | C47: 139.6 | D47: 140.85 | E47: =(D47/D46)-1 -> 0.015135135 | F47: 44355 | G47: 1496.55 | H47: 1483.05 | I47: =(H47/H46)-1 -> -0.01120112 | J47: 44355 | K47: 2339.3 | L47: 2359 | M47: =(L47/L46)-1 -> 0.0084213226 | N47: 44355 | O47: 2055.151 | P47: 2044.075 | Q47: =(P47/P46)-1 -> -0.0057464192 | R47: 44355 | S47: 113.27 | T47: 111.11 | U47: =(T47/T46)-1 -> -0.01559316 | V47: 44355 | W47: 15773.9 | X47: 15740.1 | Y47: =(X47/X46)-1 -> -0.00073325652
B48: 44356 | C48: 141.95 | D48: 138.9 | E48: =(D48/D47)-1 -> -0.013844515 | F48: 44356 | G48: 1483.9 | H48: 1480.3 | I48: =(H48/H47)-1 -> -0.0018542868 | J48: 44356 | K48: 2362 | L48: 2356 | M48: =(L48/L47)-1 -> -0.0012717253 | N48: 44356 | O48: 2048.136 | P48: 2007.524 | Q48: =(P48/P47)-1 -> -0.017881438 | R48: 44356 | S48: 111.7 | T48: 110.1 | U48: =(T48/T47)-1 -> -0.0090900909 | V48: 44356 | W48: 15766.3 | X48: 15635.35 | Y48: =(X48/X47)-1 -> -0.0066549768
B49: 44357 | C49: 142.1 | D49: 141.85 | E49: =(D49/D48)-1 -> 0.021238301 | F49: 44357 | G49: 1482.1 | H49: 1481.05 | I49: =(H49/H48)-1 -> 0.00050665406 | J49: 44357 | K49: 2364 | L49: 2378.8 | M49: =(L49/L48)-1 -> 0.0096774194 | N49: 44357 | O49: 2024.507 | P49: 2014.908 | Q49: =(P49/P48)-1 -> 0.0036781628 | R49: 44357 | S49: 110.93 | T49: 111.445 | U49: =(T49/T48)-1 -> 0.012216167 | V49: 44357 | W49: 15692.1 | X49: 15737.75 | Y49: =(X49/X48)-1 -> 0.0065492618
B50: 44358 | C50: 146 | D50: 146.75 | E50: =(D50/D49)-1 -> 0.034543532 | F50: 44358 | G50: 1491 | H50: 1486.35 | I50: =(H50/H49)-1 -> 0.0035785422 | J50: 44358 | K50: 2381 | L50: 2366.5 | M50: =(L50/L49)-1 -> -0.0051706743 | N50: 44358 | O50: 2014.816 | P50: 2042.737 | Q50: =(P50/P49)-1 -> 0.013811549 | R50: 44358 | S50: 112.78 | T50: 115.835 | U50: =(T50/T49)-1 -> 0.039391628 | V50: 44358 | W50: 15796.45 | X50: 15799.35 | Y50: =(X50/X49)-1 -> 0.0039141555
B51: 44361 | C51: 138.9 | D51: 138.5 | E51: =(D51/D50)-1 -> -0.056218058 | F51: 44361 | G51: 1478.25 | H51: 1479.45 | I51: =(H51/H50)-1 -> -0.0046422444 | J51: 44361 | K51: 2358.4 | L51: 2364.6 | M51: =(L51/L50)-1 -> -0.00080287344 | N51: 44361 | O51: 2044.444 | P51: 2072.042 | Q51: =(P51/P50)-1 -> 0.014345949 | R51: 44361 | S51: 116.8 | T51: 116.48 | U51: =(T51/T50)-1 -> 0.0055682652 | V51: 44361 | W51: 15791.4 | X51: 15811.85 | Y51: =(X51/X50)-1 -> 0.00079117179 | AB51: PART (C)
B52: 44362 | C52: 139.9 | D52: 146.1 | E52: =(D52/D51)-1 -> 0.054873646 | F52: 44362 | G52: 1486 | H52: 1490.25 | I52: =(H52/H51)-1 -> 0.0073000101 | J52: 44362 | K52: 2360 | L52: 2391.95 | M52: =(L52/L51)-1 -> 0.011566438 | N52: 44362 | O52: 2086.902 | P52: 2076.749 | Q52: =(P52/P51)-1 -> 0.0022716721 | R52: 44362 | S52: 117 | T52: 117.43 | U52: =(T52/T51)-1 -> 0.0081559066 | V52: 44362 | W52: 15866.95 | X52: 15869.25 | Y52: =(X52/X51)-1 -> 0.0036301888
B53: 44363 | C53: 147.1 | D53: 142.05 | E53: =(D53/D52)-1 -> -0.027720739 | F53: 44363 | G53: 1488 | H53: 1484.6 | I53: =(H53/H52)-1 -> -0.0037913102 | J53: 44363 | K53: 2385 | L53: 2407.9 | M53: =(L53/L52)-1 -> 0.0066681996 | N53: 44363 | O53: 2072.042 | P53: 2041.306 | Q53: =(P53/P52)-1 -> -0.017066579 | R53: 44363 | S53: 116.9 | T53: 114.215 | U53: =(T53/T52)-1 -> -0.027378012 | V53: 44363 | W53: 15847.5 | X53: 15767.55 | Y53: =(X53/X52)-1 -> -0.0064086204
B54: 44364 | C54: 143 | D54: 141.15 | E54: =(D54/D53)-1 -> -0.0063357973 | F54: 44364 | G54: 1466 | H54: 1466.1 | I54: =(H54/H53)-1 -> -0.012461269 | J54: 44364 | K54: 2398 | L54: 2417.7 | M54: =(L54/L53)-1 -> 0.0040699365 | N54: 44364 | O54: 2030.599 | P54: 2045.044 | Q54: =(P54/P53)-1 -> 0.0018311806 | R54: 44364 | S54: 111.895 | T54: 110.375 | U54: =(T54/T53)-1 -> -0.033620803 | V54: 44364 | W54: 15648.3 | X54: 15691.4 | Y54: =(X54/X53)-1 -> -0.0048295391 | AC54: Correlation Matrix of the Original Portfolio | AJ54: Correlation | AK54: Weights
B55: 44365 | C55: 142 | D55: 140.75 | E55: =(D55/D54)-1 -> -0.0028338647 | F55: 44365 | G55: 1469.5 | H55: 1479.8 | I55: =(H55/H54)-1 -> 0.0093445195 | J55: 44365 | K55: 2420 | L55: 2482.9 | M55: =(L55/L54)-1 -> 0.026967779 | N55: 44365 | O55: 2054.136 | P55: 2054.274 | Q55: =(P55/P54)-1 -> 0.0045133503 | R55: 44365 | S55: 110.5 | T55: 109.23 | U55: =(T55/T54)-1 -> -0.010373726 | V55: 44365 | W55: 15756.5 | X55: 15683.35 | Y55: =(X55/X54)-1 -> -0.00051301987 | AD55: Parag Milk Food Ltd | AE55: HDFC Bank Ltd | AF55: HUL | AG55: Reliance Ind Ltd | AH55: Tata Steel Ltd | AJ55: 1 | AK55: 0.3
B56: 44368 | C56: 139.3 | D56: 139.2 | E56: =(D56/D55)-1 -> -0.011012433 | F56: 44368 | G56: 1461.35 | H56: 1488.7 | I56: =(H56/H55)-1 -> 0.0060143263 | J56: 44368 | K56: 2473.95 | L56: 2514.35 | M56: =(L56/L55)-1 -> 0.01266664 | N56: 44368 | O56: 2033.83 | P56: 2064.981 | Q56: =(P56/P55)-1 -> 0.0052120603 | R56: 44368 | S56: 107 | T56: 110.615 | U56: =(T56/T55)-1 -> 0.012679667 | V56: 44368 | W56: 15525.85 | X56: 15746.5 | Y56: =(X56/X55)-1 -> 0.0040265632 | AC56: Parag Milk Food Ltd | AD56: =CORREL(E:E,E:E) -> 1 | AE56: =CORREL(E:E,I:I) -> 0.11139489 | AF56: =CORREL(E:E,M:M) -> 0.091194553 | AG56: =CORREL(E:E,Q:Q) -> 0.18404791 | AH56: =CORREL(E:E,U:U) -> 0.21813492 | AJ56: 0.21813492 | AK56: 0.28764601
B57: 44369 | C57: 140.3 | D57: 138.45 | E57: =(D57/D56)-1 -> -0.005387931 | F57: 44369 | G57: 1497 | H57: 1483.8 | I57: =(H57/H56)-1 -> -0.0032914624 | J57: 44369 | K57: 2518.1 | L57: 2490.25 | M57: =(L57/L56)-1 -> -0.0095849822 | N57: 44369 | O57: 2080.441 | P57: 2054.366 | Q57: =(P57/P56)-1 -> -0.0051404831 | R57: 44369 | S57: 111.42 | T57: 111.23 | U57: =(T57/T56)-1 -> 0.0055598246 | V57: 44369 | W57: 15840.5 | X57: 15772.75 | Y57: =(X57/X56)-1 -> 0.0016670371 | AC57: HDFC Bank Ltd | AD57: =CORREL(I:I,E:E) -> 0.11139489 | AE57: =CORREL(I:I,I:I) -> 1 | AF57: =CORREL(I:I,M:M) -> 0.24553392 | AG57: =CORREL(I:I,Q:Q) -> 0.35801305 | AH57: =CORREL(I:I,U:U) -> 0.28272255 | AJ57: 0.18404791 | AK57: 0.22374869
B58: 44370 | C58: 139 | D58: 137.75 | E58: =(D58/D57)-1 -> -0.0050559769 | F58: 44370 | G58: 1490 | H58: 1485.5 | I58: =(H58/H57)-1 -> 0.001145707 | J58: 44370 | K58: 2495 | L58: 2480.5 | M58: =(L58/L57)-1 -> -0.0039152696 | N58: 44370 | O58: 2076.749 | P58: 2035.537 | Q58: =(P58/P57)-1 -> -0.0091653581 | R58: 44370 | S58: 112.05 | T58: 110.01 | U58: =(T58/T57)-1 -> -0.010968264 | V58: 44370 | W58: 15862.8 | X58: 15686.95 | Y58: =(X58/X57)-1 -> -0.0054397616 | AC58: HUL | AD58: =CORREL(M:M,E:E) -> 0.091194553 | AE58: =CORREL(M:M,I:I) -> 0.24553392 | AF58: =COVAR(M:M,M:M) -> 0.00015990365 | AG58: =CORREL(M:M,Q:Q) -> 0.21221237 | AH58: =CORREL(M:M,U:U) -> 0.067651121 | AJ58: 0.11139489 | AK58: 0.17825755
B59: 44371 | C59: 138.55 | D59: 137.65 | E59: =(D59/D58)-1 -> -0.00072595281 | F59: 44371 | G59: 1490 | H59: 1506.25 | I59: =(H59/H58)-1 -> 0.013968361 | J59: 44371 | K59: 2490 | L59: 2490.15 | M59: =(L59/L58)-1 -> 0.0038903447 | N59: 44371 | O59: 2036.922 | P59: 1987.68 | Q59: =(P59/P58)-1 -> -0.023510749 | R59: 44371 | S59: 110.5 | T59: 111.315 | U59: =(T59/T58)-1 -> 0.011862558 | V59: 44371 | W59: 15737.3 | X59: 15790.45 | Y59: =(X59/X58)-1 -> 0.0065978409 | AC59: Reliance Ind Ltd | AD59: =CORREL(Q:Q,E:E) -> 0.18404791 | AE59: =COVAR(Q:Q,I:I) -> 7.1267767e-05 | AF59: =CORREL(Q:Q,M:M) -> 0.21221237 | AG59: =CORREL(Q:Q,Q:Q) -> 1 | AH59: =CORREL(Q:Q,U:U) -> 0.37765077 | AJ59: 0.091194553 | AK59: 0.010347751
B60: 44372 | C60: 138.75 | D60: 135.85 | E60: =(D60/D59)-1 -> -0.013076644 | F60: 44372 | G60: 1511.1 | H60: 1515.1 | I60: =(H60/H59)-1 -> 0.0058755187 | J60: 44372 | K60: 2488 | L60: 2448.65 | M60: =(L60/L59)-1 -> -0.016665663 | N60: 44372 | O60: 1987.68 | P60: 1942.407 | Q60: =(P60/P59)-1 -> -0.022776805 | R60: 44372 | S60: 113.5 | T60: 116.525 | U60: =(T60/T59)-1 -> 0.046804114 | V60: 44372 | W60: 15839.35 | X60: 15860.35 | Y60: =(X60/X59)-1 -> 0.0044267263 | AC60: Tata Steel Ltd | AD60: =CORREL(U:U,E:E) -> 0.21813492 | AE60: =CORREL(U:U,I:I) -> 0.28272255 | AF60: =CORREL(U:U,M:M) -> 0.067651121 | AG60: =COVAR(U:U,Q:Q) -> 0.00011750687 | AH60: =CORREL(U:U,U:U) -> 1
B61: 44375 | C61: 137.4 | D61: 137.55 | E61: =(D61/D60)-1 -> 0.012513802 | F61: 44375 | G61: 1520 | H61: 1508.35 | I61: =(H61/H60)-1 -> -0.0044551515 | J61: 44375 | K61: 2450.1 | L61: 2460.2 | M61: =(L61/L60)-1 -> 0.0047168848 | N61: 44375 | O61: 1958.605 | P61: 1925.377 | Q61: =(P61/P60)-1 -> -0.0087674725 | R61: 44375 | S61: 117.4 | T61: 118.4 | U61: =(T61/T60)-1 -> 0.016090968 | V61: 44375 | W61: 15915.35 | X61: 15814.7 | Y61: =(X61/X60)-1 -> -0.0028782467
B62: 44376 | C62: 138.6 | D62: 137.95 | E62: =(D62/D61)-1 -> 0.0029080334 | F62: 44376 | G62: 1507 | H62: 1502.05 | I62: =(H62/H61)-1 -> -0.0041767494 | J62: 44376 | K62: 2455 | L62: 2492.55 | M62: =(L62/L61)-1 -> 0.013149337 | N62: 44376 | O62: 1928.608 | P62: 1927.039 | Q62: =(P62/P61)-1 -> 0.00086320757 | R62: 44376 | S62: 118.45 | T62: 117.255 | U62: =(T62/T61)-1 -> -0.0096706081 | V62: 44376 | W62: 15807.5 | X62: 15748.45 | Y62: =(X62/X61)-1 -> -0.0041891405
B63: 44377 | C63: 138.95 | D63: 136.6 | E63: =(D63/D62)-1 -> -0.0097861544 | F63: 44377 | G63: 1498 | H63: 1497.9 | I63: =(H63/H62)-1 -> -0.0027628907 | J63: 44377 | K63: 2492.55 | L63: 2471.3 | M63: =(L63/L62)-1 -> -0.0085254057 | N63: 44377 | O63: 1934.838 | P63: 1948.129 | Q63: =(P63/P62)-1 -> 0.010944252 | R63: 44377 | S63: 118.105 | T63: 116.66 | U63: =(T63/T62)-1 -> -0.0050744105 | V63: 44377 | W63: 15776.9 | X63: 15721.5 | Y63: =(X63/X62)-1 -> -0.0017112795 | AB63: Security | AC63: Returns | AD63: Weights | AE63: Weighted Returns | AF63: Risk(Std Dev) | AG63: Beta | AH63: Weighted Beta
B64: 44378 | C64: 136.7 | D64: 136.2 | E64: =(D64/D63)-1 -> -0.0029282577 | F64: 44378 | G64: 1502 | H64: 1486.75 | I64: =(H64/H63)-1 -> -0.0074437546 | J64: 44378 | K64: 2484 | L64: 2478 | M64: =(L64/L63)-1 -> 0.0027111237 | N64: 44378 | O64: 1954.913 | P64: 1936.407 | Q64: =(P64/P63)-1 -> -0.0060170553 | R64: 44378 | S64: 117.19 | T64: 116.355 | U64: =(T64/T63)-1 -> -0.0026144351 | V64: 44378 | W64: 15755.05 | X64: 15680 | Y64: =(X64/X63)-1 -> -0.0026396972 | AB64: Parag Milk Foods Ltd | AC64: =AVERAGE(E:E) -> 0.0012656678 | AD64: 0.3 | AE64: =AC64*AD64 -> 0.00037970034 | AF64: 0.029362422 | AG64: 0.93514347 | AH64: =AD64*AG64 -> 0.28054304
B65: 44379 | C65: 136.9 | D65: 137.95 | E65: =(D65/D64)-1 -> 0.012848752 | F65: 44379 | G65: 1485 | H65: 1480.4 | I65: =(H65/H64)-1 -> -0.004271061 | J65: 44379 | K65: 2478 | L65: 2487.3 | M65: =(L65/L64)-1 -> 0.0037530266 | N65: 44379 | O65: 1935.53 | P65: 1965.112 | Q65: =(P65/P64)-1 -> 0.014823846 | R65: 44379 | S65: 116.6 | T65: 113.6 | U65: =(T65/T64)-1 -> -0.023677539 | V65: 44379 | W65: 15705.85 | X65: 15722.2 | Y65: =(X65/X64)-1 -> 0.0026913265 | AB65: HDFC Bank Ltd | AC65: =AVERAGE(I:I) -> 5.8250538e-05 | AD65: 0.17825755 | AE65: =AC65*AD65 -> 1.0383599e-05 | AF65: 0.013721419 | AG65: 1.1132767 | AH65: =AD65*AG65 -> 0.19844998
B66: 44382 | C66: 138.85 | D66: 137.1 | E66: =(D66/D65)-1 -> -0.0061616528 | F66: 44382 | G66: 1489.95 | H66: 1495.45 | I66: =(H66/H65)-1 -> 0.010166171 | J66: 44382 | K66: 2499 | L66: 2499.05 | M66: =(L66/L65)-1 -> 0.0047239979 | N66: 44382 | O66: 1971.943 | P66: 1984.634 | Q66: =(P66/P65)-1 -> 0.0099342938 | R66: 44382 | S66: 114.6 | T66: 115.685 | U66: =(T66/T65)-1 -> 0.018353873 | V66: 44382 | W66: 15793.4 | X66: 15834.35 | Y66: =(X66/X65)-1 -> 0.0071332256 | AB66: Hindustan Unilever Ltd | AC66: =AVERAGE(M:M) -> 1.7995846e-06 | AD66: 0.010347751 | AE66: =AC66*AD66 -> 1.8621652e-08 | AF66: 0.012653866 | AG66: 0.61771585 | AH66: =AD66*AG66 -> 0.0063919696
B67: 44383 | C67: 137.7 | D67: 135.1 | E67: =(D67/D66)-1 -> -0.014587892 | F67: 44383 | G67: 1497 | H67: 1534.7 | I67: =(H67/H66)-1 -> 0.02624628 | J67: 44383 | K67: 2490 | L67: 2472.5 | M67: =(L67/L66)-1 -> -0.010624037 | N67: 44383 | O67: 1979.788 | P67: 1961.19 | Q67: =(P67/P66)-1 -> -0.011812757 | R67: 44383 | S67: 115.865 | T67: 116.725 | U67: =(T67/T66)-1 -> 0.0089899295 | V67: 44383 | W67: 15813.75 | X67: 15818.25 | Y67: =(X67/X66)-1 -> -0.0010167768 | AB67: Reliance Industries Ltd | AC67: =AVERAGE(Q:Q) -> 0.0007348725 | AD67: 0.22374869 | AE67: =AC67*AD67 -> 0.00016442676 | AF67: 0.014527247 | AG67: 1.1255285 | AH67: =AD67*AG67 -> 0.25183552
B68: 44384 | C68: 135.75 | D68: 134.5 | E68: =(D68/D67)-1 -> -0.0044411547 | F68: 44384 | G68: 1534 | H68: 1539.5 | I68: =(H68/H67)-1 -> 0.0031276471 | J68: 44384 | K68: 2458 | L68: 2481.65 | M68: =(L68/L67)-1 -> 0.0037007078 | N68: 44384 | O68: 1963.913 | P68: 1947.575 | Q68: =(P68/P67)-1 -> -0.0069422137 | R68: 44384 | S68: 116.795 | T68: 121.865 | U68: =(T68/T67)-1 -> 0.044035125 | V68: 44384 | W68: 15819.6 | X68: 15879.65 | Y68: =(X68/X67)-1 -> 0.0038815925 | AB68: Tata Steel Ltd | AC68: =AVERAGE(U:U) -> 0.0010307844 | AD68: 0.28764601 | AE68: =AC68*AD68 -> 0.000296501 | AF68: 0.021447547 | AG68: 1.356409 | AH68: =AD68*AG68 -> 0.39016563
B69: 44385 | C69: 134.5 | D69: 135.6 | E69: =(D69/D68)-1 -> 0.0081784387 | F69: 44385 | G69: 1525 | H69: 1520.45 | I69: =(H69/H68)-1 -> -0.012374147 | J69: 44385 | K69: 2462.2 | L69: 2447.55 | M69: =(L69/L68)-1 -> -0.013740858 | N69: 44385 | O69: 1953.944 | P69: 1931.469 | Q69: =(P69/P68)-1 -> -0.0082697714 | R69: 44385 | S69: 122.5 | T69: 118.975 | U69: =(T69/T68)-1 -> -0.023714766 | V69: 44385 | W69: 15855.4 | X69: 15727.9 | Y69: =(X69/X68)-1 -> -0.009556256 | AB69: Nifty 50 | AC69: =AVERAGE(Y:Y) -> 0.00058793455 | AF69: =STDEV(Y:Y) -> 0.0086608488
B70: 44386 | C70: 136 | D70: 135 | E70: =(D70/D69)-1 -> -0.0044247788 | F70: 44386 | G70: 1512.55 | H70: 1502 | I70: =(H70/H69)-1 -> -0.012134565 | J70: 44386 | K70: 2440 | L70: 2451.45 | M70: =(L70/L69)-1 -> 0.0015934302 | N70: 44386 | O70: 1927.223 | P70: 1911.717 | Q70: =(P70/P69)-1 -> -0.010226413 | R70: 44386 | S70: 119.2 | T70: 123.935 | U70: =(T70/T69)-1 -> 0.041689431 | V70: 44386 | W70: 15688.25 | X70: 15689.8 | Y70: =(X70/X69)-1 -> -0.0024224467
B71: 44389 | C71: 136.1 | D71: 136.15 | E71: =(D71/D70)-1 -> 0.0085185185 | F71: 44389 | G71: 1502 | H71: 1487 | I71: =(H71/H70)-1 -> -0.0099866844 | J71: 44389 | K71: 2453 | L71: 2444.15 | M71: =(L71/L70)-1 -> -0.0029778294 | N71: 44389 | O71: 1919.609 | P71: 1923.624 | Q71: =(P71/P70)-1 -> 0.0062284323 | R71: 44389 | S71: 125.1 | T71: 122.695 | U71: =(T71/T70)-1 -> -0.010005245 | V71: 44389 | W71: 15766.8 | X71: 15692.6 | Y71: =(X71/X70)-1 -> 0.00017845989 | AD71: PORTFOLIO PARAMETERS
B72: 44390 | C72: 137.3 | D72: 136.5 | E72: =(D72/D71)-1 -> 0.0025706941 | F72: 44390 | G72: 1496.1 | H72: 1501.85 | I72: =(H72/H71)-1 -> 0.0099865501 | J72: 44390 | K72: 2455 | L72: 2436.7 | M72: =(L72/L71)-1 -> -0.0030480944 | N72: 44390 | O72: 1938.299 | P72: 1938.022 | Q72: =(P72/P71)-1 -> 0.0074848307 | R72: 44390 | S72: 123.8 | T72: 122.875 | U72: =(T72/T71)-1 -> 0.0014670524 | V72: 44390 | W72: 15794 | X72: 15812.35 | Y72: =(X72/X71)-1 -> 0.0076309853 | AD72: Portfolio Returns | AE72: =sum(AE64:AE68) -> 0.00085103032 | AG72: Risk Free Rate | AH72: 0.0693
B73: 44391 | C73: 136.85 | D73: 140.6 | E73: =(D73/D72)-1 -> 0.03003663 | F73: 44391 | G73: 1497.5 | H73: 1499.15 | I73: =(H73/H72)-1 -> -0.0017977827 | J73: 44391 | K73: 2439.8 | L73: 2414.85 | M73: =(L73/L72)-1 -> -0.0089670456 | N73: 44391 | O73: 1938.622 | P73: 1925.377 | Q73: =(P73/P72)-1 -> -0.0065246937 | R73: 44391 | S73: 123.195 | T73: 124.47 | U73: =(T73/T72)-1 -> 0.012980671 | V73: 44391 | W73: 15808.7 | X73: 15853.95 | Y73: =(X73/X72)-1 -> 0.002630855 | AD73: Portfolio Beta | AE73: =sum(AH64:AH68) -> 1.1273861 | AG73: Daily Risk Free Rate | AH73: =AH72/252 -> 0.000275
B74: 44392 | C74: 143 | D74: 142.1 | E74: =(D74/D73)-1 -> 0.010668563 | F74: 44392 | G74: 1505 | H74: 1520.7 | I74: =(H74/H73)-1 -> 0.014374812 | J74: 44392 | K74: 2425 | L74: 2412.35 | M74: =(L74/L73)-1 -> -0.001035261 | N74: 44392 | O74: 1933.684 | P74: 1922.008 | Q74: =(P74/P73)-1 -> -0.0017497872 | R74: 44392 | S74: 124.61 | T74: 125.595 | U74: =(T74/T73)-1 -> 0.0090383225 | V74: 44392 | W74: 15872.15 | X74: 15924.2 | Y74: =(X74/X73)-1 -> 0.0044310724 | AD74: Portfolio Variance | AE74: {=MMULT(TRANSPOSE(AD64:AD68),MMULT(AE3:AI7,AD64:AD68))} -> 0.00020102373
B75: 44393 | C75: 142.55 | D75: 143.3 | E75: =(D75/D74)-1 -> 0.0084447572 | F75: 44393 | G75: 1527.95 | H75: 1522.35 | I75: =(H75/H74)-1 -> 0.0010850266 | J75: 44393 | K75: 2420 | L75: 2417.4 | M75: =(L75/L74)-1 -> 0.0020933944 | N75: 44393 | O75: 1926.993 | P75: 1949.745 | Q75: =(P75/P74)-1 -> 0.014431261 | R75: 44393 | S75: 126.47 | T75: 127.845 | U75: =(T75/T74)-1 -> 0.017914726 | V75: 44393 | W75: 15958.35 | X75: 15923.4 | Y75: =(X75/X74)-1 -> -5.0238003e-05 | AD75: Portfolio Std Dev | AE75: =SQRT(AE74) -> 0.014178284
B76: 44396 | C76: 141.8 | D76: 141.8 | E76: =(D76/D75)-1 -> -0.010467551 | F76: 44396 | G76: 1487 | H76: 1471 | I76: =(H76/H75)-1 -> -0.033730745 | J76: 44396 | K76: 2400.05 | L76: 2408.65 | M76: =(L76/L75)-1 -> -0.0036195913 | N76: 44396 | O76: 1938.299 | P76: 1937.33 | Q76: =(P76/P75)-1 -> -0.0063674993 | R76: 44396 | S76: 125.9 | T76: 126.64 | U76: =(T76/T75)-1 -> -0.0094254762 | V76: 44396 | W76: 15754.5 | X76: 15752.4 | Y76: =(X76/X75)-1 -> -0.010738913
B77: 44397 | C77: 141 | D77: 138.3 | E77: =(D77/D76)-1 -> -0.024682652 | F77: 44397 | G77: 1442 | H77: 1443.15 | I77: =(H77/H76)-1 -> -0.018932699 | J77: 44397 | K77: 2403 | L77: 2434.9 | M77: =(L77/L76)-1 -> 0.010898221 | N77: 44397 | O77: 1937.838 | P77: 1932.577 | Q77: =(P77/P76)-1 -> -0.0024533766 | R77: 44397 | S77: 127.2 | T77: 123.335 | U77: =(T77/T76)-1 -> -0.026097599 | V77: 44397 | W77: 15703.95 | X77: 15632.1 | Y77: =(X77/X76)-1 -> -0.0076369315
B78: 44399 | C78: 139.6 | D78: 142.45 | E78: =(D78/D77)-1 -> 0.030007231 | F78: 44399 | G78: 1456.1 | H78: 1448.7 | I78: =(H78/H77)-1 -> 0.0038457541 | J78: 44399 | K78: 2450 | L78: 2378.15 | M78: =(L78/L77)-1 -> -0.023306912 | N78: 44399 | O78: 1955.836 | P78: 1957.405 | Q78: =(P78/P77)-1 -> 0.012847095 | R78: 44399 | S78: 124.9 | T78: 127.3 | U78: =(T78/T77)-1 -> 0.032148214 | V78: 44399 | W78: 15736.6 | X78: 15824.05 | Y78: =(X78/X77)-1 -> 0.01227922 | AC78: Ratios | AD78: Portfolio | AE78: Market | AF78: Parag Milk Foods Limited
B79: 44400 | C79: 143.75 | D79: 138.7 | E79: =(D79/D78)-1 -> -0.026325026 | F79: 44400 | G79: 1451.5 | H79: 1442.75 | I79: =(H79/H78)-1 -> -0.0041071305 | J79: 44400 | K79: 2382 | L79: 2358.1 | M79: =(L79/L78)-1 -> -0.0084309232 | N79: 44400 | O79: 1970.097 | P79: 1943.56 | Q79: =(P79/P78)-1 -> -0.0070731402 | R79: 44400 | S79: 127.935 | T79: 128.14 | U79: =(T79/T78)-1 -> 0.006598586 | V79: 44400 | W79: 15856.8 | X79: 15856.05 | Y79: =(X79/X78)-1 -> 0.0020222383 | AC79: Sharpe Ratio | AD79: =(AE72-AH73)/AE75 -> 0.040627648 | AE79: 0.036132087 | AF79: 0.033739308
B80: 44403 | C80: 138 | D80: 137.65 | E80: =(D80/D79)-1 -> -0.0075702956 | F80: 44403 | G80: 1430 | H80: 1434.55 | I80: =(H80/H79)-1 -> -0.0056835904 | J80: 44403 | K80: 2357.25 | L80: 2348.7 | M80: =(L80/L79)-1 -> -0.0039862601 | N80: 44403 | O80: 1945.683 | P80: 1916.932 | Q80: =(P80/P79)-1 -> -0.013700632 | R80: 44403 | S80: 128.9 | T80: 129.795 | U80: =(T80/T79)-1 -> 0.012915561 | V80: 44403 | W80: 15849.3 | X80: 15824.45 | Y80: =(X80/X79)-1 -> -0.0019929301 | AC80: Treynor Ratio | AD80: =(AE72-AH73)/AE73 -> 0.00051094323 | AE80: 0.00031293455 | AF80: 0.0010593752
B81: 44404 | C81: 138.5 | D81: 135.8 | E81: =(D81/D80)-1 -> -0.013439884 | F81: 44404 | G81: 1436.1 | H81: 1439.75 | I81: =(H81/H80)-1 -> 0.0036248301 | J81: 44404 | K81: 2348.7 | L81: 2342.4 | M81: =(L81/L80)-1 -> -0.0026823349 | N81: 44404 | O81: 1916.886 | P81: 1896.764 | Q81: =(P81/P80)-1 -> -0.010520978 | R81: 44404 | S81: 131.5 | T81: 133.065 | U81: =(T81/T80)-1 -> 0.025193574 | V81: 44404 | W81: 15860.5 | X81: 15746.45 | Y81: =(X81/X80)-1 -> -0.0049290813
